Workbook

Sheet SCM KPI FY26 DASHBOARD
B2: PIONEER SCM KPI FY26 DASHBOARD | F2: NOV
H3: Operational Objectives Dashboard
B4: KPI | C4: Budget/Target | D4: Actual | E4: Status
B6: Conversion Cost (SC only) | C6: 11 | D6: {=INDEX('2026 KPI TRACKER'!$E$8:$P$8,MATCH('SCM KPI FY26 DASHBOARD'!F2,'2026 KPI TRACKER'!E4:P4,0))} -> 9.9039022 | E6: ● | H6: Production Reports
B7: Conversion Cost (Overall) | C7: 15 | D7: {=INDEX('2026 KPI TRACKER'!$E$9:$P$9,MATCH('SCM KPI FY26 DASHBOARD'!F2,'2026 KPI TRACKER'!E4:P4,0))} -> 15.555569 | E7: ●
B8: Volume Produced MT | C8: {=INDEX('2026 KPI TRACKER'!$E$12:$P$12,MATCH('SCM KPI FY26 DASHBOARD'!F2,'2026 KPI TRACKER'!E4:P4,0))} -> 1414.9244 | D8: {=INDEX('2026 KPI TRACKER'!$E$11:$P$11,MATCH('SCM KPI FY26 DASHBOARD'!F2,'2026 KPI TRACKER'!E4:P4,0))} -> 1603.4058 | E8: ● | H8: OUTPUT VS TARGET | M8: MACHINE UTLIZATION | R8: RMPM SAVINGS (M) | W8: FORECAST ACCURACY
B9: Fill Rate | C9: 0.99 | D9: {=INDEX('2026 KPI TRACKER'!$E$15:$P$15,MATCH('SCM KPI FY26 DASHBOARD'!F2,'2026 KPI TRACKER'!E4:P4,0))} -> 0.8076873 | E9: ● | H9: {=INDEX('2026 KPI TRACKER'!$E$37:$P$37,MATCH('SCM KPI FY26 DASHBOARD'!F2,'2026 KPI TRACKER'!E4:P4,0))} -> 1569.3354 | J9: MT | R9: {=INDEX('2026 KPI TRACKER'!$E$168:$P$168,MATCH('SCM KPI FY26 DASHBOARD'!F2,'2026 KPI TRACKER'!E4:P4,0))/1000} -> 2428.4741 | T9: Php | W9: {=INDEX('2026 KPI TRACKER'!$E$105:$P$105,MATCH('SCM KPI FY26 DASHBOARD'!F2,'2026 KPI TRACKER'!E4:P4,0))} -> 0.41602569 | Z9: LOCAL
B10: OTIF | C10: 0.7 | D10: {=INDEX('2026 KPI TRACKER'!$E$16:$P$16,MATCH('SCM KPI FY26 DASHBOARD'!F2,'2026 KPI TRACKER'!E4:P4,0))} -> NO VALUE | E10: ● | K10: {=INDEX('2026 KPI TRACKER'!$E$36:$P$36,MATCH('SCM KPI FY26 DASHBOARD'!F2,'2026 KPI TRACKER'!E4:P4,0))} -> 0.99412883 | M10: {=INDEX('2026 KPI TRACKER'!$E$50:$P$50,MATCH('SCM KPI FY26 DASHBOARD'!F2,'2026 KPI TRACKER'!E4:P4,0))} -> 1.2688208 | U10: {=INDEX('2026 KPI TRACKER'!$E$170:$P$170,MATCH('SCM KPI FY26 DASHBOARD'!F2,'2026 KPI TRACKER'!E4:P4,0))} -> 0.72854224 | Z10: {=INDEX('2026 KPI TRACKER'!$E$122:$P$122,MATCH('SCM KPI FY26 DASHBOARD'!F2,'2026 KPI TRACKER'!E4:P4,0))} -> 0.37709718
B11: Operational Cost | C11: {=INDEX('2026 KPI TRACKER'!$E$21:$P$21,MATCH('SCM KPI FY26 DASHBOARD'!F2,'2026 KPI TRACKER'!E4:P4,0))} -> 16210988 | D11: {=INDEX('2026 KPI TRACKER'!$E$20:$P$20,MATCH('SCM KPI FY26 DASHBOARD'!F2,'2026 KPI TRACKER'!E4:P4,0))} -> 15879974 | E11: ● | P11: {=INDEX('2026 KPI TRACKER'!$E$54:$P$54,MATCH('SCM KPI FY26 DASHBOARD'!F2,'2026 KPI TRACKER'!E4:P4,0))} -> 23.65 | Z11: EXPORT
B12: Capital Expenditures | C12: {=INDEX('2026 KPI TRACKER'!$E$25:$P$25,MATCH('SCM KPI FY26 DASHBOARD'!F2,'2026 KPI TRACKER'!E4:P4,0))} -> 1966800 | D12: {=INDEX('2026 KPI TRACKER'!$E$24:$P$24,MATCH('SCM KPI FY26 DASHBOARD'!F2,'2026 KPI TRACKER'!E4:P4,0))} -> 2033330 | E12: ● | H12: {=INDEX('2026 KPI TRACKER'!$E$38:$P$38,MATCH('SCM KPI FY26 DASHBOARD'!F2,'2026 KPI TRACKER'!E4:P4,0))} -> 1578.6036 | J12: MT | P12: days | R12: {=INDEX('2026 KPI TRACKER'!$E$169:$P$169,MATCH('SCM KPI FY26 DASHBOARD'!F2,'2026 KPI TRACKER'!E4:P4,0))/1000} -> 3333.3333 | T12: Php | Z12: {=INDEX('2026 KPI TRACKER'!$E$130:$P$130,MATCH('SCM KPI FY26 DASHBOARD'!F2,'2026 KPI TRACKER'!E4:P4,0))} -> 0.12195203
B13: Variance Analysis
B14: Efficiency Ratio
B15: Progress on Strategic Initiatives | H15: PRODUCTIVE TIME | M15: DOWNTIME | R15: Inventory Accuracy | W15: FORECAST ACCURACY
B16: Risk Assessment | R16: {=INDEX('2026 KPI TRACKER'!$E$90:$P$90,MATCH('SCM KPI FY26 DASHBOARD'!F2,'2026 KPI TRACKER'!E4:P4,0))} -> 0.98675497 | U16: FG | W16: ='2026 KPI TRACKER'!B106 -> EPOXY (MARINE + CONSTRUCTION) | Y16: {=INDEX('2026 KPI TRACKER'!$E106:$P106,MATCH('SCM KPI FY26 DASHBOARD'!$F$2,'2026 KPI TRACKER'!$E$4:$P$4,0))} -> 0.45772562
B17: Resource Allocation | H17: {=INDEX('2026 KPI TRACKER'!$E$49:$P$49,MATCH('SCM KPI FY26 DASHBOARD'!F2,'2026 KPI TRACKER'!E4:P4,0))} -> 0.21150467 | M17: {=INDEX('2026 KPI TRACKER'!$E$39:$P$39,MATCH('SCM KPI FY26 DASHBOARD'!F2,'2026 KPI TRACKER'!E4:P4,0))} -> #ERROR! | W17: ='2026 KPI TRACKER'!B107 -> ELASTOSEAL | Y17: {=INDEX('2026 KPI TRACKER'!$E107:$P107,MATCH('SCM KPI FY26 DASHBOARD'!$F$2,'2026 KPI TRACKER'!$E$4:$P$4,0))} -> 0.76971992
K18: {=INDEX('2026 KPI TRACKER'!$E$54:$P$54,MATCH('SCM KPI FY26 DASHBOARD'!F2,'2026 KPI TRACKER'!E4:P4,0))} -> 23.65 | P18: {=INDEX('2026 KPI TRACKER'!$E$54:$P$54,MATCH('SCM KPI FY26 DASHBOARD'!F2,'2026 KPI TRACKER'!E4:P4,0))} -> 23.65 | R18: {=INDEX('2026 KPI TRACKER'!$E$91:$P$91,MATCH('SCM KPI FY26 DASHBOARD'!F2,'2026 KPI TRACKER'!E4:P4,0))} -> 0.98717949 | U18: RMPM | W18: ='2026 KPI TRACKER'!B108 -> MIGHTY BOND | Y18: {=INDEX('2026 KPI TRACKER'!$E108:$P108,MATCH('SCM KPI FY26 DASHBOARD'!$F$2,'2026 KPI TRACKER'!$E$4:$P$4,0))} -> 0.66919905
B19: Financial Trend FY26 | K19: days | P19: days | W19: ='2026 KPI TRACKER'!B109 -> PRO-EPOXY | Y19: {=INDEX('2026 KPI TRACKER'!$E109:$P109,MATCH('SCM KPI FY26 DASHBOARD'!$F$2,'2026 KPI TRACKER'!$E$4:$P$4,0))} -> 0.64811092
R20: {=INDEX('2026 KPI TRACKER'!$E$92:$P$92,MATCH('SCM KPI FY26 DASHBOARD'!F2,'2026 KPI TRACKER'!E4:P4,0))} -> NO DATA | U20: PROD | W20: ='2026 KPI TRACKER'!B110 -> BUILDERS BOND | Y20: {=INDEX('2026 KPI TRACKER'!$E110:$P110,MATCH('SCM KPI FY26 DASHBOARD'!$F$2,'2026 KPI TRACKER'!$E$4:$P$4,0))} -> 0.48097973
W21: ='2026 KPI TRACKER'!B111 -> COATING MARINE | Y21: {=INDEX('2026 KPI TRACKER'!$E111:$P111,MATCH('SCM KPI FY26 DASHBOARD'!$F$2,'2026 KPI TRACKER'!$E$4:$P$4,0))} -> 0.41566339
H22: DOWNTIME BREAKDOWN | M22: LABOR REPORTS | W22: ='2026 KPI TRACKER'!B112 -> TRASPORTATION | Y22: {=INDEX('2026 KPI TRACKER'!$E112:$P112,MATCH('SCM KPI FY26 DASHBOARD'!$F$2,'2026 KPI TRACKER'!$E$4:$P$4,0))} -> 0.27658279
H23: =Sheet1!G10 -> Idle time | K23: {=INDEX('2026 KPI TRACKER'!$E47:$P47,MATCH('SCM KPI FY26 DASHBOARD'!$F$2,'2026 KPI TRACKER'!$E$4:$P$4,0))} -> 0.0060530939 | M23: {=INDEX('2026 KPI TRACKER'!$E$137:$P$137,MATCH('SCM KPI FY26 DASHBOARD'!F2,'2026 KPI TRACKER'!E4:P4,0))} -> 36117.1 | O23: Reg hrs | R23: Warehouse Utlization | W23: ='2026 KPI TRACKER'!B113 -> OTHER CONSUMER | Y23: {=INDEX('2026 KPI TRACKER'!$E113:$P113,MATCH('SCM KPI FY26 DASHBOARD'!$F$2,'2026 KPI TRACKER'!$E$4:$P$4,0))} -> 0.0065382981
H24: =Sheet1!G3 -> Change Over Time | K24: {=INDEX('2026 KPI TRACKER'!$E40:$P40,MATCH('SCM KPI FY26 DASHBOARD'!$F$2,'2026 KPI TRACKER'!$E$4:$P$4,0))} -> 0.021621366 | P24: {=INDEX('2026 KPI TRACKER'!$E$139:$P$139,MATCH('SCM KPI FY26 DASHBOARD'!F2,'2026 KPI TRACKER'!E4:P4,0))} -> 0.32690886 | R24: {=INDEX('2026 KPI TRACKER'!$E$95:$P$95,MATCH('SCM KPI FY26 DASHBOARD'!F2,'2026 KPI TRACKER'!E4:P4,0))} -> 0.90973202 | W24: ='2026 KPI TRACKER'!B114 -> PRO-SEALANT | Y24: {=INDEX('2026 KPI TRACKER'!$E114:$P114,MATCH('SCM KPI FY26 DASHBOARD'!$F$2,'2026 KPI TRACKER'!$E$4:$P$4,0))} -> 0.50318328
H25: =Sheet1!G6 -> Start-up Time/Setup | K25: {=INDEX('2026 KPI TRACKER'!$E43:$P43,MATCH('SCM KPI FY26 DASHBOARD'!$F$2,'2026 KPI TRACKER'!$E$4:$P$4,0))} -> 0.020867854 | U25: FG | W25: ='2026 KPI TRACKER'!B115 -> PRO-WATERPROOFING | Y25: {=INDEX('2026 KPI TRACKER'!$E115:$P115,MATCH('SCM KPI FY26 DASHBOARD'!$F$2,'2026 KPI TRACKER'!$E$4:$P$4,0))} -> 0.535723
H26: =Sheet1!G8 -> Breaktime | K26: {=INDEX('2026 KPI TRACKER'!$E45:$P45,MATCH('SCM KPI FY26 DASHBOARD'!$F$2,'2026 KPI TRACKER'!$E$4:$P$4,0))} -> 0.019459878 | M26: {=INDEX('2026 KPI TRACKER'!$E$138:$P$138,MATCH('SCM KPI FY26 DASHBOARD'!F2,'2026 KPI TRACKER'!E4:P4,0))} -> 11807 | O26: OT hrs | W26: ='2026 KPI TRACKER'!B116 -> PRO-PAINTING | Y26: {=INDEX('2026 KPI TRACKER'!$E116:$P116,MATCH('SCM KPI FY26 DASHBOARD'!$F$2,'2026 KPI TRACKER'!$E$4:$P$4,0))} -> 0.69714382
H27: =Sheet1!G5 -> Sanitation Time | K27: {=INDEX('2026 KPI TRACKER'!$E42:$P42,MATCH('SCM KPI FY26 DASHBOARD'!$F$2,'2026 KPI TRACKER'!$E$4:$P$4,0))} -> 0.010041897 | R27: {=INDEX('2026 KPI TRACKER'!$E$96:$P$96,MATCH('SCM KPI FY26 DASHBOARD'!F2,'2026 KPI TRACKER'!E4:P4,0))} -> 1.2604273 | W27: ='2026 KPI TRACKER'!B117 -> PRO-ADHESIVES | Y27: {=INDEX('2026 KPI TRACKER'!$E117:$P117,MATCH('SCM KPI FY26 DASHBOARD'!$F$2,'2026 KPI TRACKER'!$E$4:$P$4,0))} -> 0.20556193
H28: =Sheet1!G4 -> Meeting | K28: {=INDEX('2026 KPI TRACKER'!$E41:$P41,MATCH('SCM KPI FY26 DASHBOARD'!$F$2,'2026 KPI TRACKER'!$E$4:$P$4,0))} -> 0.0015625665 | M28: LABOR REPORTS (Direct Labor) | U28: RMPM | W28: ='2026 KPI TRACKER'!B118 -> MINING | Y28: {=INDEX('2026 KPI TRACKER'!$E118:$P118,MATCH('SCM KPI FY26 DASHBOARD'!$F$2,'2026 KPI TRACKER'!$E$4:$P$4,0))} -> 0.15822785
H29: =Sheet1!G9 -> Breakdown | K29: {=INDEX('2026 KPI TRACKER'!$E46:$P46,MATCH('SCM KPI FY26 DASHBOARD'!$F$2,'2026 KPI TRACKER'!$E$4:$P$4,0))} -> 3.1473497e-05 | M29: {=INDEX('2026 KPI TRACKER'!$E$140:$P$140,MATCH('SCM KPI FY26 DASHBOARD'!F2,'2026 KPI TRACKER'!E4:P4,0))} -> 29807.03 | O29: OT hrs | W29: ='2026 KPI TRACKER'!B119 -> OTHERS | Y29: {=INDEX('2026 KPI TRACKER'!$E119:$P119,MATCH('SCM KPI FY26 DASHBOARD'!$F$2,'2026 KPI TRACKER'!$E$4:$P$4,0))} -> 0
H30: =Sheet1!G7 -> Testing Time | K30: {=INDEX('2026 KPI TRACKER'!$E44:$P44,MATCH('SCM KPI FY26 DASHBOARD'!$F$2,'2026 KPI TRACKER'!$E$4:$P$4,0))} -> 0.009783629 | P30: {=INDEX('2026 KPI TRACKER'!$E$142:$P$142,MATCH('SCM KPI FY26 DASHBOARD'!F2,'2026 KPI TRACKER'!E4:P4,0))} -> 0.33782299
H31: =Sheet1!G11 -> Preventive Maintenance | K31: {=INDEX('2026 KPI TRACKER'!$E48:$P48,MATCH('SCM KPI FY26 DASHBOARD'!$F$2,'2026 KPI TRACKER'!$E$4:$P$4,0))} -> #ERROR! | W31: FORECAST ACCURACY
M32: {=INDEX('2026 KPI TRACKER'!$E$141:$P$141,MATCH('SCM KPI FY26 DASHBOARD'!F2,'2026 KPI TRACKER'!E4:P4,0))} -> 10069.5 | O32: Reg hrs | W32: ='2026 KPI TRACKER'!B122 -> LOCAL PHILIPPINES | Y32: {=INDEX('2026 KPI TRACKER'!$E122:$P122,MATCH('SCM KPI FY26 DASHBOARD'!$F$2,'2026 KPI TRACKER'!$E$4:$P$4,0))} -> 0.37709718
H33: ABSENTEEISM | W33: ='2026 KPI TRACKER'!B123 -> GMA | Y33: {=INDEX('2026 KPI TRACKER'!$E123:$P123,MATCH('SCM KPI FY26 DASHBOARD'!$F$2,'2026 KPI TRACKER'!$E$4:$P$4,0))} -> 0.37469668
H34: {=INDEX('2026 KPI TRACKER'!$E$147:$P$147,MATCH('SCM KPI FY26 DASHBOARD'!F2,'2026 KPI TRACKER'!E4:P4,0))} -> 0.12107349 | K34: {=INDEX('2026 KPI TRACKER'!$E$150:$P$150,MATCH('SCM KPI FY26 DASHBOARD'!F2,'2026 KPI TRACKER'!E4:P4,0))} -> 23.65 | M34: LABOR REPORTS (Indirect Labor) | W34: ='2026 KPI TRACKER'!B124 -> NORTH LUZON | Y34: {=INDEX('2026 KPI TRACKER'!$E124:$P124,MATCH('SCM KPI FY26 DASHBOARD'!$F$2,'2026 KPI TRACKER'!$E$4:$P$4,0))} -> 0.49527923
K35: days | M35: {=INDEX('2026 KPI TRACKER'!$E$143:$P$143,MATCH('SCM KPI FY26 DASHBOARD'!F2,'2026 KPI TRACKER'!E4:P4,0))} -> 6310.07 | O35: OT hrs | W35: ='2026 KPI TRACKER'!B125 -> SOUTH LUZON | Y35: {=INDEX('2026 KPI TRACKER'!$E125:$P125,MATCH('SCM KPI FY26 DASHBOARD'!$F$2,'2026 KPI TRACKER'!$E$4:$P$4,0))} -> 0.39307041
J36: {=INDEX('2026 KPI TRACKER'!$E$148:$P$148,MATCH('SCM KPI FY26 DASHBOARD'!F2,'2026 KPI TRACKER'!E4:P4,0))} -> 183 | P36: {=INDEX('2026 KPI TRACKER'!$E$145:$P$145,MATCH('SCM KPI FY26 DASHBOARD'!F2,'2026 KPI TRACKER'!E4:P4,0))} -> 0.27535352 | W36: ='2026 KPI TRACKER'!B126 -> VISAYAS | Y36: {=INDEX('2026 KPI TRACKER'!$E126:$P126,MATCH('SCM KPI FY26 DASHBOARD'!$F$2,'2026 KPI TRACKER'!$E$4:$P$4,0))} -> 0.38475153
H37: {=INDEX('2026 KPI TRACKER'!$E$149:$P$149,MATCH('SCM KPI FY26 DASHBOARD'!F2,'2026 KPI TRACKER'!E4:P4,0))} -> 524 | I37: Absences | W37: ='2026 KPI TRACKER'!B127 -> MINDANAO | Y37: {=INDEX('2026 KPI TRACKER'!$E127:$P127,MATCH('SCM KPI FY26 DASHBOARD'!$F$2,'2026 KPI TRACKER'!$E$4:$P$4,0))} -> 0.29967189
J38: Manpower | M38: {=INDEX('2026 KPI TRACKER'!$E$144:$P$144,MATCH('SCM KPI FY26 DASHBOARD'!F2,'2026 KPI TRACKER'!E4:P4,0))} -> 1737.5 | O38: Reg hrs | W38: ='2026 KPI TRACKER'!B128 -> MODERN TRADE | Y38: {=INDEX('2026 KPI TRACKER'!$E128:$P128,MATCH('SCM KPI FY26 DASHBOARD'!$F$2,'2026 KPI TRACKER'!$E$4:$P$4,0))} -> 0.69221053
W39: ='2026 KPI TRACKER'!B129 -> PSBSI | Y39: {=INDEX('2026 KPI TRACKER'!$E129:$P129,MATCH('SCM KPI FY26 DASHBOARD'!$F$2,'2026 KPI TRACKER'!$E$4:$P$4,0))} -> 0
H40: ABSENTEEISM | W40: ='2026 KPI TRACKER'!B130 -> EXPORT | Y40: {=INDEX('2026 KPI TRACKER'!$E130:$P130,MATCH('SCM KPI FY26 DASHBOARD'!$F$2,'2026 KPI TRACKER'!$E$4:$P$4,0))} -> 0.12195203
H41: ='2026 KPI TRACKER'!B151 -> L06 - EPOXY | J41: {=INDEX('2026 KPI TRACKER'!$E151:$P151,MATCH('SCM KPI FY26 DASHBOARD'!$F$2,'2026 KPI TRACKER'!$E$4:$P$4,0))} -> 0.11250378 | W41: ='2026 KPI TRACKER'!B131 -> INDONESIA | Y41: {=INDEX('2026 KPI TRACKER'!$E131:$P131,MATCH('SCM KPI FY26 DASHBOARD'!$F$2,'2026 KPI TRACKER'!$E$4:$P$4,0))} -> 0.31872979
H42: ='2026 KPI TRACKER'!B152 -> L04B - ELASTO | J42: {=INDEX('2026 KPI TRACKER'!$E152:$P152,MATCH('SCM KPI FY26 DASHBOARD'!$F$2,'2026 KPI TRACKER'!$E$4:$P$4,0))} -> 0.15070201 | W42: ='2026 KPI TRACKER'!B132 -> INDIA | Y42: {=INDEX('2026 KPI TRACKER'!$E132:$P132,MATCH('SCM KPI FY26 DASHBOARD'!$F$2,'2026 KPI TRACKER'!$E$4:$P$4,0))} -> 0
H43: ='2026 KPI TRACKER'!B153 -> L03 - CYANO TUBE | J43: {=INDEX('2026 KPI TRACKER'!$E153:$P153,MATCH('SCM KPI FY26 DASHBOARD'!$F$2,'2026 KPI TRACKER'!$E$4:$P$4,0))} -> 0.29598309 | W43: ='2026 KPI TRACKER'!B133 -> DIRECT EXPORT | Y43: {=INDEX('2026 KPI TRACKER'!$E133:$P133,MATCH('SCM KPI FY26 DASHBOARD'!$F$2,'2026 KPI TRACKER'!$E$4:$P$4,0))} -> 0.047126287
H44: ='2026 KPI TRACKER'!B154 -> L01 - COATINGS | J44: {=INDEX('2026 KPI TRACKER'!$E154:$P154,MATCH('SCM KPI FY26 DASHBOARD'!$F$2,'2026 KPI TRACKER'!$E$4:$P$4,0))} -> 0.062181321
H45: ='2026 KPI TRACKER'!B155 -> L07 - EPOXY TUBE | J45: {=INDEX('2026 KPI TRACKER'!$E155:$P155,MATCH('SCM KPI FY26 DASHBOARD'!$F$2,'2026 KPI TRACKER'!$E$4:$P$4,0))} -> 0.073995772
H46: ='2026 KPI TRACKER'!B156 -> LINE 9 - EPS | J46: {=INDEX('2026 KPI TRACKER'!$E156:$P156,MATCH('SCM KPI FY26 DASHBOARD'!$F$2,'2026 KPI TRACKER'!$E$4:$P$4,0))} -> 0.16913319
H47: ='2026 KPI TRACKER'!B157 -> L10 - CONTACT BOND | J47: {=INDEX('2026 KPI TRACKER'!$E157:$P157,MATCH('SCM KPI FY26 DASHBOARD'!$F$2,'2026 KPI TRACKER'!$E$4:$P$4,0))} -> 0.33826638
H48: ='2026 KPI TRACKER'!B158 -> GIP L11 - SILICONE | J48: {=INDEX('2026 KPI TRACKER'!$E158:$P158,MATCH('SCM KPI FY26 DASHBOARD'!$F$2,'2026 KPI TRACKER'!$E$4:$P$4,0))} -> 0.063424947
H49: ='2026 KPI TRACKER'!B159 -> L12 - SPECIAL - EPOXY BASED | J49: {=INDEX('2026 KPI TRACKER'!$E159:$P159,MATCH('SCM KPI FY26 DASHBOARD'!$F$2,'2026 KPI TRACKER'!$E$4:$P$4,0))} -> 0.11476895
H50: ='2026 KPI TRACKER'!B160 -> L13 - SPECIAL | J50: {=INDEX('2026 KPI TRACKER'!$E160:$P160,MATCH('SCM KPI FY26 DASHBOARD'!$F$2,'2026 KPI TRACKER'!$E$4:$P$4,0))} -> 0.19027484
H51: ='2026 KPI TRACKER'!B161 -> LINE 14 | J51: {=INDEX('2026 KPI TRACKER'!$E161:$P161,MATCH('SCM KPI FY26 DASHBOARD'!$F$2,'2026 KPI TRACKER'!$E$4:$P$4,0))} -> 0.067653277
H52: ='2026 KPI TRACKER'!B162 -> L02 - CYNO BOTTLE / L05- EPOXY CLAY | J52: {=INDEX('2026 KPI TRACKER'!$E162:$P162,MATCH('SCM KPI FY26 DASHBOARD'!$F$2,'2026 KPI TRACKER'!$E$4:$P$4,0))} -> 0.021141649
H53: ='2026 KPI TRACKER'!B163 -> LABELING LINE | J53: {=INDEX('2026 KPI TRACKER'!$E163:$P163,MATCH('SCM KPI FY26 DASHBOARD'!$F$2,'2026 KPI TRACKER'!$E$4:$P$4,0))} -> 0.162869

Sheet 2026 KPI TRACKER
A1: PIONEER
A2: 2026 KPI TRACKER
B4: KPI | C4: UoM | D4: 2026 TARGET | E4: OCT | F4: NOV | G4: DEC | H4: JAN | I4: FEB | J4: MAR | K4: APR | L4: MAY | M4: JUN | N4: JUL | O4: AUG | P4: SEP | Q4: 2026 ACTUAL
A5: BUSINESS GOALS:
A6: =MAX($A$5:A5)+1 -> 1 | B6: FINANCIALS
B7: Conversion Cost
B8: Conversion Cost (SC only) | C8: PHP/KG | D8: ='FINANCE DEPT'!G6 -> 11 | E8: ='FINANCE DEPT'!I6 -> 10.929592 | F8: ='FINANCE DEPT'!J6 -> 9.9039022 | G8: ='FINANCE DEPT'!K6 -> 14.391261 | H8: ='FINANCE DEPT'!L6 -> 9.9342105 | I8: ='FINANCE DEPT'!M6 | J8: ='FINANCE DEPT'!N6 | K8: ='FINANCE DEPT'!O6 | L8: ='FINANCE DEPT'!P6 | ... P8: ='FINANCE DEPT'!T6
B9: ='FINANCE DEPT'!B7 -> Conversion Cost (Overall) | C9: PHP/KG | D9: ='FINANCE DEPT'!G7 -> 15 | E9: ='FINANCE DEPT'!I7 -> 18.577245 | F9: ='FINANCE DEPT'!J7 -> 15.555569 | G9: ='FINANCE DEPT'!K7 -> 23.639818 | H9: ='FINANCE DEPT'!L7 -> 15.056688 | I9: ='FINANCE DEPT'!M7 | J9: ='FINANCE DEPT'!N7 | K9: ='FINANCE DEPT'!O7 | L9: ='FINANCE DEPT'!P7 | ... P9: ='FINANCE DEPT'!T7
B10: Conversion Cost (SC only) vs Target | C10: % | E10: =IFERROR(E8/D8,0) -> 0.99359929 | F10: =IFERROR(F8/#REF!,0) -> 0 | G10: =IFERROR(G8/E8,0) -> 1.3167244 | H10: =IFERROR(H8/F8,0) -> 1.0030602 | I10: =IFERROR(I8/G8,0) -> 0 | J10: =IFERROR(J8/H8,0) -> 0 | K10: =IFERROR(K8/I8,0) -> 0 | L10: =IFERROR(L8/J8,0) -> 0 | M10: =IFERROR(M8/K8,0) -> 0 | N10: =IFERROR(N8/L8,0) -> 0 | ... P10: =IFERROR(P8/N8,0) -> 0
B11: Volume produced (MT) Actual | C11: MT | D11: ='FINANCE DEPT'!G8 -> 5574.716 | E11: ='FINANCE DEPT'!I8 -> 1235.0772 | F11: ='FINANCE DEPT'!J8 -> 1603.4058 | G11: ='FINANCE DEPT'!K8 -> 1115.1986 | H11: ='FINANCE DEPT'!L8 -> 1621.0345 | I11: ='FINANCE DEPT'!M8 | J11: ='FINANCE DEPT'!N8 | K11: ='FINANCE DEPT'!O8 | L11: ='FINANCE DEPT'!P8 | ... Q11: ='FINANCE DEPT'!U8 -> 5574.716
B12: Volume produced (MT) Target | C12: MT | D12: ='FINANCE DEPT'!G9 -> 18814 | E12: ='FINANCE DEPT'!I9 -> 1221.8656 | F12: ='FINANCE DEPT'!J9 -> 1414.9244 | G12: ='FINANCE DEPT'!K9 -> 1090.6968 | H12: ='FINANCE DEPT'!L9 -> 1561.4227 | I12: ='FINANCE DEPT'!M9 | J12: ='FINANCE DEPT'!N9 | K12: ='FINANCE DEPT'!O9 | L12: ='FINANCE DEPT'!P9 | ... Q12: ='FINANCE DEPT'!U9 -> 5288.9096
B13: Volume produced % | C13: % | D13: ='FINANCE DEPT'!G10 -> 0.29630679 | E13: ='FINANCE DEPT'!I10 -> 1.0108127 | F13: ='FINANCE DEPT'!J10 -> 1.1332095 | G13: ='FINANCE DEPT'!K10 -> 1.0224643 | H13: ='FINANCE DEPT'!L10 -> 1.0381779 | I13: ='FINANCE DEPT'!M10 | J13: ='FINANCE DEPT'!N10 | K13: ='FINANCE DEPT'!O10 | L13: ='FINANCE DEPT'!P10 | ... Q13: ='FINANCE DEPT'!U10 -> 1.0540388
A14: =MAX($A$5:A6)+1 -> 2 | B14: FILL RATE
B15: Achievement (Value) | C15: % | D15: 0.99 | E15: ='WHSE & LOGS'!G22 -> 0.59877975 | F15: ='WHSE & LOGS'!H22 -> 0.8076873 | G15: ='WHSE & LOGS'!I22 -> 0.87977398 | H15: ='WHSE & LOGS'!J22 -> 0.98941 | I15: ='WHSE & LOGS'!K22 -> 0 | J15: ='WHSE & LOGS'!L22 -> 0 | K15: ='WHSE & LOGS'!M22 -> 0 | L15: ='WHSE & LOGS'!N22 -> 0 | ... Q15: ='WHSE & LOGS'!S22 -> 0.83972508
A16: =MAX($A$5:A15)+1 -> 3 | B16: OTIF | E16: NO VALUE | F16: NO VALUE
B17: OTIF Rate | C17: % | D17: 0.7 | E17: ='WHSE & LOGS'!G11 -> 0 | F17: ='WHSE & LOGS'!H11 -> 0 | G17: ='WHSE & LOGS'!I11 -> 0 | H17: ='WHSE & LOGS'!J11 -> 0 | I17: ='WHSE & LOGS'!K11 -> 0 | J17: ='WHSE & LOGS'!L11 -> 0 | K17: ='WHSE & LOGS'!M11 -> 0 | L17: ='WHSE & LOGS'!N11 -> 0 | ... Q17: ='WHSE & LOGS'!S11 -> 0
A18: =MAX($A$5:A17)+1 -> 4 | B18: FINANCIALS
B19: Operational Cost
B20: Actual | E20: ='FINANCE DEPT'!I14 -> 13498890 | F20: ='FINANCE DEPT'!J14 -> 15879974
B21: Budget | E21: ='FINANCE DEPT'!I15 -> 16189431 | F21: ='FINANCE DEPT'!J15 -> 16210988
B22: Operational Cost % | E22: ='FINANCE DEPT'!I16 -> 0.8338088 | F22: ='FINANCE DEPT'!J16 -> 0.97958091
B23: Capital Expenditures
B24: Actual | E24: ='FINANCE DEPT'!I19 -> 2042360 | F24: ='FINANCE DEPT'!J19 -> 2033330
B25: Budget | E25: ='FINANCE DEPT'!I20 -> 1946800 | F25: ='FINANCE DEPT'!J20 -> 1966800
B26: Capital Expenditure % | E26: ='FINANCE DEPT'!I21 -> 1.0490857 | F26: ='FINANCE DEPT'!J21 -> 1.0338265
B27: Variance Analysis
B28: Efficiency Ratio
A29: 5 | B29: Project Status
B30: Progress on Strategic Initiatives
B31: Risk Assessment
B32: Resource Allocation
A34: OPERATIONAL OBJECTIVES
A35: =MAX($A$34:A34)+1 -> 1 | B35: Production Reports
B36: Output vs Target (planned) | C36: % | D36: 0.9 | E36: =PRODUCTION!G1255 -> 0.73483834 | F36: =PRODUCTION!H1255 -> 0.99412883 | G36: =PRODUCTION!I1255 -> 0.88294392 | H36: =PRODUCTION!J1255 -> 0.86916136 | I36: =PRODUCTION!K1255 -> 0 | J36: =PRODUCTION!L1255 -> 0 | K36: =PRODUCTION!M1255 -> 0 | L36: =PRODUCTION!N1255 -> 0 | ... Q36: =PRODUCTION!S1255 -> 0.86881847
B37: Output Actual | C37: MT | E37: =PRODUCTION!G1253/1000 -> 1185.1593 | F37: =PRODUCTION!H1253/1000 -> 1569.3354 | G37: =PRODUCTION!I1253/1000 -> 1103.3091 | H37: =PRODUCTION!J1253/1000 -> 1569.1495 | I37: =PRODUCTION!K1253/1000 -> 0 | J37: =PRODUCTION!L1253/1000 -> 0 | K37: =PRODUCTION!M1253/1000 -> 0 | L37: =PRODUCTION!N1253/1000 -> 0 | ... Q37: =PRODUCTION!S1253/1000 -> 5426.9533
B38: Output Target | C38: MT | E38: =PRODUCTION!G1254/1000 -> 1612.8164 | F38: =PRODUCTION!H1254/1000 -> 1578.6036 | G38: =PRODUCTION!I1254/1000 -> 1249.58 | H38: =PRODUCTION!J1254/1000 -> 1805.3604 | I38: =PRODUCTION!K1254/1000 -> 0 | J38: =PRODUCTION!L1254/1000 -> 0 | K38: =PRODUCTION!M1254/1000 -> 0 | L38: =PRODUCTION!N1254/1000 -> 0 | ... Q38: =PRODUCTION!S1254/1000 -> 6246.3604
B39: Downtime Analysis | C39: % | E39: =SUM(E40:E48) -> #ERROR! | F39: =SUM(F40:F48) -> #ERROR! | G39: =SUM(G40:G48) -> #ERROR! | H39: =SUM(H40:H48) -> #ERROR! | I39: =SUM(I40:I48) -> #ERROR! | J39: =SUM(J40:J48) -> #ERROR! | K39: =SUM(K40:K48) -> #ERROR! | L39: =SUM(L40:L48) -> #ERROR! | ... Q39: =SUM(Q40:Q48) -> #ERROR!
B40: Change Over Time | C40: % | E40: =PRODUCTION!G37 -> 0.016065308 | F40: =PRODUCTION!H37 -> 0.021621366 | G40: =PRODUCTION!I37 -> 0.018904734 | H40: =PRODUCTION!J37 -> 0 | I40: =PRODUCTION!K37 -> 0 | J40: =PRODUCTION!L37 -> 0 | K40: =PRODUCTION!M37 -> 0 | L40: =PRODUCTION!N37 -> 0 | ... Q40: =PRODUCTION!S37 -> 0.018838528
B41: Meeting | C41: % | E41: =PRODUCTION!G38 -> 0.0015941701 | F41: =PRODUCTION!H38 -> 0.0015625665 | G41: =PRODUCTION!I38 -> 0.00064686857 | H41: =PRODUCTION!J38 -> 0 | I41: =PRODUCTION!K38 -> 0 | J41: =PRODUCTION!L38 -> 0 | K41: =PRODUCTION!M38 -> 0 | L41: =PRODUCTION!N38 -> 0 | ... Q41: =PRODUCTION!S38 -> 0.0013569949
B42: Sanitation Time | C42: % | E42: =PRODUCTION!G39 -> 0.0086488727 | F42: =PRODUCTION!H39 -> 0.010041897 | G42: =PRODUCTION!I39 -> 0.0063745957 | H42: =PRODUCTION!J39 -> 0 | I42: =PRODUCTION!K39 -> 0 | J42: =PRODUCTION!L39 -> 0 | K42: =PRODUCTION!M39 -> 0 | L42: =PRODUCTION!N39 -> 0 | ... Q42: =PRODUCTION!S39 -> 0.0086341508
B43: Start-up Time/Setup | C43: % | E43: =PRODUCTION!G40 -> 0.016721517 | F43: =PRODUCTION!H40 -> 0.020867854 | G43: =PRODUCTION!I40 -> 0.011259924 | H43: =PRODUCTION!J40 -> 0 | I43: =PRODUCTION!K40 -> 0 | J43: =PRODUCTION!L40 -> 0 | K43: =PRODUCTION!M40 -> 0 | L43: =PRODUCTION!N40 -> 0 | ... Q43: =PRODUCTION!S40 -> 0.016988653
B44: Testing Time | C44: % | E44: =PRODUCTION!G42 -> 0.0064403018 | F44: =PRODUCTION!H42 -> 0.009783629 | G44: =PRODUCTION!I42 -> 0.00074095854 | H44: =PRODUCTION!J42 -> 0 | I44: =PRODUCTION!K42 -> 0 | J44: =PRODUCTION!L42 -> 0 | K44: =PRODUCTION!M42 -> 0 | L44: =PRODUCTION!N42 -> 0 | ... Q44: =PRODUCTION!S42 -> 0.0063476738
B45: Breaktime | C45: % | E45: =PRODUCTION!G43 -> 0.015072815 | F45: =PRODUCTION!H43 -> 0.019459878 | G45: =PRODUCTION!I43 -> 0.017153778 | H45: =PRODUCTION!J43 -> 0 | I45: =PRODUCTION!K43 -> 0 | J45: =PRODUCTION!L43 -> 0 | K45: =PRODUCTION!M43 -> 0 | L45: =PRODUCTION!N43 -> 0 | ... Q45: =PRODUCTION!S43 -> 0.017224257
B46: Breakdown | C46: % | E46: =PRODUCTION!G46 -> 1.3633154e-05 | F46: =PRODUCTION!H46 -> 3.1473497e-05 | G46: =PRODUCTION!I46 -> 8.820935e-05 | H46: =PRODUCTION!J46 -> 0 | I46: =PRODUCTION!K46 -> 0 | J46: =PRODUCTION!L46 -> 0 | K46: =PRODUCTION!M46 -> 0 | L46: =PRODUCTION!N46 -> 0 | ... Q46: =PRODUCTION!S46 -> 3.8102123e-05
B47: Idle time | C47: % | E47: =PRODUCTION!G56 -> 0.0044971229 | F47: =PRODUCTION!H56 -> 0.0060530939 | G47: =PRODUCTION!I56 -> 0.0049470744 | H47: =PRODUCTION!J56 -> 0 | I47: =PRODUCTION!K56 -> 0 | J47: =PRODUCTION!L56 -> 0 | K47: =PRODUCTION!M56 -> 0 | L47: =PRODUCTION!N56 -> 0 | ... Q47: =PRODUCTION!S56 -> 0.0051916764
B48: Preventive Maintenance | C48: % | E48: =PRODUCTION!#REF! -> #ERROR! | F48: =PRODUCTION!#REF! -> #ERROR! | G48: =PRODUCTION!#REF! -> #ERROR! | H48: =PRODUCTION!#REF! -> #ERROR! | I48: =PRODUCTION!#REF! -> #ERROR! | J48: =PRODUCTION!#REF! -> #ERROR! | K48: =PRODUCTION!#REF! -> #ERROR! | L48: =PRODUCTION!#REF! -> #ERROR! | ... Q48: =PRODUCTION!#REF! -> #ERROR!
B49: Productive Time | C49: % | D49: 0.8 | E49: =PRODUCTION!G35 -> 0.29180311 | F49: =PRODUCTION!H35 -> 0.21150467 | G49: =PRODUCTION!I35 -> 0.10195678 | H49: =PRODUCTION!J35 -> 0 | I49: =PRODUCTION!K35 -> 0 | J49: =PRODUCTION!L35 -> 0 | K49: =PRODUCTION!M35 -> 0 | L49: =PRODUCTION!N35 -> 0 | ... Q49: =PRODUCTION!S35 -> 0.21634071
B50: Machine Utilization | C50: % | E50: =PRODUCTION!G61 -> 1.547481 | F50: =PRODUCTION!H61 -> 1.2688208 | G50: =PRODUCTION!I61 -> 0.97143673 | H50: =PRODUCTION!J61 -> 0 | I50: =PRODUCTION!K61 -> 0 | J50: =PRODUCTION!L61 -> 0 | K50: =PRODUCTION!M61 -> 0 | L50: =PRODUCTION!N61 -> 0 | ... Q50: =PRODUCTION!S61 -> 1.5804456
B51: Material Usage (Yield Rate)
B52: Internal Rejection
B53: Scrap
B54: Number of Days per month | E54: =PRODUCTION!G914 -> 19.75 | F54: =PRODUCTION!H914 -> 23.65 | G54: =PRODUCTION!I914 -> 19.45
A56: =MAX($A$34:A55)+1 -> 2 | B56: Inventory Reports
B57: Stock levels
B58: DIO | C58: days | D58: 70 | E58: ='SCM - PLANNING'!G41 -> 107 | F58: 111 | G58: 137 | H58: 154 | I58: ='SCM - PLANNING'!K41 | J58: ='SCM - PLANNING'!L41 | K58: ='SCM - PLANNING'!M41 | L58: ='SCM - PLANNING'!N41 | M58: ='SCM - PLANNING'!O41 | N58: ='SCM - PLANNING'!P41 | O58: ='SCM - PLANNING'!Q41 | P58: ='SCM - PLANNING'!R41 | Q58: ='SCM - PLANNING'!S41
B59: Safety Stocks FG | C59: days
B60: Safety Stocks RM | C60: days
B61: Safety Stocks PM | C61: days
B63: Turnover rates
B65: Aging Inventory FG
B66: Fast Moving (GOOD) Class A&B
B67: Fast Moving (NTE) Class A&B
B68: Slow Moving /NTE Class C
B69: No Movement Class C
B70: Expired Stocks
B71: Total Inventory
B73: Aging Inventory RM
B74: Fast Moving (GOOD) Class A&B
B75: Fast Moving (NTE) Class A&B
B76: Slow Moving /NTE Class C
... B89: Inventory Accuracy
B90: Inventory Accuracy FG | C90: % | D90: 1 | E90: ='SCM - PLANNING'!G122 -> 0.0079051383 | F90: ='SCM - PLANNING'!H122 -> 0.98675497 | G90: ='SCM - PLANNING'!I122 -> 0 | H90: ='SCM - PLANNING'!J122 -> 0 | I90: ='SCM - PLANNING'!K122 -> 0 | J90: ='SCM - PLANNING'!L122 -> 0 | K90: ='SCM - PLANNING'!M122 -> 0 | L90: ='SCM - PLANNING'!N122 -> 0 | ... Q90: ='SCM - PLANNING'!S122 -> 0.37376238
B91: Inventory Accuracy RMPM | C91: % | D91: 1 | E91: ='SCM - PLANNING'!G128 -> 0.50198413 | F91: ='SCM - PLANNING'!H128 -> 0.98717949 | G91: ='SCM - PLANNING'!I128 -> 0.98734177 | H91: ='SCM - PLANNING'!J128 -> 0.97619048 | I91: ='SCM - PLANNING'!K128 -> 0 | J91: ='SCM - PLANNING'!L128 -> 0 | K91: ='SCM - PLANNING'!M128 -> 0 | L91: ='SCM - PLANNING'!N128 -> 0 | ... Q91: ='SCM - PLANNING'!S128 -> 0.65771812
B92: Inventory Accuracy Production | C92: % | D92: 1 | E92: NO DATA | F92: NO DATA
B94: Warehouse Utlization
B95: Warehouse Utlization FG | C95: % | E95: ='WHSE & LOGS'!G170 -> 0.78984485 | F95: ='WHSE & LOGS'!H170 -> 0.90973202 | G95: ='WHSE & LOGS'!I170 -> 0.75956633 | H95: ='WHSE & LOGS'!J170 -> 0.703125 | I95: ='WHSE & LOGS'!K170 -> 0 | J95: ='WHSE & LOGS'!L170 -> 0 | K95: ='WHSE & LOGS'!M170 -> 0 | L95: ='WHSE & LOGS'!N170 -> 0 | ... Q95: ='WHSE & LOGS'!S170 -> 0.7875921
B96: Warehouse Utlization RMPM | C96: % | E96: ='WHSE & LOGS'!G163 -> 0.99724284 | F96: ='WHSE & LOGS'!H163 -> 1.2604273 | G96: ='WHSE & LOGS'!I163 -> 0 | H96: ='WHSE & LOGS'!J163 -> 0 | I96: ='WHSE & LOGS'!K163 -> 0 | J96: ='WHSE & LOGS'!L163 -> 0 | K96: ='WHSE & LOGS'!M163 -> 0 | L96: ='WHSE & LOGS'!N163 -> 0 | ... Q96: ='WHSE & LOGS'!S163 -> 1.0985125
A98: =MAX($A$34:A88)+1 -> 3 | B98: Supply Chain and Logistics Reports
B99: Supplier Performance
B100: Lead Times
B101: Freight Costs
A103: =MAX($A$34:A102)+1 -> 4 | B103: Sales & Operations Planning (S&OP) Reports
B104: Demand vs supply alignment
B105: Forecast Accuracy | C105: % | E105: ='SCM - PLANNING'!G182 -> 0.099922253 | F105: ='SCM - PLANNING'!H182 -> 0.41602569 | G105: ='SCM - PLANNING'!I182 -> 0.41862193 | H105: ='SCM - PLANNING'!J182 | I105: ='SCM - PLANNING'!K182 | J105: ='SCM - PLANNING'!L182 | K105: ='SCM - PLANNING'!M182 | L105: ='SCM - PLANNING'!N182 | ... Q105: ='SCM - PLANNING'!S182 -> 0.31152329
B106: EPOXY (MARINE + CONSTRUCTION) | C106: % | E106: ='SCM - PLANNING'!G168 -> 0 | F106: ='SCM - PLANNING'!H168 -> 0.45772562 | G106: ='SCM - PLANNING'!I168 -> 0.4353062 | H106: ='SCM - PLANNING'!J168 | I106: ='SCM - PLANNING'!K168 | J106: ='SCM - PLANNING'!L168 | K106: ='SCM - PLANNING'!M168 | L106: ='SCM - PLANNING'!N168 | ... Q106: ='SCM - PLANNING'!S168 -> 0.29767727
B107: ELASTOSEAL | C107: % | E107: ='SCM - PLANNING'!G169 -> 0.34921989 | F107: ='SCM - PLANNING'!H169 -> 0.76971992 | G107: ='SCM - PLANNING'!I169 -> 0.81588353 | H107: ='SCM - PLANNING'!J169 | I107: ='SCM - PLANNING'!K169 | J107: ='SCM - PLANNING'!L169 | K107: ='SCM - PLANNING'!M169 | L107: ='SCM - PLANNING'!N169 | ... Q107: ='SCM - PLANNING'!S169 -> 0.64494111
B108: MIGHTY BOND | C108: % | E108: ='SCM - PLANNING'!G170 -> 0 | F108: ='SCM - PLANNING'!H170 -> 0.66919905 | G108: ='SCM - PLANNING'!I170 -> 0.64893346 | H108: ='SCM - PLANNING'!J170 | I108: ='SCM - PLANNING'!K170 | J108: ='SCM - PLANNING'!L170 | K108: ='SCM - PLANNING'!M170 | L108: ='SCM - PLANNING'!N170 | ... Q108: ='SCM - PLANNING'!S170 -> 0.4393775
B109: PRO-EPOXY | C109: % | E109: ='SCM - PLANNING'!G171 -> 0 | F109: ='SCM - PLANNING'!H171 -> 0.64811092 | G109: ='SCM - PLANNING'!I171 -> 0.61578612 | H109: ='SCM - PLANNING'!J171 | I109: ='SCM - PLANNING'!K171 | J109: ='SCM - PLANNING'!L171 | K109: ='SCM - PLANNING'!M171 | L109: ='SCM - PLANNING'!N171 | ... Q109: ='SCM - PLANNING'!S171 -> 0.42129901
B110: BUILDERS BOND | C110: % | E110: ='SCM - PLANNING'!G172 -> 0.19477051 | F110: ='SCM - PLANNING'!H172 -> 0.48097973 | G110: ='SCM - PLANNING'!I172 -> 0.52710643 | H110: ='SCM - PLANNING'!J172 | I110: ='SCM - PLANNING'!K172 | J110: ='SCM - PLANNING'!L172 | K110: ='SCM - PLANNING'!M172 | L110: ='SCM - PLANNING'!N172 | ... Q110: ='SCM - PLANNING'!S172 -> 0.40095222
B111: COATING MARINE | C111: % | E111: ='SCM - PLANNING'!G173 -> 0 | F111: ='SCM - PLANNING'!H173 -> 0.41566339 | G111: ='SCM - PLANNING'!I173 -> 0.64291217 | H111: ='SCM - PLANNING'!J173 | I111: ='SCM - PLANNING'!K173 | J111: ='SCM - PLANNING'!L173 | K111: ='SCM - PLANNING'!M173 | L111: ='SCM - PLANNING'!N173 | ... Q111: ='SCM - PLANNING'!S173 -> 0.35285852
B112: TRASPORTATION | C112: % | E112: ='SCM - PLANNING'!G174 -> 0 | F112: ='SCM - PLANNING'!H174 -> 0.27658279 | G112: ='SCM - PLANNING'!I174 -> 0 | H112: ='SCM - PLANNING'!J174 | I112: ='SCM - PLANNING'!K174 | J112: ='SCM - PLANNING'!L174 | K112: ='SCM - PLANNING'!M174 | L112: ='SCM - PLANNING'!N174 | ... Q112: ='SCM - PLANNING'!S174 -> 0.092194264
B113: OTHER CONSUMER | C113: % | E113: ='SCM - PLANNING'!G175 -> 0.38746551 | F113: ='SCM - PLANNING'!H175 -> 0.0065382981 | G113: ='SCM - PLANNING'!I175 -> 0 | H113: ='SCM - PLANNING'!J175 | I113: ='SCM - PLANNING'!K175 | J113: ='SCM - PLANNING'!L175 | K113: ='SCM - PLANNING'!M175 | L113: ='SCM - PLANNING'!N175 | ... Q113: ='SCM - PLANNING'!S175 -> 0.1313346
B114: PRO-SEALANT | C114: % | E114: ='SCM - PLANNING'!G176 -> 0 | F114: ='SCM - PLANNING'!H176 -> 0.50318328 | G114: ='SCM - PLANNING'!I176 -> 0.4870057 | H114: ='SCM - PLANNING'!J176 | I114: ='SCM - PLANNING'!K176 | J114: ='SCM - PLANNING'!L176 | K114: ='SCM - PLANNING'!M176 | L114: ='SCM - PLANNING'!N176 | ... Q114: ='SCM - PLANNING'!S176 -> 0.33006299
B115: PRO-WATERPROOFING | C115: % | E115: ='SCM - PLANNING'!G177 -> 0 | F115: ='SCM - PLANNING'!H177 -> 0.535723 | G115: ='SCM - PLANNING'!I177 -> 0 | H115: ='SCM - PLANNING'!J177 | I115: ='SCM - PLANNING'!K177 | J115: ='SCM - PLANNING'!L177 | K115: ='SCM - PLANNING'!M177 | L115: ='SCM - PLANNING'!N177 | ... Q115: ='SCM - PLANNING'!S177 -> 0.17857433
B116: PRO-PAINTING | C116: % | E116: ='SCM - PLANNING'!G178 -> 0 | F116: ='SCM - PLANNING'!H178 -> 0.69714382 | G116: ='SCM - PLANNING'!I178 -> 0.52004867 | H116: ='SCM - PLANNING'!J178 | I116: ='SCM - PLANNING'!K178 | J116: ='SCM - PLANNING'!L178 | K116: ='SCM - PLANNING'!M178 | L116: ='SCM - PLANNING'!N178 | ... Q116: ='SCM - PLANNING'!S178 -> 0.40573083
B117: PRO-ADHESIVES | C117: % | E117: ='SCM - PLANNING'!G179 -> 0 | F117: ='SCM - PLANNING'!H179 -> 0.20556193 | G117: ='SCM - PLANNING'!I179 -> 0.3221365 | H117: ='SCM - PLANNING'!J179 | I117: ='SCM - PLANNING'!K179 | J117: ='SCM - PLANNING'!L179 | K117: ='SCM - PLANNING'!M179 | L117: ='SCM - PLANNING'!N179 | ... Q117: ='SCM - PLANNING'!S179 -> 0.17589947
... B119: OTHERS | C119: % | E119: ='SCM - PLANNING'!G181 -> 0 | F119: ='SCM - PLANNING'!H181 -> 0 | G119: ='SCM - PLANNING'!I181 -> 0 | H119: ='SCM - PLANNING'!J181 | I119: ='SCM - PLANNING'!K181 | J119: ='SCM - PLANNING'!L181 | K119: ='SCM - PLANNING'!M181 | L119: ='SCM - PLANNING'!N181 | ... Q119: ='SCM - PLANNING'!S181 -> 0
B121: Forecast Accuracy Location | C121: % | E121: ='SCM - PLANNING'!G165 -> 0.082512686 | F121: ='SCM - PLANNING'!H165 -> 0.24952461 | G121: ='SCM - PLANNING'!I165 -> 0.15843228 | H121: ='SCM - PLANNING'!J165 | I121: ='SCM - PLANNING'!K165 | J121: ='SCM - PLANNING'!L165 | K121: ='SCM - PLANNING'!M165 | L121: ='SCM - PLANNING'!N165 | ... Q121: ='SCM - PLANNING'!S165 -> 0.16348986
B122: LOCAL PHILIPPINES | C122: % | E122: ='SCM - PLANNING'!G153 -> 0.030850576 | F122: ='SCM - PLANNING'!H153 -> 0.37709718 | G122: ='SCM - PLANNING'!I153 -> 0.31686455 | H122: ='SCM - PLANNING'!J153 | I122: ='SCM - PLANNING'!K153 | J122: ='SCM - PLANNING'!L153 | K122: ='SCM - PLANNING'!M153 | L122: ='SCM - PLANNING'!N153 | ... Q122: ='SCM - PLANNING'!S153 -> 0.2416041
B123: GMA | C123: % | E123: ='SCM - PLANNING'!G154 -> 0 | F123: ='SCM - PLANNING'!H154 -> 0.37469668 | G123: ='SCM - PLANNING'!I154 -> 0 | H123: ='SCM - PLANNING'!J154 | I123: ='SCM - PLANNING'!K154 | J123: ='SCM - PLANNING'!L154 | K123: ='SCM - PLANNING'!M154 | L123: ='SCM - PLANNING'!N154 | ... Q123: ='SCM - PLANNING'!S154 -> 0.12489889
...

Sheet SCM - PLANNING
A1: PIONEER
A2: 2026 KPI TRACKER
A3: SC - PLANNING
G5: Q1 | H5: Q1 | I5: Q1 | J5: Q2 | K5: Q2 | L5: Q2 | M5: Q3 | N5: Q3 | O5: Q3 | P5: Q4 | Q5: Q4 | R5: Q4
C6: UoM | E6: 2026 ABP | G6: OCT | H6: NOV | I6: DEC | J6: JAN | K6: FEB | L6: MAR | M6: APR | N6: MAY | O6: JUN | P6: JUL | Q6: AUG | R6: SEP | S6: 2026 YTD | U6: Q1 | V6: Q2 | W6: Q3 | X6: Q4
A7: A. | B7: COMPLIANCE TO SCHEDULE
B8: COMPLIANCE
B9: L06 - EPOXY | C9: % | D9: L06 | S9: =IFERROR(AVERAGE(G9:R9),0) -> 0 | U9: =IFERROR(AVERAGEIF($G$5:$R$5,U$6,$G9:$R9),0) -> 0 | V9: =IFERROR(AVERAGEIF($G$5:$R$5,V$6,$G9:$R9),0) -> 0 | W9: =IFERROR(AVERAGEIF($G$5:$R$5,W$6,$G9:$R9),0) -> 0 | X9: =IFERROR(AVERAGEIF($G$5:$R$5,X$6,$G9:$R9),0) -> 0
B10: L04B - ELASTO | C10: % | D10: L04B | S10: =IFERROR(AVERAGE(G10:R10),0) -> 0 | U10: =IFERROR(AVERAGEIF($G$5:$R$5,U$6,$G10:$R10),0) -> 0 | V10: =IFERROR(AVERAGEIF($G$5:$R$5,V$6,$G10:$R10),0) -> 0 | W10: =IFERROR(AVERAGEIF($G$5:$R$5,W$6,$G10:$R10),0) -> 0 | X10: =IFERROR(AVERAGEIF($G$5:$R$5,X$6,$G10:$R10),0) -> 0
B11: L03 - CYANO TUBE | C11: % | D11: GIP L03 | S11: =IFERROR(AVERAGE(G11:R11),0) -> 0 | U11: =IFERROR(AVERAGEIF($G$5:$R$5,U$6,$G11:$R11),0) -> 0 | V11: =IFERROR(AVERAGEIF($G$5:$R$5,V$6,$G11:$R11),0) -> 0 | W11: =IFERROR(AVERAGEIF($G$5:$R$5,W$6,$G11:$R11),0) -> 0 | X11: =IFERROR(AVERAGEIF($G$5:$R$5,X$6,$G11:$R11),0) -> 0
B12: L01 - COATINGS | C12: % | D12: L01 | S12: =IFERROR(AVERAGE(G12:R12),0) -> 0 | U12: =IFERROR(AVERAGEIF($G$5:$R$5,U$6,$G12:$R12),0) -> 0 | V12: =IFERROR(AVERAGEIF($G$5:$R$5,V$6,$G12:$R12),0) -> 0 | W12: =IFERROR(AVERAGEIF($G$5:$R$5,W$6,$G12:$R12),0) -> 0 | X12: =IFERROR(AVERAGEIF($G$5:$R$5,X$6,$G12:$R12),0) -> 0
B13: L07 - EPOXY TUBE | C13: % | D13: GIP L07 | S13: =IFERROR(AVERAGE(G13:R13),0) -> 0 | U13: =IFERROR(AVERAGEIF($G$5:$R$5,U$6,$G13:$R13),0) -> 0 | V13: =IFERROR(AVERAGEIF($G$5:$R$5,V$6,$G13:$R13),0) -> 0 | W13: =IFERROR(AVERAGEIF($G$5:$R$5,W$6,$G13:$R13),0) -> 0 | X13: =IFERROR(AVERAGEIF($G$5:$R$5,X$6,$G13:$R13),0) -> 0
B14: LINE 9 - EPS | C14: % | D14: EPS | S14: =IFERROR(AVERAGE(G14:R14),0) -> 0 | U14: =IFERROR(AVERAGEIF($G$5:$R$5,U$6,$G14:$R14),0) -> 0 | V14: =IFERROR(AVERAGEIF($G$5:$R$5,V$6,$G14:$R14),0) -> 0 | W14: =IFERROR(AVERAGEIF($G$5:$R$5,W$6,$G14:$R14),0) -> 0 | X14: =IFERROR(AVERAGEIF($G$5:$R$5,X$6,$G14:$R14),0) -> 0
B15: L10 - CONTACT BOND | C15: % | D15: L10 | S15: =IFERROR(AVERAGE(G15:R15),0) -> 0 | U15: =IFERROR(AVERAGEIF($G$5:$R$5,U$6,$G15:$R15),0) -> 0 | V15: =IFERROR(AVERAGEIF($G$5:$R$5,V$6,$G15:$R15),0) -> 0 | W15: =IFERROR(AVERAGEIF($G$5:$R$5,W$6,$G15:$R15),0) -> 0 | X15: =IFERROR(AVERAGEIF($G$5:$R$5,X$6,$G15:$R15),0) -> 0
B16: L11 - SILICONE | C16: % | D16: GIP L11 | S16: =IFERROR(AVERAGE(G16:R16),0) -> 0 | U16: =IFERROR(AVERAGEIF($G$5:$R$5,U$6,$G16:$R16),0) -> 0 | V16: =IFERROR(AVERAGEIF($G$5:$R$5,V$6,$G16:$R16),0) -> 0 | W16: =IFERROR(AVERAGEIF($G$5:$R$5,W$6,$G16:$R16),0) -> 0 | X16: =IFERROR(AVERAGEIF($G$5:$R$5,X$6,$G16:$R16),0) -> 0
B17: L12 - SPECIAL - EPOXY BASED | C17: % | D17: L12 | S17: =IFERROR(AVERAGE(G17:R17),0) -> 0 | U17: =IFERROR(AVERAGEIF($G$5:$R$5,U$6,$G17:$R17),0) -> 0 | V17: =IFERROR(AVERAGEIF($G$5:$R$5,V$6,$G17:$R17),0) -> 0 | W17: =IFERROR(AVERAGEIF($G$5:$R$5,W$6,$G17:$R17),0) -> 0 | X17: =IFERROR(AVERAGEIF($G$5:$R$5,X$6,$G17:$R17),0) -> 0
B18: L13 - SPECIAL | C18: % | D18: L13 | S18: =IFERROR(AVERAGE(G18:R18),0) -> 0 | U18: =IFERROR(AVERAGEIF($G$5:$R$5,U$6,$G18:$R18),0) -> 0 | V18: =IFERROR(AVERAGEIF($G$5:$R$5,V$6,$G18:$R18),0) -> 0 | W18: =IFERROR(AVERAGEIF($G$5:$R$5,W$6,$G18:$R18),0) -> 0 | X18: =IFERROR(AVERAGEIF($G$5:$R$5,X$6,$G18:$R18),0) -> 0
B19: LINE 14 | C19: % | D19: L14 | S19: =IFERROR(AVERAGE(G19:R19),0) -> 0 | U19: =IFERROR(AVERAGEIF($G$5:$R$5,U$6,$G19:$R19),0) -> 0 | V19: =IFERROR(AVERAGEIF($G$5:$R$5,V$6,$G19:$R19),0) -> 0 | W19: =IFERROR(AVERAGEIF($G$5:$R$5,W$6,$G19:$R19),0) -> 0 | X19: =IFERROR(AVERAGEIF($G$5:$R$5,X$6,$G19:$R19),0) -> 0
B20: L05 - EPOXY CLAY | C20: % | D20: GIP L05 | S20: =IFERROR(AVERAGE(G20:R20),0) -> 0 | U20: =IFERROR(AVERAGEIF($G$5:$R$5,U$6,$G20:$R20),0) -> 0 | V20: =IFERROR(AVERAGEIF($G$5:$R$5,V$6,$G20:$R20),0) -> 0 | W20: =IFERROR(AVERAGEIF($G$5:$R$5,W$6,$G20:$R20),0) -> 0 | X20: =IFERROR(AVERAGEIF($G$5:$R$5,X$6,$G20:$R20),0) -> 0
B21: L02 - CYNO BOTTLE | C21: % | D21: L02 | S21: =IFERROR(AVERAGE(G21:R21),0) -> 0 | U21: =IFERROR(AVERAGEIF($G$5:$R$5,U$6,$G21:$R21),0) -> 0 | V21: =IFERROR(AVERAGEIF($G$5:$R$5,V$6,$G21:$R21),0) -> 0 | W21: =IFERROR(AVERAGEIF($G$5:$R$5,W$6,$G21:$R21),0) -> 0 | X21: =IFERROR(AVERAGEIF($G$5:$R$5,X$6,$G21:$R21),0) -> 0
B22: COMPLIANCE TO SCHEDULE | C22: % | S22: =IFERROR(AVERAGE(G22:R22),0) -> 0 | U22: =IFERROR(AVERAGEIF($G$5:$R$5,U$6,$G22:$R22),0) -> 0 | V22: =IFERROR(AVERAGEIF($G$5:$R$5,V$6,$G22:$R22),0) -> 0 | W22: =IFERROR(AVERAGEIF($G$5:$R$5,W$6,$G22:$R22),0) -> 0 | X22: =IFERROR(AVERAGEIF($G$5:$R$5,X$6,$G22:$R22),0) -> 0
A24: B. | B24: DIO (based on P&L COGS)
B25: DIO
B26: FG - Consignment | C26: DAYS | E26: 1 | S26: =R26 | U26: =IFERROR(AVERAGE(G26,H26,I26),0) -> 0 | V26: =IFERROR(AVERAGE(H26,I26,J26),0) -> 0 | W26: =IFERROR(AVERAGE(I26,J26,K26),0) -> 0 | X26: =IFERROR(AVERAGE(P26:R26),0) -> 0
B27: FG | C27: DAYS | E27: 25 | S27: =R27 | U27: =IFERROR(AVERAGE(G27:I27),0) -> 0 | V27: =IFERROR(AVERAGE(J27:L27),0) -> 0 | W27: =IFERROR(AVERAGE(M27:O27),0) -> 0 | X27: =IFERROR(AVERAGE(P27:R27),0) -> 0
B28: SFG | C28: DAYS | E28: 1 | S28: =R28 | U28: =IFERROR(AVERAGE(G28:I28),0) -> 0 | V28: =IFERROR(AVERAGE(J28:L28),0) -> 0 | W28: =IFERROR(AVERAGE(M28:O28),0) -> 0 | X28: =IFERROR(AVERAGE(P28:R28),0) -> 0
B29: BM | C29: DAYS | E29: 1 | S29: =R29 | U29: =IFERROR(AVERAGE(G29:I29),0) -> 0 | V29: =IFERROR(AVERAGE(J29:L29),0) -> 0 | W29: =IFERROR(AVERAGE(M29:O29),0) -> 0 | X29: =IFERROR(AVERAGE(P29:R29),0) -> 0
B30: RM | C30: DAYS | E30: 34 | S30: =R30 | U30: =IFERROR(AVERAGE(G30:I30),0) -> 0 | V30: =IFERROR(AVERAGE(J30:L30),0) -> 0 | W30: =IFERROR(AVERAGE(M30:O30),0) -> 0 | X30: =IFERROR(AVERAGE(P30:R30),0) -> 0
B31: PM | C31: DAYS | E31: 8 | S31: =R31 | U31: =IFERROR(AVERAGE(G31:I31),0) -> 0 | V31: =IFERROR(AVERAGE(J31:L31),0) -> 0 | W31: =IFERROR(AVERAGE(M31:O31),0) -> 0 | X31: =IFERROR(AVERAGE(P31:R31),0) -> 0
B33: DIO-SOH | C33: DAYS | E33: 69 | S33: =R33 | U33: =IFERROR(AVERAGE(G33:I33),0) -> 0 | V33: =IFERROR(AVERAGE(J33:L33),0) -> 0 | W33: =IFERROR(AVERAGE(M33:O33),0) -> 0 | X33: =IFERROR(AVERAGE(P33:R33),0) -> 0
B35: TOTAL-OTHERS | C35: DAYS | E35: 0 | S35: =R35 | U35: =IFERROR(AVERAGE(G35:I35),0) -> 0 | V35: =IFERROR(AVERAGE(J35:L35),0) -> 0 | W35: =IFERROR(AVERAGE(M35:O35),0) -> 0 | X35: =IFERROR(AVERAGE(P35:R35),0) -> 0
B37: FG In-transit | C37: DAYS | E37: 1 | S37: =R37 | U37: =IFERROR(AVERAGE(G37:I37),0) -> 0 | V37: =IFERROR(AVERAGE(J37:L37),0) -> 0 | W37: =IFERROR(AVERAGE(M37:O37),0) -> 0 | X37: =IFERROR(AVERAGE(P37:R37),0) -> 0
B38: RM In-transit | C38: DAYS | E38: 7 | S38: =R38 | U38: =IFERROR(AVERAGE(G38:I38),0) -> 0 | V38: =IFERROR(AVERAGE(J38:L38),0) -> 0 | W38: =IFERROR(AVERAGE(M38:O38),0) -> 0 | X38: =IFERROR(AVERAGE(P38:R38),0) -> 0
B39: TOTAL IN-TRANSIT | C39: DAYS | E39: =E37+E38 -> 8 | S39: =S37+S38 -> 0 | U39: =U37+U38 -> 0 | V39: =V37+V38 -> 0 | W39: =W37+W38 -> 0 | X39: =X37+X38 -> 0
B41: TOTAL INVENTORY | C41: DAYS | E41: 77 | G41: 107 | H41: 108 | S41: =R41 | U41: =IFERROR(AVERAGE(G41:I41),0) -> 107.5 | V41: =IFERROR(AVERAGE(J41:L41),0) -> 0 | W41: =IFERROR(AVERAGE(M41:O41),0) -> 0 | X41: =IFERROR(AVERAGE(P41:R41),0) -> 0
A43: C. | B43: DIO-SOH (net of consignment & SLOB Provisions)
B44: DIO-SOH
B45: FG | C45: DAYS | S45: =R45 | U45: =IFERROR(AVERAGE(G45:I45),0) -> 0 | V45: =IFERROR(AVERAGE(J45:L45),0) -> 0 | W45: =IFERROR(AVERAGE(M45:O45),0) -> 0 | X45: =IFERROR(AVERAGE(P45:R45),0) -> 0
B46: SFG | C46: DAYS | S46: =R46 | U46: =IFERROR(AVERAGE(G46:I46),0) -> 0 | V46: =IFERROR(AVERAGE(J46:L46),0) -> 0 | W46: =IFERROR(AVERAGE(M46:O46),0) -> 0 | X46: =IFERROR(AVERAGE(P46:R46),0) -> 0
B47: BM | C47: DAYS | S47: =R47 | U47: =IFERROR(AVERAGE(G47:I47),0) -> 0 | V47: =IFERROR(AVERAGE(J47:L47),0) -> 0 | W47: =IFERROR(AVERAGE(M47:O47),0) -> 0 | X47: =IFERROR(AVERAGE(P47:R47),0) -> 0
B48: RM | C48: DAYS | S48: =R48 | U48: =IFERROR(AVERAGE(G48:I48),0) -> 0 | V48: =IFERROR(AVERAGE(J48:L48),0) -> 0 | W48: =IFERROR(AVERAGE(M48:O48),0) -> 0 | X48: =IFERROR(AVERAGE(P48:R48),0) -> 0
B49: PM | C49: DAYS | S49: =R49 | U49: =IFERROR(AVERAGE(G49:I49),0) -> 0 | V49: =IFERROR(AVERAGE(J49:L49),0) -> 0 | W49: =IFERROR(AVERAGE(M49:O49),0) -> 0 | X49: =IFERROR(AVERAGE(P49:R49),0) -> 0
A51: D. | B51: SAFETY STOCKS MONITORING FG
B52: INVENTORY SAFETY STOCKS FG
B53: Class A | C53: DAYS | S53: =SUM(G53:R53) -> 0 | U53: =SUMIFS($G53:$R53,$G$5:$R$5,U$6) -> 0 | V53: =SUMIFS($G53:$R53,$G$5:$R$5,V$6) -> 0 | W53: =SUMIFS($G53:$R53,$G$5:$R$5,W$6) -> 0 | X53: =SUMIFS($G53:$R53,$G$5:$R$5,X$6) -> 0
B54: Class B | C54: DAYS | S54: =SUM(G54:R54) -> 0 | U54: =SUMIFS($G54:$R54,$G$5:$R$5,U$6) -> 0 | V54: =SUMIFS($G54:$R54,$G$5:$R$5,V$6) -> 0 | W54: =SUMIFS($G54:$R54,$G$5:$R$5,W$6) -> 0 | X54: =SUMIFS($G54:$R54,$G$5:$R$5,X$6) -> 0
B55: Class C | C55: DAYS | S55: =SUM(G55:R55) -> 0 | U55: =SUMIFS($G55:$R55,$G$5:$R$5,U$6) -> 0 | V55: =SUMIFS($G55:$R55,$G$5:$R$5,V$6) -> 0 | W55: =SUMIFS($G55:$R55,$G$5:$R$5,W$6) -> 0 | X55: =SUMIFS($G55:$R55,$G$5:$R$5,X$6) -> 0
B56: ALL IN | C56: DAYS | S56: =SUM(G56:R56) -> 0 | U56: =SUMIFS($G56:$R56,$G$5:$R$5,U$6) -> 0 | V56: =SUMIFS($G56:$R56,$G$5:$R$5,V$6) -> 0 | W56: =SUMIFS($G56:$R56,$G$5:$R$5,W$6) -> 0 | X56: =SUMIFS($G56:$R56,$G$5:$R$5,X$6) -> 0
B57: Grand total | C57: DAYS | S57: =SUM(G57:R57) -> 0 | U57: =SUMIFS($G57:$R57,$G$5:$R$5,U$6) -> 0 | V57: =SUMIFS($G57:$R57,$G$5:$R$5,V$6) -> 0 | W57: =SUMIFS($G57:$R57,$G$5:$R$5,W$6) -> 0 | X57: =SUMIFS($G57:$R57,$G$5:$R$5,X$6) -> 0
A60: E. | B60: SAFETY STOCKS MONITORING RM
B61: INVENTORY SAFETY STOCKS RM
B62: Class A | C62: DAYS | S62: =SUM(G62:R62) -> 0 | U62: =SUMIFS($G62:$R62,$G$5:$R$5,U$6) -> 0 | V62: =SUMIFS($G62:$R62,$G$5:$R$5,V$6) -> 0 | W62: =SUMIFS($G62:$R62,$G$5:$R$5,W$6) -> 0 | X62: =SUMIFS($G62:$R62,$G$5:$R$5,X$6) -> 0
B63: Class B | C63: DAYS | S63: =SUM(G63:R63) -> 0 | U63: =SUMIFS($G63:$R63,$G$5:$R$5,U$6) -> 0 | V63: =SUMIFS($G63:$R63,$G$5:$R$5,V$6) -> 0 | W63: =SUMIFS($G63:$R63,$G$5:$R$5,W$6) -> 0 | X63: =SUMIFS($G63:$R63,$G$5:$R$5,X$6) -> 0
B64: Class C | C64: DAYS | S64: =SUM(G64:R64) -> 0 | U64: =SUMIFS($G64:$R64,$G$5:$R$5,U$6) -> 0 | V64: =SUMIFS($G64:$R64,$G$5:$R$5,V$6) -> 0 | W64: =SUMIFS($G64:$R64,$G$5:$R$5,W$6) -> 0 | X64: =SUMIFS($G64:$R64,$G$5:$R$5,X$6) -> 0
B65: Grand total | C65: DAYS | G65: =SUM(G62,G63,G64) -> 0 | H65: =SUM(H62,H63,H64) -> 0 | I65: =SUM(I62,I63,I64) -> 0 | J65: =SUM(J62,J63,J64) -> 0 | K65: =SUM(K62,K63,K64) -> 0 | L65: =SUM(L62,L63,L64) -> 0 | M65: =SUM(M62,M63,M64) -> 0 | N65: =SUM(N62,N63,N64) -> 0 | ... Q65: =SUM(Q62,Q63,Q64) -> 0 | S65: =SUM(G65:R65) -> 0 | U65: =SUMIFS($G65:$R65,$G$5:$R$5,U$6) -> 0 | V65: =SUMIFS($G65:$R65,$G$5:$R$5,V$6) -> 0 | W65: =SUMIFS($G65:$R65,$G$5:$R$5,W$6) -> 0 | X65: =SUMIFS($G65:$R65,$G$5:$R$5,X$6) -> 0
A68: F. | B68: SAFETY STOCKS MONITORING PM
B69: INVENTORY SAFETY STOCKS PM
B70: CORE | C70: DAYS | G70: 48 | H70: 59 | I70: 74 | J70: 102 | K70: 78 | L70: 60 | S70: =SUM(G70:R70) -> 421 | U70: =SUMIFS($G70:$R70,$G$5:$R$5,U$6) -> 181 | V70: =SUMIFS($G70:$R70,$G$5:$R$5,V$6) -> 240 | W70: =SUMIFS($G70:$R70,$G$5:$R$5,W$6) -> 0 | X70: =SUMIFS($G70:$R70,$G$5:$R$5,X$6) -> 0
B71: M7 | C71: DAYS | G71: 36 | H71: 62 | I71: 69 | J71: 28 | K71: 15 | L71: 16 | S71: =SUM(G71:R71) -> 226 | U71: =SUMIFS($G71:$R71,$G$5:$R$5,U$6) -> 167 | V71: =SUMIFS($G71:$R71,$G$5:$R$5,V$6) -> 59 | W71: =SUMIFS($G71:$R71,$G$5:$R$5,W$6) -> 0 | X71: =SUMIFS($G71:$R71,$G$5:$R$5,X$6) -> 0
B72: OTHERS | C72: DAYS | G72: 136 | H72: 113 | I72: 86 | J72: 106 | K72: 67 | L72: 73 | S72: =SUM(G72:R72) -> 581 | U72: =SUMIFS($G72:$R72,$G$5:$R$5,U$6) -> 335 | V72: =SUMIFS($G72:$R72,$G$5:$R$5,V$6) -> 246 | W72: =SUMIFS($G72:$R72,$G$5:$R$5,W$6) -> 0 | X72: =SUMIFS($G72:$R72,$G$5:$R$5,X$6) -> 0
B73: Grand total | C73: DAYS | G73: =SUM(G70,G71,G72) -> 220 | H73: =SUM(H70,H71,H72) -> 234 | I73: =SUM(I70,I71,I72) -> 229 | J73: =SUM(J70,J71,J72) -> 236 | K73: =SUM(K70,K71,K72) -> 160 | L73: =SUM(L70,L71,L72) -> 149 | M73: =SUM(M70,M71,M72) -> 0 | N73: =SUM(N70,N71,N72) -> 0 | ... Q73: =SUM(Q70,Q71,Q72) -> 0 | S73: =SUM(G73:R73) -> 1228 | U73: =SUMIFS($G73:$R73,'WHSE & LOGS'!$G$5:$R$5,'WHSE & LOGS'!U$6) -> 683 | V73: =SUMIFS($G73:$R73,'WHSE & LOGS'!$G$5:$R$5,'WHSE & LOGS'!V$6) -> 545 | W73: =SUMIFS($G73:$R73,'WHSE & LOGS'!$G$5:$R$5,'WHSE & LOGS'!W$6) -> 0 | X73: =SUMIFS($G73:$R73,'WHSE & LOGS'!$G$5:$R$5,'WHSE & LOGS'!X$6) -> 0
A76: G. | B76: INVENTORY
B77: FG Inventory Distribution
B78: Fast Moving (GOOD) Class A&B | C78: kgs | S78: =SUM(G78:R78) -> 0 | U78: =SUMIFS($G78:$R78,'WHSE & LOGS'!$G$5:$R$5,'WHSE & LOGS'!U$6) -> 0 | V78: =SUMIFS($G78:$R78,'WHSE & LOGS'!$G$5:$R$5,'WHSE & LOGS'!V$6) -> 0 | W78: =SUMIFS($G78:$R78,'WHSE & LOGS'!$G$5:$R$5,'WHSE & LOGS'!W$6) -> 0 | X78: =SUMIFS($G78:$R78,'WHSE & LOGS'!$G$5:$R$5,'WHSE & LOGS'!X$6) -> 0
B79: Fast Moving (NTE) Class A&B | C79: kgs | S79: =SUM(G79:R79) -> 0 | U79: =SUMIFS($G79:$R79,'WHSE & LOGS'!$G$5:$R$5,'WHSE & LOGS'!U$6) -> 0 | V79: =SUMIFS($G79:$R79,'WHSE & LOGS'!$G$5:$R$5,'WHSE & LOGS'!V$6) -> 0 | W79: =SUMIFS($G79:$R79,'WHSE & LOGS'!$G$5:$R$5,'WHSE & LOGS'!W$6) -> 0 | X79: =SUMIFS($G79:$R79,'WHSE & LOGS'!$G$5:$R$5,'WHSE & LOGS'!X$6) -> 0
B80: Slow Moving /NTE Class C | C80: kgs | S80: =SUM(G80:R80) -> 0 | U80: =SUMIFS($G80:$R80,'WHSE & LOGS'!$G$5:$R$5,'WHSE & LOGS'!U$6) -> 0 | V80: =SUMIFS($G80:$R80,'WHSE & LOGS'!$G$5:$R$5,'WHSE & LOGS'!V$6) -> 0 | W80: =SUMIFS($G80:$R80,'WHSE & LOGS'!$G$5:$R$5,'WHSE & LOGS'!W$6) -> 0 | X80: =SUMIFS($G80:$R80,'WHSE & LOGS'!$G$5:$R$5,'WHSE & LOGS'!X$6) -> 0
B81: No Movement Class C | C81: kgs | S81: =SUM(G81:R81) -> 0 | U81: =SUMIFS($G81:$R81,'WHSE & LOGS'!$G$5:$R$5,'WHSE & LOGS'!U$6) -> 0 | V81: =SUMIFS($G81:$R81,'WHSE & LOGS'!$G$5:$R$5,'WHSE & LOGS'!V$6) -> 0 | W81: =SUMIFS($G81:$R81,'WHSE & LOGS'!$G$5:$R$5,'WHSE & LOGS'!W$6) -> 0 | X81: =SUMIFS($G81:$R81,'WHSE & LOGS'!$G$5:$R$5,'WHSE & LOGS'!X$6) -> 0
B82: Expired Stocks | C82: kgs | S82: =SUM(G82:R82) -> 0 | U82: =SUMIFS($G82:$R82,'WHSE & LOGS'!$G$5:$R$5,'WHSE & LOGS'!U$6) -> 0 | V82: =SUMIFS($G82:$R82,'WHSE & LOGS'!$G$5:$R$5,'WHSE & LOGS'!V$6) -> 0 | W82: =SUMIFS($G82:$R82,'WHSE & LOGS'!$G$5:$R$5,'WHSE & LOGS'!W$6) -> 0 | X82: =SUMIFS($G82:$R82,'WHSE & LOGS'!$G$5:$R$5,'WHSE & LOGS'!X$6) -> 0
B83: Total Inventory | C83: kgs | G83: =SUM(G78:G82) -> 0 | H83: =SUM(H78:H82) -> 0 | I83: =SUM(I78:I82) -> 0 | J83: =SUM(J78:J82) -> 0 | K83: =SUM(K78:K82) -> 0 | L83: =SUM(L78:L82) -> 0 | M83: =SUM(M78:M82) -> 0 | N83: =SUM(N78:N82) -> 0 | ... R83: =SUM(R78:R82) -> 0 | S83: =SUM(G83:R83) -> 0 | U83: =SUMIFS($G83:$R83,'WHSE & LOGS'!$G$5:$R$5,'WHSE & LOGS'!U$6) -> 0 | V83: =SUMIFS($G83:$R83,'WHSE & LOGS'!$G$5:$R$5,'WHSE & LOGS'!V$6) -> 0 | W83: =SUMIFS($G83:$R83,'WHSE & LOGS'!$G$5:$R$5,'WHSE & LOGS'!W$6) -> 0 | X83: =SUMIFS($G83:$R83,'WHSE & LOGS'!$G$5:$R$5,'WHSE & LOGS'!X$6) -> 0
B84: No. of Inventory days | C84: day/s | S84: =SUM(G84:R84) -> 0 | U84: =SUMIFS($G84:$R84,'WHSE & LOGS'!$G$5:$R$5,'WHSE & LOGS'!U$6) -> 0 | V84: =SUMIFS($G84:$R84,'WHSE & LOGS'!$G$5:$R$5,'WHSE & LOGS'!V$6) -> 0 | W84: =SUMIFS($G84:$R84,'WHSE & LOGS'!$G$5:$R$5,'WHSE & LOGS'!W$6) -> 0 | X84: =SUMIFS($G84:$R84,'WHSE & LOGS'!$G$5:$R$5,'WHSE & LOGS'!X$6) -> 0
A86: H. | B86: INVENTORY
B87: FG Inventory Distribution
B88: Fast Moving (GOOD) Class A&B | C88: PHP | S88: =SUM(G88:R88) -> 0 | U88: =SUMIFS($G88:$R88,'WHSE & LOGS'!$G$5:$R$5,'WHSE & LOGS'!U$6) -> 0 | V88: =SUMIFS($G88:$R88,'WHSE & LOGS'!$G$5:$R$5,'WHSE & LOGS'!V$6) -> 0 | W88: =SUMIFS($G88:$R88,'WHSE & LOGS'!$G$5:$R$5,'WHSE & LOGS'!W$6) -> 0 | X88: =SUMIFS($G88:$R88,'WHSE & LOGS'!$G$5:$R$5,'WHSE & LOGS'!X$6) -> 0
B89: Fast Moving (NTE) Class A&B | C89: PHP | S89: =SUM(G89:R89) -> 0 | U89: =SUMIFS($G89:$R89,'WHSE & LOGS'!$G$5:$R$5,'WHSE & LOGS'!U$6) -> 0 | V89: =SUMIFS($G89:$R89,'WHSE & LOGS'!$G$5:$R$5,'WHSE & LOGS'!V$6) -> 0 | W89: =SUMIFS($G89:$R89,'WHSE & LOGS'!$G$5:$R$5,'WHSE & LOGS'!W$6) -> 0 | X89: =SUMIFS($G89:$R89,'WHSE & LOGS'!$G$5:$R$5,'WHSE & LOGS'!X$6) -> 0
B90: Slow Moving /NTE Class C | C90: PHP | S90: =SUM(G90:R90) -> 0 | U90: =SUMIFS($G90:$R90,'WHSE & LOGS'!$G$5:$R$5,'WHSE & LOGS'!U$6) -> 0 | V90: =SUMIFS($G90:$R90,'WHSE & LOGS'!$G$5:$R$5,'WHSE & LOGS'!V$6) -> 0 | W90: =SUMIFS($G90:$R90,'WHSE & LOGS'!$G$5:$R$5,'WHSE & LOGS'!W$6) -> 0 | X90: =SUMIFS($G90:$R90,'WHSE & LOGS'!$G$5:$R$5,'WHSE & LOGS'!X$6) -> 0
B91: No Movement Class C | C91: PHP | S91: =SUM(G91:R91) -> 0 | U91: =SUMIFS($G91:$R91,'WHSE & LOGS'!$G$5:$R$5,'WHSE & LOGS'!U$6) -> 0 | V91: =SUMIFS($G91:$R91,'WHSE & LOGS'!$G$5:$R$5,'WHSE & LOGS'!V$6) -> 0 | W91: =SUMIFS($G91:$R91,'WHSE & LOGS'!$G$5:$R$5,'WHSE & LOGS'!W$6) -> 0 | X91: =SUMIFS($G91:$R91,'WHSE & LOGS'!$G$5:$R$5,'WHSE & LOGS'!X$6) -> 0
B92: Expired Stocks | C92: PHP | S92: =SUM(G92:R92) -> 0 | U92: =SUMIFS($G92:$R92,'WHSE & LOGS'!$G$5:$R$5,'WHSE & LOGS'!U$6) -> 0 | V92: =SUMIFS($G92:$R92,'WHSE & LOGS'!$G$5:$R$5,'WHSE & LOGS'!V$6) -> 0 | W92: =SUMIFS($G92:$R92,'WHSE & LOGS'!$G$5:$R$5,'WHSE & LOGS'!W$6) -> 0 | X92: =SUMIFS($G92:$R92,'WHSE & LOGS'!$G$5:$R$5,'WHSE & LOGS'!X$6) -> 0
B93: Total Inventory | C93: PHP | G93: =SUM(G88:G92) -> 0 | H93: =SUM(H88:H92) -> 0 | I93: =SUM(I88:I92) -> 0 | J93: =SUM(J88:J92) -> 0 | K93: =SUM(K88:K92) -> 0 | L93: =SUM(L88:L92) -> 0 | M93: =SUM(M88:M92) -> 0 | N93: =SUM(N88:N92) -> 0 | ... R93: =SUM(R88:R92) -> 0 | S93: =SUM(G93:R93) -> 0 | U93: =SUMIFS($G93:$R93,'WHSE & LOGS'!$G$5:$R$5,'WHSE & LOGS'!U$6) -> 0 | V93: =SUMIFS($G93:$R93,'WHSE & LOGS'!$G$5:$R$5,'WHSE & LOGS'!V$6) -> 0 | W93: =SUMIFS($G93:$R93,'WHSE & LOGS'!$G$5:$R$5,'WHSE & LOGS'!W$6) -> 0 | X93: =SUMIFS($G93:$R93,'WHSE & LOGS'!$G$5:$R$5,'WHSE & LOGS'!X$6) -> 0
B94: No. of Inventory days | C94: day/s | G94: =G84 | H94: =H84 | I94: =I84 | J94: =J84 | K94: =K84 | L94: =L84 | M94: =M84 | N94: =N84 | S94: =SUM(G94:R94) -> 0 | U94: =SUMIFS($G94:$R94,'WHSE & LOGS'!$G$5:$R$5,'WHSE & LOGS'!U$6) -> 0 | V94: =SUMIFS($G94:$R94,'WHSE & LOGS'!$G$5:$R$5,'WHSE & LOGS'!V$6) -> 0 | W94: =SUMIFS($G94:$R94,'WHSE & LOGS'!$G$5:$R$5,'WHSE & LOGS'!W$6) -> 0 | X94: =SUMIFS($G94:$R94,'WHSE & LOGS'!$G$5:$R$5,'WHSE & LOGS'!X$6) -> 0
A97: I. | B97: INVENTORY
B98: RM/PM Inventory Distribution
B99: Fast Moving (GOOD) Class A&B | C99: kgs | S99: =SUM(G99:R99) -> 0 | U99: =SUMIFS($G99:$R99,'WHSE & LOGS'!$G$5:$R$5,'WHSE & LOGS'!U$6) -> 0 | V99: =SUMIFS($G99:$R99,'WHSE & LOGS'!$G$5:$R$5,'WHSE & LOGS'!V$6) -> 0 | W99: =SUMIFS($G99:$R99,'WHSE & LOGS'!$G$5:$R$5,'WHSE & LOGS'!W$6) -> 0 | X99: =SUMIFS($G99:$R99,'WHSE & LOGS'!$G$5:$R$5,'WHSE & LOGS'!X$6) -> 0
B100: Fast Moving (NTE) Class A&B | C100: kgs | S100: =SUM(G100:R100) -> 0 | U100: =SUMIFS($G100:$R100,'WHSE & LOGS'!$G$5:$R$5,'WHSE & LOGS'!U$6) -> 0 | V100: =SUMIFS($G100:$R100,'WHSE & LOGS'!$G$5:$R$5,'WHSE & LOGS'!V$6) -> 0 | W100: =SUMIFS($G100:$R100,'WHSE & LOGS'!$G$5:$R$5,'WHSE & LOGS'!W$6) -> 0 | X100: =SUMIFS($G100:$R100,'WHSE & LOGS'!$G$5:$R$5,'WHSE & LOGS'!X$6) -> 0
B101: Slow Moving /NTE Class C | C101: kgs | S101: =SUM(G101:R101) -> 0 | U101: =SUMIFS($G101:$R101,'WHSE & LOGS'!$G$5:$R$5,'WHSE & LOGS'!U$6) -> 0 | V101: =SUMIFS($G101:$R101,'WHSE & LOGS'!$G$5:$R$5,'WHSE & LOGS'!V$6) -> 0 | W101: =SUMIFS($G101:$R101,'WHSE & LOGS'!$G$5:$R$5,'WHSE & LOGS'!W$6) -> 0 | X101: =SUMIFS($G101:$R101,'WHSE & LOGS'!$G$5:$R$5,'WHSE & LOGS'!X$6) -> 0
B102: No Movement Class C | C102: kgs | S102: =SUM(G102:R102) -> 0 | U102: =SUMIFS($G102:$R102,'WHSE & LOGS'!$G$5:$R$5,'WHSE & LOGS'!U$6) -> 0 | V102: =SUMIFS($G102:$R102,'WHSE & LOGS'!$G$5:$R$5,'WHSE & LOGS'!V$6) -> 0 | W102: =SUMIFS($G102:$R102,'WHSE & LOGS'!$G$5:$R$5,'WHSE & LOGS'!W$6) -> 0 | X102: =SUMIFS($G102:$R102,'WHSE & LOGS'!$G$5:$R$5,'WHSE & LOGS'!X$6) -> 0
B103: Expired Stocks | C103: kgs | S103: =SUM(G103:R103) -> 0 | U103: =SUMIFS($G103:$R103,'WHSE & LOGS'!$G$5:$R$5,'WHSE & LOGS'!U$6) -> 0 | V103: =SUMIFS($G103:$R103,'WHSE & LOGS'!$G$5:$R$5,'WHSE & LOGS'!V$6) -> 0 | W103: =SUMIFS($G103:$R103,'WHSE & LOGS'!$G$5:$R$5,'WHSE & LOGS'!W$6) -> 0 | X103: =SUMIFS($G103:$R103,'WHSE & LOGS'!$G$5:$R$5,'WHSE & LOGS'!X$6) -> 0
B104: Total Inventory | C104: kgs | G104: =SUM(G99:G103) -> 0 | H104: =SUM(H99:H103) -> 0 | I104: =SUM(I99:I103) -> 0 | J104: =SUM(J99:J103) -> 0 | K104: =SUM(K99:K103) -> 0 | L104: =SUM(L99:L103) -> 0 | M104: =SUM(M99:M103) -> 0 | N104: =SUM(N99:N103) -> 0 | ... R104: =SUM(R99:R103) -> 0 | S104: =SUM(G104:R104) -> 0 | U104: =SUMIFS($G104:$R104,'WHSE & LOGS'!$G$5:$R$5,'WHSE & LOGS'!U$6) -> 0 | V104: =SUMIFS($G104:$R104,'WHSE & LOGS'!$G$5:$R$5,'WHSE & LOGS'!V$6) -> 0 | W104: =SUMIFS($G104:$R104,'WHSE & LOGS'!$G$5:$R$5,'WHSE & LOGS'!W$6) -> 0 | X104: =SUMIFS($G104:$R104,'WHSE & LOGS'!$G$5:$R$5,'WHSE & LOGS'!X$6) -> 0
B105: No. of Inventory days | C105: day/s | S105: =SUM(G105:R105) -> 0 | U105: =SUMIFS($G105:$R105,'WHSE & LOGS'!$G$5:$R$5,'WHSE & LOGS'!U$6) -> 0 | V105: =SUMIFS($G105:$R105,'WHSE & LOGS'!$G$5:$R$5,'WHSE & LOGS'!V$6) -> 0 | W105: =SUMIFS($G105:$R105,'WHSE & LOGS'!$G$5:$R$5,'WHSE & LOGS'!W$6) -> 0 | X105: =SUMIFS($G105:$R105,'WHSE & LOGS'!$G$5:$R$5,'WHSE & LOGS'!X$6) -> 0
A107: J. | B107: INVENTORY
B108: RM/PM Inventory Distribution
B109: Fast Moving (GOOD) Class A&B | C109: PHP | S109: =SUM(G109:R109) -> 0 | U109: =SUMIFS($G109:$R109,'WHSE & LOGS'!$G$5:$R$5,'WHSE & LOGS'!U$6) -> 0 | V109: =SUMIFS($G109:$R109,'WHSE & LOGS'!$G$5:$R$5,'WHSE & LOGS'!V$6) -> 0 | W109: =SUMIFS($G109:$R109,'WHSE & LOGS'!$G$5:$R$5,'WHSE & LOGS'!W$6) -> 0 | X109: =SUMIFS($G109:$R109,'WHSE & LOGS'!$G$5:$R$5,'WHSE & LOGS'!X$6) -> 0
B110: Fast Moving (NTE) Class A&B | C110: PHP | S110: =SUM(G110:R110) -> 0 | U110: =SUMIFS($G110:$R110,'WHSE & LOGS'!$G$5:$R$5,'WHSE & LOGS'!U$6) -> 0 | V110: =SUMIFS($G110:$R110,'WHSE & LOGS'!$G$5:$R$5,'WHSE & LOGS'!V$6) -> 0 | W110: =SUMIFS($G110:$R110,'WHSE & LOGS'!$G$5:$R$5,'WHSE & LOGS'!W$6) -> 0 | X110: =SUMIFS($G110:$R110,'WHSE & LOGS'!$G$5:$R$5,'WHSE & LOGS'!X$6) -> 0
B111: Slow Moving /NTE Class C | C111: PHP | S111: =SUM(G111:R111) -> 0 | U111: =SUMIFS($G111:$R111,'WHSE & LOGS'!$G$5:$R$5,'WHSE & LOGS'!U$6) -> 0 | V111: =SUMIFS($G111:$R111,'WHSE & LOGS'!$G$5:$R$5,'WHSE & LOGS'!V$6) -> 0 | W111: =SUMIFS($G111:$R111,'WHSE & LOGS'!$G$5:$R$5,'WHSE & LOGS'!W$6) -> 0 | X111: =SUMIFS($G111:$R111,'WHSE & LOGS'!$G$5:$R$5,'WHSE & LOGS'!X$6) -> 0
B112: No Movement Class C | C112: PHP | S112: =SUM(G112:R112) -> 0 | U112: =SUMIFS($G112:$R112,'WHSE & LOGS'!$G$5:$R$5,'WHSE & LOGS'!U$6) -> 0 | V112: =SUMIFS($G112:$R112,'WHSE & LOGS'!$G$5:$R$5,'WHSE & LOGS'!V$6) -> 0 | W112: =SUMIFS($G112:$R112,'WHSE & LOGS'!$G$5:$R$5,'WHSE & LOGS'!W$6) -> 0 | X112: =SUMIFS($G112:$R112,'WHSE & LOGS'!$G$5:$R$5,'WHSE & LOGS'!X$6) -> 0
B113: Expired Stocks | C113: PHP | S113: =SUM(G113:R113) -> 0 | U113: =SUMIFS($G113:$R113,'WHSE & LOGS'!$G$5:$R$5,'WHSE & LOGS'!U$6) -> 0 | V113: =SUMIFS($G113:$R113,'WHSE & LOGS'!$G$5:$R$5,'WHSE & LOGS'!V$6) -> 0 | W113: =SUMIFS($G113:$R113,'WHSE & LOGS'!$G$5:$R$5,'WHSE & LOGS'!W$6) -> 0 | X113: =SUMIFS($G113:$R113,'WHSE & LOGS'!$G$5:$R$5,'WHSE & LOGS'!X$6) -> 0
B114: Total Inventory | C114: PHP | G114: =SUM(G109:G113) -> 0 | H114: =SUM(H109:H113) -> 0 | I114: =SUM(I109:I113) -> 0 | J114: =SUM(J109:J113) -> 0 | K114: =SUM(K109:K113) -> 0 | L114: =SUM(L109:L113) -> 0 | M114: =SUM(M109:M113) -> 0 | N114: =SUM(N109:N113) -> 0 | ... R114: =SUM(R109:R113) -> 0 | S114: =SUM(G114:R114) -> 0 | U114: =SUMIFS($G114:$R114,'WHSE & LOGS'!$G$5:$R$5,'WHSE & LOGS'!U$6) -> 0 | V114: =SUMIFS($G114:$R114,'WHSE & LOGS'!$G$5:$R$5,'WHSE & LOGS'!V$6) -> 0 | W114: =SUMIFS($G114:$R114,'WHSE & LOGS'!$G$5:$R$5,'WHSE & LOGS'!W$6) -> 0 | X114: =SUMIFS($G114:$R114,'WHSE & LOGS'!$G$5:$R$5,'WHSE & LOGS'!X$6) -> 0
B115: No. of Inventory days | C115: day/s | S115: =SUM(G115:R115) -> 0 | U115: =SUMIFS($G115:$R115,'WHSE & LOGS'!$G$5:$R$5,'WHSE & LOGS'!U$6) -> 0 | V115: =SUMIFS($G115:$R115,'WHSE & LOGS'!$G$5:$R$5,'WHSE & LOGS'!V$6) -> 0 | W115: =SUMIFS($G115:$R115,'WHSE & LOGS'!$G$5:$R$5,'WHSE & LOGS'!W$6) -> 0 | X115: =SUMIFS($G115:$R115,'WHSE & LOGS'!$G$5:$R$5,'WHSE & LOGS'!X$6) -> 0
A118: K. | B118: INVENTORY ACCURACY
B119: Finished Good Inventory Accuracy
B120: Total Count | C120: count | G120: 253 | H120: 151 | I120: 0 | J120: 0 | S120: =SUM(G120:R120) -> 404 | U120: =SUMIFS($G120:$R120,$G$5:$R$5,U$6) -> 404 | V120: =SUMIFS($G120:$R120,$G$5:$R$5,V$6) -> 0 | W120: =SUMIFS($G120:$R120,$G$5:$R$5,W$6) -> 0 | X120: =SUMIFS($G120:$R120,$G$5:$R$5,X$6) -> 0
...

Sheet PURCHASING
A1: PIONEER
A2: 2026 KPI TRACKER
A3: SC - PROCUREMENT
I5: Q1 | J5: Q1 | K5: Q1 | L5: Q2 | M5: Q2 | N5: Q2 | O5: Q3 | P5: Q3 | Q5: Q3 | R5: Q4 | S5: Q4 | T5: Q4
C6: UoM | E6: 2025 ACTUAL | G6: 2026 ABP | I6: OCT | J6: NOV | K6: DEC | L6: JAN | M6: FEB | N6: MAR | O6: APR | P6: MAY | Q6: JUN | R6: JUL | S6: AUG | T6: SEP | U6: 2026 YTD | X6: Q1 | Y6: Q2 | Z6: Q3 | AA6: Q4
A7: A. | B7: SAVINGS
B8: SAVINGS (Actual) | C8: Php | E8: 60470276 | G8: =SUM(I8:T8) -> 4447024.5 | I8: 2018550.4 | J8: 2428474.1 | U8: =SUM(I8:T8) -> 4447024.5
B9: SAVINGS (Target) | C9: Php | E9: 50000000 | G9: 40000000 | I9: =G9/12 -> 3333333.3 | J9: =G9/12 -> 3333333.3 | U9: =SUM(I9:T9) -> 6666666.7
B10: SAVINGS | C10: Php | E10: =IFERROR(E8/E9,0) -> 1.2094055 | G10: =IFERROR(G8/G9,0) -> 0.11117561 | I10: =IFERROR(I8/I9,0) -> 0.60556511 | J10: =IFERROR(J8/J9,0) -> 0.72854224 | K10: =IFERROR(K8/K9,0) -> 0 | L10: =IFERROR(L8/L9,0) -> 0 | M10: =IFERROR(M8/M9,0) -> 0 | N10: =IFERROR(N8/N9,0) -> 0 | O10: =IFERROR(O8/O9,0) -> 0 | P10: =IFERROR(P8/P9,0) -> 0 | ... U10: =IFERROR(U8/U9,0) -> 0.66705367
A12: B. | B12: P.O CONFORMANCE | C12: AFTER PR APPROVED
B13: Average P.O. Cycle Time | X13: =SUMIFS($I13:$T13,$I$5:$T$5,X$6) -> 0 | Y13: =SUMIFS($I13:$T13,$I$5:$T$5,Y$6) -> 0 | Z13: =SUMIFS($I13:$T13,$I$5:$T$5,Z$6) -> 0 | AA13: =SUMIFS($I13:$T13,$I$5:$T$5,AA$6) -> 0
B14: P.O for RM | C14: DAY | G14: 10 | U14: =IFERROR(AVERAGE(I14:T14),0) -> 0 | X14: =SUMIFS($I14:$T14,$I$6:$T$6,X$6) -> 0 | Y14: =SUMIFS($I14:$T14,$I$6:$T$6,Y$6) -> 0 | Z14: =SUMIFS($I14:$T14,$I$6:$T$6,Z$6) -> 0 | AA14: =SUMIFS($I14:$T14,$I$6:$T$6,AA$6) -> 0
B15: P.O for PM | C15: DAY | G15: 10 | U15: =IFERROR(AVERAGE(I15:T15),0) -> 0 | X15: =SUMIFS($I15:$T15,$I$6:$T$6,X$6) -> 0 | Y15: =SUMIFS($I15:$T15,$I$6:$T$6,Y$6) -> 0 | Z15: =SUMIFS($I15:$T15,$I$6:$T$6,Z$6) -> 0 | AA15: =SUMIFS($I15:$T15,$I$6:$T$6,AA$6) -> 0
B16: P.O for MRO | C16: DAY | G16: 21 | U16: =IFERROR(AVERAGE(I16:T16),0) -> 0 | X16: =SUMIFS($I16:$T16,$I$6:$T$6,X$6) -> 0 | Y16: =SUMIFS($I16:$T16,$I$6:$T$6,Y$6) -> 0 | Z16: =SUMIFS($I16:$T16,$I$6:$T$6,Z$6) -> 0 | AA16: =SUMIFS($I16:$T16,$I$6:$T$6,AA$6) -> 0
B17: P.O for MARKETING | C17: DAY | G17: 21 | U17: =IFERROR(AVERAGE(I17:T17),0) -> 0 | X17: =SUMIFS($I17:$T17,$I$6:$T$6,X$6) -> 0 | Y17: =SUMIFS($I17:$T17,$I$6:$T$6,Y$6) -> 0 | Z17: =SUMIFS($I17:$T17,$I$6:$T$6,Z$6) -> 0 | AA17: =SUMIFS($I17:$T17,$I$6:$T$6,AA$6) -> 0
B19: P.O. Accuracy
B20: Total number of P.O. | C20: count | U20: =SUM(I20:T20) -> 0 | X20: =SUMIFS($I20:$T20,$I$6:$T$6,X$6) -> 0 | Y20: =SUMIFS($I20:$T20,$I$6:$T$6,Y$6) -> 0 | Z20: =SUMIFS($I20:$T20,$I$6:$T$6,Z$6) -> 0 | AA20: =SUMIFS($I20:$T20,$I$6:$T$6,AA$6) -> 0
B21: # of erroneous delivery | C21: count | U21: =SUM(I21:T21) -> 0 | X21: =SUMIFS($I21:$T21,$I$6:$T$6,X$6) -> 0 | Y21: =SUMIFS($I21:$T21,$I$6:$T$6,Y$6) -> 0 | Z21: =SUMIFS($I21:$T21,$I$6:$T$6,Z$6) -> 0 | AA21: =SUMIFS($I21:$T21,$I$6:$T$6,AA$6) -> 0
B22: # of emergency P.O. | C22: count | U22: =SUM(I22:T22) -> 0 | X22: =SUMIFS($I22:$T22,$I$6:$T$6,X$6) -> 0 | Y22: =SUMIFS($I22:$T22,$I$6:$T$6,Y$6) -> 0 | Z22: =SUMIFS($I22:$T22,$I$6:$T$6,Z$6) -> 0 | AA22: =SUMIFS($I22:$T22,$I$6:$T$6,AA$6) -> 0
B23: Accuracy Rate | C23: % | E23: =IFERROR((E20-E21)/E20,0) -> 0 | G23: =IFERROR((G20-G21)/G20,0) -> 0 | I23: =IFERROR((I20-I21)/I20,0) -> 0 | J23: =IFERROR((J20-J21)/J20,0) -> 0 | K23: =IFERROR((K20-K21)/K20,0) -> 0 | L23: =IFERROR((L20-L21)/L20,0) -> 0 | M23: =IFERROR((M20-M21)/M20,0) -> 0 | N23: =IFERROR((N20-N21)/N20,0) -> 0 | O23: =IFERROR((O20-O21)/O20,0) -> 0 | P23: =IFERROR((P20-P21)/P20,0) -> 0 | ... U23: =IFERROR((U20-U21)/U20,0) -> 0 | X23: =IFERROR((X20-X21)/X20,0) -> 0 | Y23: =IFERROR((Y20-Y21)/Y20,0) -> 0 | Z23: =IFERROR((Z20-Z21)/Z20,0) -> 0 | AA23: =IFERROR((AA20-AA21)/AA20,0) -> 0
B24: Emergency Purchase ratio | C24: % | E24: =IFERROR((E20-E22)/E20,0) -> 0 | G24: =IFERROR((G20-G22)/G20,0) -> 0 | I24: =IFERROR((I20-I22)/I20,0) -> 0 | J24: =IFERROR((J20-J22)/J20,0) -> 0 | K24: =IFERROR((K20-K22)/K20,0) -> 0 | L24: =IFERROR((L20-L22)/L20,0) -> 0 | M24: =IFERROR((M20-M22)/M20,0) -> 0 | N24: =IFERROR((N20-N22)/N20,0) -> 0 | O24: =IFERROR((O20-O22)/O20,0) -> 0 | P24: =IFERROR((P20-P22)/P20,0) -> 0 | ... U24: =IFERROR((U20-U22)/U20,0) -> 0 | X24: =IFERROR((X20-X22)/X20,0) -> 0 | Y24: =IFERROR((Y20-Y22)/Y20,0) -> 0 | Z24: =IFERROR((Z20-Z22)/Z20,0) -> 0 | AA24: =IFERROR((AA20-AA22)/AA20,0) -> 0
A26: C. | B26: RM/PM PRICE ANALYSIS
B27: RM | V27: Actual vs last purchase | W27: Actual vs budget
B28: CHEM EPOXY RESIN 8 | C28: PHP | E28: 106.5 | F28: 1 | G28: 120.7 | U28: =IFERROR(AVERAGE(I28:T28),0) -> 0 | V28: =IFERROR(U28/E28,0)-1 -> -1 | W28: =IFERROR(U28/G28,0)-1 -> -1 | X28: =SUMIFS($I28:$T28,$I$6:$T$6,X$6) -> 0 | Y28: =SUMIFS($I28:$T28,$I$6:$T$6,Y$6) -> 0 | Z28: =SUMIFS($I28:$T28,$I$6:$T$6,Z$6) -> 0 | AA28: =SUMIFS($I28:$T28,$I$6:$T$6,AA$6) -> 0
B29: CHEM HARDENER PA 7 | C29: PHP | E29: 216.3 | G29: 247.1 | U29: =IFERROR(AVERAGE(I29:T29),0) -> 0 | V29: =IFERROR(U29/E29,0)-1 -> -1 | W29: =IFERROR(U29/G29,0)-1 -> -1 | X29: =SUMIFS($I29:$T29,$I$6:$T$6,X$6) -> 0 | Y29: =SUMIFS($I29:$T29,$I$6:$T$6,Y$6) -> 0 | Z29: =SUMIFS($I29:$T29,$I$6:$T$6,Z$6) -> 0 | AA29: =SUMIFS($I29:$T29,$I$6:$T$6,AA$6) -> 0
B30: CHEM HARDENER PA 9 | C30: PHP | E30: 221.9 | G30: 245 | U30: =IFERROR(AVERAGE(I30:T30),0) -> 0 | V30: =IFERROR(U30/E30,0)-1 -> -1 | W30: =IFERROR(U30/G30,0)-1 -> -1 | X30: =SUMIFS($I30:$T30,$I$6:$T$6,X$6) -> 0 | Y30: =SUMIFS($I30:$T30,$I$6:$T$6,Y$6) -> 0 | Z30: =SUMIFS($I30:$T30,$I$6:$T$6,Z$6) -> 0 | AA30: =SUMIFS($I30:$T30,$I$6:$T$6,AA$6) -> 0
B31: CHEM EPOXY RESIN 4 | C31: PHP | E31: 136.6 | G31: 152.49 | U31: =IFERROR(AVERAGE(I31:T31),0) -> 0 | V31: =IFERROR(U31/E31,0)-1 -> -1 | W31: =IFERROR(U31/G31,0)-1 -> -1 | X31: =SUMIFS($I31:$T31,$I$6:$T$6,X$6) -> 0 | Y31: =SUMIFS($I31:$T31,$I$6:$T$6,Y$6) -> 0 | Z31: =SUMIFS($I31:$T31,$I$6:$T$6,Z$6) -> 0 | AA31: =SUMIFS($I31:$T31,$I$6:$T$6,AA$6) -> 0
B32: CHEM RUBBER 2 | C32: PHP | E32: 284.3 | G32: 311.9 | U32: =IFERROR(AVERAGE(I32:T32),0) -> 0 | V32: =IFERROR(U32/E32,0)-1 -> -1 | W32: =IFERROR(U32/G32,0)-1 -> -1 | X32: =SUMIFS($I32:$T32,$I$6:$T$6,X$6) -> 0 | Y32: =SUMIFS($I32:$T32,$I$6:$T$6,Y$6) -> 0 | Z32: =SUMIFS($I32:$T32,$I$6:$T$6,Z$6) -> 0 | AA32: =SUMIFS($I32:$T32,$I$6:$T$6,AA$6) -> 0
B33: CHEM HARDENER AM 1 | C33: PHP | E33: 268.3 | U33: =IFERROR(AVERAGE(I33:T33),0) -> 0 | V33: =IFERROR(U33/E33,0)-1 -> -1 | W33: =IFERROR(U33/G33,0)-1 -> -1 | X33: =SUMIFS($I33:$T33,$I$6:$T$6,X$6) -> 0 | Y33: =SUMIFS($I33:$T33,$I$6:$T$6,Y$6) -> 0 | Z33: =SUMIFS($I33:$T33,$I$6:$T$6,Z$6) -> 0 | AA33: =SUMIFS($I33:$T33,$I$6:$T$6,AA$6) -> 0
B34: CHEM SOLVENT 15 | C34: PHP | U34: =IFERROR(AVERAGE(I34:T34),0) -> 0 | V34: =IFERROR(U34/E34,0)-1 -> -1 | W34: =IFERROR(U34/G34,0)-1 -> -1 | X34: =SUMIFS($I34:$T34,$I$6:$T$6,X$6) -> 0 | Y34: =SUMIFS($I34:$T34,$I$6:$T$6,Y$6) -> 0 | Z34: =SUMIFS($I34:$T34,$I$6:$T$6,Z$6) -> 0 | AA34: =SUMIFS($I34:$T34,$I$6:$T$6,AA$6) -> 0
B35: CHEM TACKIFIER RESIN 7 | C35: PHP | U35: =IFERROR(AVERAGE(I35:T35),0) -> 0 | V35: =IFERROR(U35/E35,0)-1 -> -1 | W35: =IFERROR(U35/G35,0)-1 -> -1 | X35: =SUMIFS($I35:$T35,$I$6:$T$6,X$6) -> 0 | Y35: =SUMIFS($I35:$T35,$I$6:$T$6,Y$6) -> 0 | Z35: =SUMIFS($I35:$T35,$I$6:$T$6,Z$6) -> 0 | AA35: =SUMIFS($I35:$T35,$I$6:$T$6,AA$6) -> 0
B36: CHEM FILLER CLAY 10 | C36: PHP | U36: =IFERROR(AVERAGE(I36:T36),0) -> 0 | V36: =IFERROR(U36/E36,0)-1 -> -1 | W36: =IFERROR(U36/G36,0)-1 -> -1 | X36: =SUMIFS($I36:$T36,$I$6:$T$6,X$6) -> 0 | Y36: =SUMIFS($I36:$T36,$I$6:$T$6,Y$6) -> 0 | Z36: =SUMIFS($I36:$T36,$I$6:$T$6,Z$6) -> 0 | AA36: =SUMIFS($I36:$T36,$I$6:$T$6,AA$6) -> 0
B37: CHEM EPOXY RESIN 5 | C37: PHP | U37: =IFERROR(AVERAGE(I37:T37),0) -> 0 | V37: =IFERROR(U37/E37,0)-1 -> -1 | W37: =IFERROR(U37/G37,0)-1 -> -1 | X37: =SUMIFS($I37:$T37,$I$6:$T$6,X$6) -> 0 | Y37: =SUMIFS($I37:$T37,$I$6:$T$6,Y$6) -> 0 | Z37: =SUMIFS($I37:$T37,$I$6:$T$6,Z$6) -> 0 | AA37: =SUMIFS($I37:$T37,$I$6:$T$6,AA$6) -> 0
B38: CHEM EMULSION SA 1 | C38: PHP | U38: =IFERROR(AVERAGE(I38:T38),0) -> 0 | V38: =IFERROR(U38/E38,0)-1 -> -1 | W38: =IFERROR(U38/G38,0)-1 -> -1 | X38: =SUMIFS($I38:$T38,$I$6:$T$6,X$6) -> 0 | Y38: =SUMIFS($I38:$T38,$I$6:$T$6,Y$6) -> 0 | Z38: =SUMIFS($I38:$T38,$I$6:$T$6,Z$6) -> 0 | AA38: =SUMIFS($I38:$T38,$I$6:$T$6,AA$6) -> 0
B39: CHEM CYANO 5 | C39: PHP | U39: =IFERROR(AVERAGE(I39:T39),0) -> 0 | V39: =IFERROR(U39/E39,0)-1 -> -1 | W39: =IFERROR(U39/G39,0)-1 -> -1 | X39: =SUMIFS($I39:$T39,$I$6:$T$6,X$6) -> 0 | Y39: =SUMIFS($I39:$T39,$I$6:$T$6,Y$6) -> 0 | Z39: =SUMIFS($I39:$T39,$I$6:$T$6,Z$6) -> 0 | AA39: =SUMIFS($I39:$T39,$I$6:$T$6,AA$6) -> 0
B40: CHEM CONTACT CEMENT 1 | C40: PHP | U40: =IFERROR(AVERAGE(I40:T40),0) -> 0 | V40: =IFERROR(U40/E40,0)-1 -> -1 | W40: =IFERROR(U40/G40,0)-1 -> -1 | X40: =SUMIFS($I40:$T40,$I$6:$T$6,X$6) -> 0 | Y40: =SUMIFS($I40:$T40,$I$6:$T$6,Y$6) -> 0 | Z40: =SUMIFS($I40:$T40,$I$6:$T$6,Z$6) -> 0 | AA40: =SUMIFS($I40:$T40,$I$6:$T$6,AA$6) -> 0
B41: CHEM TACKIFIER RESIN 6 | C41: PHP | U41: =IFERROR(AVERAGE(I41:T41),0) -> 0 | V41: =IFERROR(U41/E41,0)-1 -> -1 | W41: =IFERROR(U41/G41,0)-1 -> -1 | X41: =SUMIFS($I41:$T41,$I$6:$T$6,X$6) -> 0 | Y41: =SUMIFS($I41:$T41,$I$6:$T$6,Y$6) -> 0 | Z41: =SUMIFS($I41:$T41,$I$6:$T$6,Z$6) -> 0 | AA41: =SUMIFS($I41:$T41,$I$6:$T$6,AA$6) -> 0
B42: CHEM - FILLER CALCIUM 39 | C42: PHP | U42: =IFERROR(AVERAGE(I42:T42),0) -> 0 | V42: =IFERROR(U42/E42,0)-1 -> -1 | W42: =IFERROR(U42/G42,0)-1 -> -1 | X42: =SUMIFS($I42:$T42,$I$6:$T$6,X$6) -> 0 | Y42: =SUMIFS($I42:$T42,$I$6:$T$6,Y$6) -> 0 | Z42: =SUMIFS($I42:$T42,$I$6:$T$6,Z$6) -> 0 | AA42: =SUMIFS($I42:$T42,$I$6:$T$6,AA$6) -> 0
B43: CHEM SOLVENT 7 | C43: PHP | U43: =IFERROR(AVERAGE(I43:T43),0) -> 0 | V43: =IFERROR(U43/E43,0)-1 -> -1 | W43: =IFERROR(U43/G43,0)-1 -> -1 | X43: =SUMIFS($I43:$T43,$I$6:$T$6,X$6) -> 0 | Y43: =SUMIFS($I43:$T43,$I$6:$T$6,Y$6) -> 0 | Z43: =SUMIFS($I43:$T43,$I$6:$T$6,Z$6) -> 0 | AA43: =SUMIFS($I43:$T43,$I$6:$T$6,AA$6) -> 0
B44: CHEM ALKYD RESIN 5 | C44: PHP | U44: =IFERROR(AVERAGE(I44:T44),0) -> 0 | V44: =IFERROR(U44/E44,0)-1 -> -1 | W44: =IFERROR(U44/G44,0)-1 -> -1 | X44: =SUMIFS($I44:$T44,$I$6:$T$6,X$6) -> 0 | Y44: =SUMIFS($I44:$T44,$I$6:$T$6,Y$6) -> 0 | Z44: =SUMIFS($I44:$T44,$I$6:$T$6,Z$6) -> 0 | AA44: =SUMIFS($I44:$T44,$I$6:$T$6,AA$6) -> 0
B45: CHEM COLORANT WHITE 29 | C45: PHP | U45: =IFERROR(AVERAGE(I45:T45),0) -> 0 | V45: =IFERROR(U45/E45,0)-1 -> -1 | W45: =IFERROR(U45/G45,0)-1 -> -1 | X45: =SUMIFS($I45:$T45,$I$6:$T$6,X$6) -> 0 | Y45: =SUMIFS($I45:$T45,$I$6:$T$6,Y$6) -> 0 | Z45: =SUMIFS($I45:$T45,$I$6:$T$6,Z$6) -> 0 | AA45: =SUMIFS($I45:$T45,$I$6:$T$6,AA$6) -> 0
... B50: CHEM HARDENER PA 2 | C50: PHP | U50: =IFERROR(AVERAGE(I50:T50),0) -> 0 | V50: =IFERROR(U50/E50,0)-1 -> -1 | W50: =IFERROR(U50/G50,0)-1 -> -1 | X50: =SUMIFS($I50:$T50,$I$6:$T$6,X$6) -> 0 | Y50: =SUMIFS($I50:$T50,$I$6:$T$6,Y$6) -> 0 | Z50: =SUMIFS($I50:$T50,$I$6:$T$6,Z$6) -> 0 | AA50: =SUMIFS($I50:$T50,$I$6:$T$6,AA$6) -> 0
B51: PM | V51: Actual vs last purchase | W51: Actual vs budget
B52: T.CAN-1/4 PINT | C52: PHP | U52: =IFERROR(AVERAGE(I52:T52),0) -> 0 | V52: =IFERROR(U52/E52,0)-1 -> -1 | W52: =IFERROR(U52/G52,0)-1 -> -1 | X52: =SUMIFS($I52:$T52,$I$6:$T$6,X$6) -> 0 | Y52: =SUMIFS($I52:$T52,$I$6:$T$6,Y$6) -> 0 | Z52: =SUMIFS($I52:$T52,$I$6:$T$6,Z$6) -> 0 | AA52: =SUMIFS($I52:$T52,$I$6:$T$6,AA$6) -> 0
B53: T.CAN-QUART | C53: PHP | U53: =IFERROR(AVERAGE(I53:T53),0) -> 0 | V53: =IFERROR(U53/E53,0)-1 -> -1 | W53: =IFERROR(U53/G53,0)-1 -> -1 | X53: =SUMIFS($I53:$T53,$I$6:$T$6,X$6) -> 0 | Y53: =SUMIFS($I53:$T53,$I$6:$T$6,Y$6) -> 0 | Z53: =SUMIFS($I53:$T53,$I$6:$T$6,Z$6) -> 0 | AA53: =SUMIFS($I53:$T53,$I$6:$T$6,AA$6) -> 0
B54: T.CAN-GALLON W/ HANDLE | C54: PHP | U54: =IFERROR(AVERAGE(I54:T54),0) -> 0 | V54: =IFERROR(U54/E54,0)-1 -> -1 | W54: =IFERROR(U54/G54,0)-1 -> -1 | X54: =SUMIFS($I54:$T54,$I$6:$T$6,X$6) -> 0 | Y54: =SUMIFS($I54:$T54,$I$6:$T$6,Y$6) -> 0 | Z54: =SUMIFS($I54:$T54,$I$6:$T$6,Z$6) -> 0 | AA54: =SUMIFS($I54:$T54,$I$6:$T$6,AA$6) -> 0
B55: T.CAN-1/2 PINT | C55: PHP | U55: =IFERROR(AVERAGE(I55:T55),0) -> 0 | V55: =IFERROR(U55/E55,0)-1 -> -1 | W55: =IFERROR(U55/G55,0)-1 -> -1 | X55: =SUMIFS($I55:$T55,$I$6:$T$6,X$6) -> 0 | Y55: =SUMIFS($I55:$T55,$I$6:$T$6,Y$6) -> 0 | Z55: =SUMIFS($I55:$T55,$I$6:$T$6,Z$6) -> 0 | AA55: =SUMIFS($I55:$T55,$I$6:$T$6,AA$6) -> 0
B56: T.CAN-PINT | C56: PHP | U56: =IFERROR(AVERAGE(I56:T56),0) -> 0 | V56: =IFERROR(U56/E56,0)-1 -> -1 | W56: =IFERROR(U56/G56,0)-1 -> -1 | X56: =SUMIFS($I56:$T56,$I$6:$T$6,X$6) -> 0 | Y56: =SUMIFS($I56:$T56,$I$6:$T$6,Y$6) -> 0 | Z56: =SUMIFS($I56:$T56,$I$6:$T$6,Z$6) -> 0 | AA56: =SUMIFS($I56:$T56,$I$6:$T$6,AA$6) -> 0
B57: CARTRIDGE-UNPRINTED PAPER | C57: PHP | U57: =IFERROR(AVERAGE(I57:T57),0) -> 0 | V57: =IFERROR(U57/E57,0)-1 -> -1 | W57: =IFERROR(U57/G57,0)-1 -> -1 | X57: =SUMIFS($I57:$T57,$I$6:$T$6,X$6) -> 0 | Y57: =SUMIFS($I57:$T57,$I$6:$T$6,Y$6) -> 0 | Z57: =SUMIFS($I57:$T57,$I$6:$T$6,Z$6) -> 0 | AA57: =SUMIFS($I57:$T57,$I$6:$T$6,AA$6) -> 0
B58: A.TUBE-M.BOND 1 SHOT W/O CAP | C58: PHP | U58: =IFERROR(AVERAGE(I58:T58),0) -> 0 | V58: =IFERROR(U58/E58,0)-1 -> -1 | W58: =IFERROR(U58/G58,0)-1 -> -1 | X58: =SUMIFS($I58:$T58,$I$6:$T$6,X$6) -> 0 | Y58: =SUMIFS($I58:$T58,$I$6:$T$6,Y$6) -> 0 | Z58: =SUMIFS($I58:$T58,$I$6:$T$6,Z$6) -> 0 | AA58: =SUMIFS($I58:$T58,$I$6:$T$6,AA$6) -> 0
B59: T.CAN-4 LITERS ROUND | C59: PHP | U59: =IFERROR(AVERAGE(I59:T59),0) -> 0 | V59: =IFERROR(U59/E59,0)-1 -> -1 | W59: =IFERROR(U59/G59,0)-1 -> -1 | X59: =SUMIFS($I59:$T59,$I$6:$T$6,X$6) -> 0 | Y59: =SUMIFS($I59:$T59,$I$6:$T$6,Y$6) -> 0 | Z59: =SUMIFS($I59:$T59,$I$6:$T$6,Z$6) -> 0 | AA59: =SUMIFS($I59:$T59,$I$6:$T$6,AA$6) -> 0
B60: A.TUBE-M.BOND 3G (13.5MM) W/O | C60: PHP | U60: =IFERROR(AVERAGE(I60:T60),0) -> 0 | V60: =IFERROR(U60/E60,0)-1 -> -1 | W60: =IFERROR(U60/G60,0)-1 -> -1 | X60: =SUMIFS($I60:$T60,$I$6:$T$6,X$6) -> 0 | Y60: =SUMIFS($I60:$T60,$I$6:$T$6,Y$6) -> 0 | Z60: =SUMIFS($I60:$T60,$I$6:$T$6,Z$6) -> 0 | AA60: =SUMIFS($I60:$T60,$I$6:$T$6,AA$6) -> 0
B61: T.CAN-1 LITER | C61: PHP | U61: =IFERROR(AVERAGE(I61:T61),0) -> 0 | V61: =IFERROR(U61/E61,0)-1 -> -1 | W61: =IFERROR(U61/G61,0)-1 -> -1 | X61: =SUMIFS($I61:$T61,$I$6:$T$6,X$6) -> 0 | Y61: =SUMIFS($I61:$T61,$I$6:$T$6,Y$6) -> 0 | Z61: =SUMIFS($I61:$T61,$I$6:$T$6,Z$6) -> 0 | AA61: =SUMIFS($I61:$T61,$I$6:$T$6,AA$6) -> 0
B62: CAP & NOZZLE - M. BOND 1G | C62: PHP | U62: =IFERROR(AVERAGE(I62:T62),0) -> 0 | V62: =IFERROR(U62/E62,0)-1 -> -1 | W62: =IFERROR(U62/G62,0)-1 -> -1 | X62: =SUMIFS($I62:$T62,$I$6:$T$6,X$6) -> 0 | Y62: =SUMIFS($I62:$T62,$I$6:$T$6,Y$6) -> 0 | Z62: =SUMIFS($I62:$T62,$I$6:$T$6,Z$6) -> 0 | AA62: =SUMIFS($I62:$T62,$I$6:$T$6,AA$6) -> 0
B63: POUCH-ELASTOSEAL PISIL 250G | C63: PHP | U63: =IFERROR(AVERAGE(I63:T63),0) -> 0 | V63: =IFERROR(U63/E63,0)-1 -> -1 | W63: =IFERROR(U63/G63,0)-1 -> -1 | X63: =SUMIFS($I63:$T63,$I$6:$T$6,X$6) -> 0 | Y63: =SUMIFS($I63:$T63,$I$6:$T$6,Y$6) -> 0 | Z63: =SUMIFS($I63:$T63,$I$6:$T$6,Z$6) -> 0 | AA63: =SUMIFS($I63:$T63,$I$6:$T$6,AA$6) -> 0
... B71: T.CAN-1/4 PINT PART B NON-SAG EPOXY PRINTED FOR PT PAI INDO | C71: PHP | U71: =IFERROR(AVERAGE(I71:T71),0) -> 0 | V71: =IFERROR(U71/E71,0)-1 -> -1 | W71: =IFERROR(U71/G71,0)-1 -> -1 | X71: =SUMIFS($I71:$T71,$I$6:$T$6,X$6) -> 0 | Y71: =SUMIFS($I71:$T71,$I$6:$T$6,Y$6) -> 0 | Z71: =SUMIFS($I71:$T71,$I$6:$T$6,Z$6) -> 0 | AA71: =SUMIFS($I71:$T71,$I$6:$T$6,AA$6) -> 0
A73: D. | B73: MANPOWER PLAN
B74: Headcount
B75: Regular | C75: count | U75: {=IFERROR(LOOKUP(2,1/(I75:T75<>""),I75:T75),0)} -> 0
B76: Agency | C76: count | U76: {=IFERROR(LOOKUP(2,1/(I76:T76<>""),I76:T76),0)} -> 0
B77: TOTAL HEADCOUNT | C77: count | E77: =SUM(E75:E76) -> 0 | G77: =SUM(G75:G76) -> 0 | I77: =SUM(I75:I76) -> 0 | J77: =SUM(J75:J76) -> 0 | K77: =SUM(K75:K76) -> 0 | L77: =SUM(L75:L76) -> 0 | M77: =SUM(M75:M76) -> 0 | N77: =SUM(N75:N76) -> 0 | O77: =SUM(O75:O76) -> 0 | P77: =SUM(P75:P76) -> 0 | ... U77: =SUM(U75:U76) -> 0 | W77: =SUM(W75:W76) -> 0 | X77: =SUM(X75:X76) -> 0 | Y77: =SUM(Y75:Y76) -> 0 | Z77: =SUM(Z75:Z76) -> 0
B79: Resigned Employee | C79: count | U79: =SUM(I79:T79) -> 0
B80: Attrition Rate | C80: % | I80: =IFERROR(I79/((I77+G77)/2),0) -> 0 | J80: =IFERROR(J79/((J77+I77)/2),0) -> 0 | K80: =IFERROR(K79/((K77+J77)/2),0) -> 0 | L80: =IFERROR(L79/((L77+K77)/2),0) -> 0 | M80: =IFERROR(M79/((M77+L77)/2),0) -> 0 | N80: =IFERROR(N79/((N77+M77)/2),0) -> 0 | O80: =IFERROR(O79/((O77+N77)/2),0) -> 0 | P80: =IFERROR(P79/((P77+O77)/2),0) -> 0 | Q80: =IFERROR(Q79/((Q77+P77)/2),0) -> 0 | ... T80: =IFERROR(T79/((T77+S77)/2),0) -> 0 | U80: =IFERROR(U79/((U77+G77)/2),0) -> 0 | W80: =IFERROR(AVERAGE(I80:K80),0) -> 0 | X80: =IFERROR(AVERAGE(L80:N80),0) -> 0 | Y80: =IFERROR(AVERAGE(O80:Q80),0) -> 0 | Z80: =IFERROR(AVERAGE(R80:T80),0) -> 0
B82: Manhours
B83: Regular | C83: HRS | U83: =SUM(I83:T83) -> 0 | W83: =SUMIFS($I83:$T83,$I$6:$T$6,X$6) -> 0 | X83: =SUMIFS($I83:$T83,$I$6:$T$6,Y$6) -> 0 | Y83: =SUMIFS($I83:$T83,$I$6:$T$6,Z$6) -> 0 | Z83: =SUMIFS($I83:$T83,$I$6:$T$6,AA$6) -> 0
B84: Agency | C84: HRS | U84: =SUM(I84:T84) -> 0 | W84: =SUMIFS($I84:$T84,$I$6:$T$6,X$6) -> 0 | X84: =SUMIFS($I84:$T84,$I$6:$T$6,Y$6) -> 0 | Y84: =SUMIFS($I84:$T84,$I$6:$T$6,Z$6) -> 0 | Z84: =SUMIFS($I84:$T84,$I$6:$T$6,AA$6) -> 0
B85: TOTAL MANHOURS | C85: HRS | E85: =SUM(E83:E84) -> 0 | G85: =SUM(G83:G84) -> 0 | I85: =SUM(I83:I84) -> 0 | J85: =SUM(J83:J84) -> 0 | K85: =SUM(K83:K84) -> 0 | L85: =SUM(L83:L84) -> 0 | M85: =SUM(M83:M84) -> 0 | N85: =SUM(N83:N84) -> 0 | O85: =SUM(O83:O84) -> 0 | P85: =SUM(P83:P84) -> 0 | ... U85: =SUM(U83:U84) -> 0 | W85: =SUM(W83:W84) -> 0 | X85: =SUM(X83:X84) -> 0 | Y85: =SUM(Y83:Y84) -> 0 | Z85: =SUM(Z83:Z84) -> 0
B87: Overtime Hours | C87: HRS | U87: =SUM(I87:T87) -> 0 | W87: =SUMIFS($I87:$T87,$I$6:$T$6,X$6) -> 0 | X87: =SUMIFS($I87:$T87,$I$6:$T$6,Y$6) -> 0 | Y87: =SUMIFS($I87:$T87,$I$6:$T$6,Z$6) -> 0 | Z87: =SUMIFS($I87:$T87,$I$6:$T$6,AA$6) -> 0
B88: Overtime Rate | C88: % | E88: =IFERROR(E87/E85,0) -> 0 | G88: =IFERROR(G87/G85,0) -> 0 | I88: =IFERROR(I87/I85,0) -> 0 | J88: =IFERROR(J87/J85,0) -> 0 | K88: =IFERROR(K87/K85,0) -> 0 | L88: =IFERROR(L87/L85,0) -> 0 | M88: =IFERROR(M87/M85,0) -> 0 | N88: =IFERROR(N87/N85,0) -> 0 | O88: =IFERROR(O87/O85,0) -> 0 | P88: =IFERROR(P87/P85,0) -> 0 | ... U88: =IFERROR(U87/U85,0) -> 0 | W88: =IFERROR(W87/W85,0) -> 0 | X88: =IFERROR(X87/X85,0) -> 0 | Y88: =IFERROR(Y87/Y85,0) -> 0 | Z88: =IFERROR(Z87/Z85,0) -> 0
B90: Absences
B91: # of Absences | C91: count | U91: =SUM(I91:T91) -> 0 | W91: =SUMIFS($I91:$T91,$I$6:$T$6,X$6) -> 0 | X91: =SUMIFS($I91:$T91,$I$6:$T$6,Y$6) -> 0 | Y91: =SUMIFS($I91:$T91,$I$6:$T$6,Z$6) -> 0 | Z91: =SUMIFS($I91:$T91,$I$6:$T$6,AA$6) -> 0
B92: # of Required working days | C92: count | U92: =SUM(I92:T92) -> 0 | W92: =SUMIFS($I92:$T92,$I$6:$T$6,X$6) -> 0 | X92: =SUMIFS($I92:$T92,$I$6:$T$6,Y$6) -> 0 | Y92: =SUMIFS($I92:$T92,$I$6:$T$6,Z$6) -> 0 | Z92: =SUMIFS($I92:$T92,$I$6:$T$6,AA$6) -> 0
B93: Absenteeism Rate | C93: % | E93: =IFERROR(E91/E92,0) -> 0 | G93: =IFERROR(G91/G92,0) -> 0 | I93: =IFERROR(I91/I92,0) -> 0 | J93: =IFERROR(J91/J92,0) -> 0 | K93: =IFERROR(K91/K92,0) -> 0 | L93: =IFERROR(L91/L92,0) -> 0 | M93: =IFERROR(M91/M92,0) -> 0 | N93: =IFERROR(N91/N92,0) -> 0 | O93: =IFERROR(O91/O92,0) -> 0 | P93: =IFERROR(P91/P92,0) -> 0 | ... U93: =IFERROR(U91/U92,0) -> 0 | W93: =IFERROR(W91/W92,0) -> 0 | X93: =IFERROR(X91/X92,0) -> 0 | Y93: =IFERROR(Y91/Y92,0) -> 0 | Z93: =IFERROR(Z91/Z92,0) -> 0

Sheet PRODUCTION
A1: PIONEER
A2: 2026 KPI TRACKER
A3: PRODUCTION
G5: Q1 | H5: Q1 | I5: Q1 | J5: Q2 | K5: Q2 | L5: Q2 | M5: Q3 | N5: Q3 | O5: Q3 | P5: Q4 | Q5: Q4 | R5: Q4
C6: UoM | E6: 2026 ABP | G6: OCT | H6: NOV | I6: DEC | J6: JAN | K6: FEB | L6: MAR | M6: APR | N6: MAY | O6: JUN | P6: JUL | Q6: AUG | R6: SEP | S6: 2026 YTD | U6: Q1 | V6: Q2 | W6: Q3 | X6: Q4
A7: A. | B7: MACHINE UTILIZATION - BY TIME
B8: SUMMARY OF ALL LINE
B9: Actual Productive Time | C9: HRS | E9: =E64+E118+E173+E228+E283+E338+E393+E448+E503+E558+E613+E668+E723+E778+E833+E862+E917 -> 0 | G9: =G64+G119+G174+G229+G284+G339+G394+G449+G504+G559+G614+G669+G724+G779+G863+G918 -> 5263.9167 | H9: =H64+H119+H174+H229+H284+H339+H394+H449+H504+H559+H614+H669+H724+H779+H863+H918 -> 6353.9167 | I9: =I64+I119+I174+I229+I284+I339+I394+I449+I504+I559+I614+I669+I724+I779+I863+I918 -> 4228.1667 | J9: =J64+J119+J174+J229+J284+J339+J394+J449+J504+J559+J614+J669+J724+J779+J863+J918 -> 0 | K9: =K64+K119+K174+K229+K284+K339+K394+K449+K504+K559+K614+K669+K724+K779+K863+K918 -> 0 | L9: =L64+L119+L174+L229+L284+L339+L394+L449+L504+L559+L614+L669+L724+L779+L863+L918 -> 0 | M9: =M64+M119+M174+M229+M284+M339+M394+M449+M504+M559+M614+M669+M724+M779+M863+M918 -> 0 | N9: =N64+N119+N174+N229+N284+N339+N394+N449+N504+N559+N614+N669+N724+N779+N863+N918 -> 0 | ... R9: =R64+R119+R174+R229+R284+R339+R394+R449+R504+R559+R614+R669+R724+R779+R863+R918 -> 0 | S9: =SUM(G9:R9) -> 15846 | U9: =SUMIFS($G9:$R9,$G$5:$R$5,U$6) -> 15846 | V9: =SUMIFS($G9:$R9,$G$5:$R$5,V$6) -> 0 | W9: =SUMIFS($G9:$R9,$G$5:$R$5,W$6) -> 0 | X9: =SUMIFS($G9:$R9,$G$5:$R$5,X$6) -> 0
B10: No Production Plan | C10: HRS | E10: =E65+E119+E174+E229+E284+E339+E394+E449+E504+E559+E614+E669+E724+E779+E834+E863+E918 -> 0 | G10: =G65+G120+G175+G230+G285+G340+G395+G450+G505+G560+G615+G670+G725+G781+G864+G919 -> 5350.9833 | H10: =H65+H120+H175+H230+H285+H340+H395+H450+H505+H560+H615+H670+H725+H781+H864+H919 -> 3808.05 | I10: =I65+I120+I175+I230+I285+I340+I395+I450+I505+I560+I615+I670+I725+I781+I864+I919 -> 1155.85 | J10: =J65+J120+J175+J230+J285+J340+J395+J450+J505+J560+J615+J670+J725+J781+J864+J919 -> 0 | K10: =K65+K120+K175+K230+K285+K340+K395+K450+K505+K560+K615+K670+K725+K781+K864+K919 -> 0 | L10: =L65+L120+L175+L230+L285+L340+L395+L450+L505+L560+L615+L670+L725+L781+L864+L919 -> 0 | M10: =M65+M120+M175+M230+M285+M340+M395+M450+M505+M560+M615+M670+M725+M781+M864+M919 -> 0 | N10: =N65+N120+N175+N230+N285+N340+N395+N450+N505+N560+N615+N670+N725+N781+N864+N919 -> 0 | ... R10: =R65+R120+R175+R230+R285+R340+R395+R450+R505+R560+R615+R670+R725+R781+R864+R919 -> 0 | S10: =SUM(G10:R10) -> 10314.883 | U10: =SUMIFS($G10:$R10,$G$5:$R$5,U$6) -> 10314.883 | V10: =SUMIFS($G10:$R10,$G$5:$R$5,V$6) -> 0 | W10: =SUMIFS($G10:$R10,$G$5:$R$5,W$6) -> 0 | X10: =SUMIFS($G10:$R10,$G$5:$R$5,X$6) -> 0
B11: No Head Count Allocation | C11: HRS | E11: =E66+E120+E175+E230+E285+E340+E395+E450+E505+E560+E615+E670+E725+E780+E835+E864+E919 -> 0 | G11: =G66+G121+G176+G231+G286+G341+G396+G451+G506+G561+G616+G671+G726+G782+G865+G920 -> 2996.7 | H11: =H66+H121+H176+H231+H286+H341+H396+H451+H506+H561+H616+H671+H726+H782+H865+H920 -> 3600.15 | I11: =I66+I121+I176+I231+I286+I341+I396+I451+I506+I561+I616+I671+I726+I782+I865+I920 -> 2839.7667 | J11: =J66+J121+J176+J231+J286+J341+J396+J451+J506+J561+J616+J671+J726+J782+J865+J920 -> 0 | K11: =K66+K121+K176+K231+K286+K341+K396+K451+K506+K561+K616+K671+K726+K782+K865+K920 -> 0 | L11: =L66+L121+L176+L231+L286+L341+L396+L451+L506+L561+L616+L671+L726+L782+L865+L920 -> 0 | M11: =M66+M121+M176+M231+M286+M341+M396+M451+M506+M561+M616+M671+M726+M782+M865+M920 -> 0 | N11: =N66+N121+N176+N231+N286+N341+N396+N451+N506+N561+N616+N671+N726+N782+N865+N920 -> 0 | ... R11: =R66+R121+R176+R231+R286+R341+R396+R451+R506+R561+R616+R671+R726+R782+R865+R920 -> 0 | S11: =SUM(G11:R11) -> 9436.6167 | U11: =SUMIFS($G11:$R11,$G$5:$R$5,U$6) -> 9436.6167 | V11: =SUMIFS($G11:$R11,$G$5:$R$5,V$6) -> 0 | W11: =SUMIFS($G11:$R11,$G$5:$R$5,W$6) -> 0 | X11: =SUMIFS($G11:$R11,$G$5:$R$5,X$6) -> 0
B12: Change Over Time | C12: HRS | E12: =E67+E121+E176+E231+E286+E341+E396+E451+E506+E561+E616+E671+E726+E781+E836+E865+E920 -> 0 | G12: =G67+G122+G177+G232+G287+G342+G397+G452+G507+G562+G617+G672+G727+G783+G866+G921 -> 294.6 | H12: =H67+H122+H177+H232+H287+H342+H397+H452+H507+H562+H617+H672+H727+H783+H866+H921 -> 389.28333 | I12: =I67+I122+I177+I232+I287+I342+I397+I452+I507+I562+I617+I672+I727+I783+I866+I921 -> 214.31667 | J12: =J67+J122+J177+J232+J287+J342+J397+J452+J507+J562+J617+J672+J727+J783+J866+J921 -> 0 | K12: =K67+K122+K177+K232+K287+K342+K397+K452+K507+K562+K617+K672+K727+K783+K866+K921 -> 0 | L12: =L67+L122+L177+L232+L287+L342+L397+L452+L507+L562+L617+L672+L727+L783+L866+L921 -> 0 | M12: =M67+M122+M177+M232+M287+M342+M397+M452+M507+M562+M617+M672+M727+M783+M866+M921 -> 0 | N12: =N67+N122+N177+N232+N287+N342+N397+N452+N507+N562+N617+N672+N727+N783+N866+N921 -> 0 | ... R12: =R67+R122+R177+R232+R287+R342+R397+R452+R507+R562+R617+R672+R727+R783+R866+R921 -> 0 | S12: =SUM(G12:R12) -> 898.2 | U12: =SUMIFS($G12:$R12,$G$5:$R$5,U$6) -> 898.2 | V12: =SUMIFS($G12:$R12,$G$5:$R$5,V$6) -> 0 | W12: =SUMIFS($G12:$R12,$G$5:$R$5,W$6) -> 0 | X12: =SUMIFS($G12:$R12,$G$5:$R$5,X$6) -> 0
B13: Meeting | C13: HRS | E13: =E68+E122+E177+E232+E287+E342+E397+E452+E507+E562+E617+E672+E727+E782+E837+E866+E921 -> 0 | G13: =G68+G123+G178+G233+G288+G343+G398+G453+G508+G563+G618+G673+G728+G784+G867+G922 -> 29.233333 | H13: =H68+H123+H178+H233+H288+H343+H398+H453+H508+H563+H618+H673+H728+H784+H867+H922 -> 28.133333 | I13: =I68+I123+I178+I233+I288+I343+I398+I453+I508+I563+I618+I673+I728+I784+I867+I922 -> 7.3333333 | J13: =J68+J123+J178+J233+J288+J343+J398+J453+J508+J563+J618+J673+J728+J784+J867+J922 -> 0 | K13: =K68+K123+K178+K233+K288+K343+K398+K453+K508+K563+K618+K673+K728+K784+K867+K922 -> 0 | L13: =L68+L123+L178+L233+L288+L343+L398+L453+L508+L563+L618+L673+L728+L784+L867+L922 -> 0 | M13: =M68+M123+M178+M233+M288+M343+M398+M453+M508+M563+M618+M673+M728+M784+M867+M922 -> 0 | N13: =N68+N123+N178+N233+N288+N343+N398+N453+N508+N563+N618+N673+N728+N784+N867+N922 -> 0 | ... R13: =R68+R123+R178+R233+R288+R343+R398+R453+R508+R563+R618+R673+R728+R784+R867+R922 -> 0 | S13: =SUM(G13:R13) -> 64.7 | U13: =SUMIFS($G13:$R13,$G$5:$R$5,U$6) -> 64.7 | V13: =SUMIFS($G13:$R13,$G$5:$R$5,V$6) -> 0 | W13: =SUMIFS($G13:$R13,$G$5:$R$5,W$6) -> 0 | X13: =SUMIFS($G13:$R13,$G$5:$R$5,X$6) -> 0
B14: Sanitation Time | C14: HRS | E14: =E69+E123+E178+E233+E288+E343+E398+E453+E508+E563+E618+E673+E728+E783+E838+E867+E922 -> 0 | G14: =G69+G124+G179+G234+G289+G344+G399+G454+G509+G564+G619+G674+G729+G785+G868+G923 -> 158.6 | H14: =H69+H124+H179+H234+H289+H344+H399+H454+H509+H564+H619+H674+H729+H785+H868+H923 -> 180.8 | I14: =I69+I124+I179+I234+I289+I344+I399+I454+I509+I564+I619+I674+I729+I785+I868+I923 -> 72.266667 | J14: =J69+J124+J179+J234+J289+J344+J399+J454+J509+J564+J619+J674+J729+J785+J868+J923 -> 0 | K14: =K69+K124+K179+K234+K289+K344+K399+K454+K509+K564+K619+K674+K729+K785+K868+K923 -> 0 | L14: =L69+L124+L179+L234+L289+L344+L399+L454+L509+L564+L619+L674+L729+L785+L868+L923 -> 0 | M14: =M69+M124+M179+M234+M289+M344+M399+M454+M509+M564+M619+M674+M729+M785+M868+M923 -> 0 | N14: =N69+N124+N179+N234+N289+N344+N399+N454+N509+N564+N619+N674+N729+N785+N868+N923 -> 0 | ... R14: =R69+R124+R179+R234+R289+R344+R399+R454+R509+R564+R619+R674+R729+R785+R868+R923 -> 0 | S14: =SUM(G14:R14) -> 411.66667 | U14: =SUMIFS($G14:$R14,$G$5:$R$5,U$6) -> 411.66667 | V14: =SUMIFS($G14:$R14,$G$5:$R$5,V$6) -> 0 | W14: =SUMIFS($G14:$R14,$G$5:$R$5,W$6) -> 0 | X14: =SUMIFS($G14:$R14,$G$5:$R$5,X$6) -> 0
B15: Start-up Time/Setup | C15: HRS | E15: =E70+E124+E179+E234+E289+E344+E399+E454+E509+E564+E619+E674+E729+E784+E839+E868+E923 -> 0 | G15: =G70+G125+G180+G235+G290+G345+G400+G455+G510+G565+G620+G675+G730+G786+G869+G924 -> 306.63333 | H15: =H70+H125+H180+H235+H290+H345+H400+H455+H510+H565+H620+H675+H730+H786+H869+H924 -> 375.71667 | I15: =I70+I125+I180+I235+I290+I345+I400+I455+I510+I565+I620+I675+I730+I786+I869+I924 -> 127.65 | J15: =J70+J125+J180+J235+J290+J345+J400+J455+J510+J565+J620+J675+J730+J786+J869+J924 -> 0 | K15: =K70+K125+K180+K235+K290+K345+K400+K455+K510+K565+K620+K675+K730+K786+K869+K924 -> 0 | L15: =L70+L125+L180+L235+L290+L345+L400+L455+L510+L565+L620+L675+L730+L786+L869+L924 -> 0 | M15: =M70+M125+M180+M235+M290+M345+M400+M455+M510+M565+M620+M675+M730+M786+M869+M924 -> 0 | N15: =N70+N125+N180+N235+N290+N345+N400+N455+N510+N565+N620+N675+N730+N786+N869+N924 -> 0 | ... R15: =R70+R125+R180+R235+R290+R345+R400+R455+R510+R565+R620+R675+R730+R786+R869+R924 -> 0 | S15: =SUM(G15:R15) -> 810 | U15: =SUMIFS($G15:$R15,$G$5:$R$5,U$6) -> 810 | V15: =SUMIFS($G15:$R15,$G$5:$R$5,V$6) -> 0 | W15: =SUMIFS($G15:$R15,$G$5:$R$5,W$6) -> 0 | X15: =SUMIFS($G15:$R15,$G$5:$R$5,X$6) -> 0
B16: Shutdown/cooldown | C16: HRS | E16: =E71+E125+E180+E235+E290+E345+E400+E455+E510+E565+E620+E675+E730+E785+E840+E869+E924 -> 0 | G16: =G71+G126+G181+G236+G291+G346+G401+G456+G511+G566+G621+G676+G731+G787+G870+G925 -> 0.83333333 | H16: =H71+H126+H181+H236+H291+H346+H401+H456+H511+H566+H621+H676+H731+H787+H870+H925 -> 0 | I16: =I71+I126+I181+I236+I291+I346+I401+I456+I511+I566+I621+I676+I731+I787+I870+I925 -> 0 | J16: =J71+J126+J181+J236+J291+J346+J401+J456+J511+J566+J621+J676+J731+J787+J870+J925 -> 0 | K16: =K71+K126+K181+K236+K291+K346+K401+K456+K511+K566+K621+K676+K731+K787+K870+K925 -> 0 | L16: =L71+L126+L181+L236+L291+L346+L401+L456+L511+L566+L621+L676+L731+L787+L870+L925 -> 0 | M16: =M71+M126+M181+M236+M291+M346+M401+M456+M511+M566+M621+M676+M731+M787+M870+M925 -> 0 | N16: =N71+N126+N181+N236+N291+N346+N401+N456+N511+N566+N621+N676+N731+N787+N870+N925 -> 0 | ... R16: =R71+R126+R181+R236+R291+R346+R401+R456+R511+R566+R621+R676+R731+R787+R870+R925 -> 0 | S16: =SUM(G16:R16) -> 0.83333333 | U16: =SUMIFS($G16:$R16,$G$5:$R$5,U$6) -> 0.83333333 | V16: =SUMIFS($G16:$R16,$G$5:$R$5,V$6) -> 0 | W16: =SUMIFS($G16:$R16,$G$5:$R$5,W$6) -> 0 | X16: =SUMIFS($G16:$R16,$G$5:$R$5,X$6) -> 0
B17: Testing Time | C17: HRS | E17: =E72+E126+E181+E236+E291+E346+E401+E456+E511+E566+E621+E676+E731+E786+E841+E870+E925 -> 0 | G17: =G72+G127+G182+G237+G292+G347+G402+G457+G512+G567+G622+G677+G732+G788+G871+G926 -> 118.1 | H17: =H72+H127+H182+H237+H292+H347+H402+H457+H512+H567+H622+H677+H732+H788+H871+H926 -> 176.15 | I17: =I72+I127+I182+I237+I292+I347+I402+I457+I512+I567+I622+I677+I732+I788+I871+I926 -> 8.4 | J17: =J72+J127+J182+J237+J292+J347+J402+J457+J512+J567+J622+J677+J732+J788+J871+J926 -> 0 | K17: =K72+K127+K182+K237+K292+K347+K402+K457+K512+K567+K622+K677+K732+K788+K871+K926 -> 0 | L17: =L72+L127+L182+L237+L292+L347+L402+L457+L512+L567+L622+L677+L732+L788+L871+L926 -> 0 | M17: =M72+M127+M182+M237+M292+M347+M402+M457+M512+M567+M622+M677+M732+M788+M871+M926 -> 0 | N17: =N72+N127+N182+N237+N292+N347+N402+N457+N512+N567+N622+N677+N732+N788+N871+N926 -> 0 | ... R17: =R72+R127+R182+R237+R292+R347+R402+R457+R512+R567+R622+R677+R732+R788+R871+R926 -> 0 | S17: =SUM(G17:R17) -> 302.65 | U17: =SUMIFS($G17:$R17,$G$5:$R$5,U$6) -> 302.65 | V17: =SUMIFS($G17:$R17,$G$5:$R$5,V$6) -> 0 | W17: =SUMIFS($G17:$R17,$G$5:$R$5,W$6) -> 0 | X17: =SUMIFS($G17:$R17,$G$5:$R$5,X$6) -> 0
B18: Breaktime | C18: HRS | E18: =E73+E127+E182+E237+E292+E347+E402+E457+E512+E567+E622+E677+E732+E787+E842+E871+E926 -> 0 | G18: =G73+G128+G183+G238+G293+G348+G403+G458+G513+G568+G623+G678+G733+G789+G872+G927 -> 276.4 | H18: =H73+H128+H183+H238+H293+H348+H403+H458+H513+H568+H623+H678+H733+H789+H872+H927 -> 350.36667 | I18: =I73+I128+I183+I238+I293+I348+I403+I458+I513+I568+I623+I678+I733+I789+I872+I927 -> 194.46667 | J18: =J73+J128+J183+J238+J293+J348+J403+J458+J513+J568+J623+J678+J733+J789+J872+J927 -> 0 | K18: =K73+K128+K183+K238+K293+K348+K403+K458+K513+K568+K623+K678+K733+K789+K872+K927 -> 0 | L18: =L73+L128+L183+L238+L293+L348+L403+L458+L513+L568+L623+L678+L733+L789+L872+L927 -> 0 | M18: =M73+M128+M183+M238+M293+M348+M403+M458+M513+M568+M623+M678+M733+M789+M872+M927 -> 0 | N18: =N73+N128+N183+N238+N293+N348+N403+N458+N513+N568+N623+N678+N733+N789+N872+N927 -> 0 | ... R18: =R73+R128+R183+R238+R293+R348+R403+R458+R513+R568+R623+R678+R733+R789+R872+R927 -> 0 | S18: =SUM(G18:R18) -> 821.23333 | U18: =SUMIFS($G18:$R18,$G$5:$R$5,U$6) -> 821.23333 | V18: =SUMIFS($G18:$R18,$G$5:$R$5,V$6) -> 0 | W18: =SUMIFS($G18:$R18,$G$5:$R$5,W$6) -> 0 | X18: =SUMIFS($G18:$R18,$G$5:$R$5,X$6) -> 0
B19: Preventitve Maintenance | C19: HRS | E19: =E74+E128+E183+E238+E293+E348+E403+E458+E513+E568+E623+E678+E733+E788+E843+E872+E927 -> 0 | G19: =G74+G129+G184+G239+G294+G349+G404+G459+G514+G569+G624+G679+G734+G790+G873+G928 -> 3 | H19: =H74+H129+H184+H239+H294+H349+H404+H459+H514+H569+H624+H679+H734+H790+H873+H928 -> 1.3333333 | I19: =I74+I129+I184+I239+I294+I349+I404+I459+I514+I569+I624+I679+I734+I790+I873+I928 -> 3.85 | J19: =J74+J129+J184+J239+J294+J349+J404+J459+J514+J569+J624+J679+J734+J790+J873+J928 -> 0 | K19: =K74+K129+K184+K239+K294+K349+K404+K459+K514+K569+K624+K679+K734+K790+K873+K928 -> 0 | L19: =L74+L129+L184+L239+L294+L349+L404+L459+L514+L569+L624+L679+L734+L790+L873+L928 -> 0 | M19: =M74+M129+M184+M239+M294+M349+M404+M459+M514+M569+M624+M679+M734+M790+M873+M928 -> 0 | N19: =N74+N129+N184+N239+N294+N349+N404+N459+N514+N569+N624+N679+N734+N790+N873+N928 -> 0 | ... R19: =R74+R129+R184+R239+R294+R349+R404+R459+R514+R569+R624+R679+R734+R790+R873+R928 -> 0 | S19: =SUM(G19:R19) -> 8.1833333 | U19: =SUMIFS($G19:$R19,$G$5:$R$5,U$6) -> 8.1833333 | V19: =SUMIFS($G19:$R19,$G$5:$R$5,V$6) -> 0 | W19: =SUMIFS($G19:$R19,$G$5:$R$5,W$6) -> 0 | X19: =SUMIFS($G19:$R19,$G$5:$R$5,X$6) -> 0
B20: Force Majeure | C20: HRS | E20: =E75+E129+E184+E239+E294+E349+E404+E459+E514+E569+E624+E679+E734+E789+E844+E873+E928 -> 0 | G20: =G75+G130+G185+G240+G295+G350+G405+G460+G515+G570+G625+G680+G735+G791+G874+G929 -> 48 | H20: =H75+H130+H185+H240+H295+H350+H405+H460+H515+H570+H625+H680+H735+H791+H874+H929 -> 0 | I20: =I75+I130+I185+I240+I295+I350+I405+I460+I515+I570+I625+I680+I735+I791+I874+I929 -> 0 | J20: =J75+J130+J185+J240+J295+J350+J405+J460+J515+J570+J625+J680+J735+J791+J874+J929 -> 0 | K20: =K75+K130+K185+K240+K295+K350+K405+K460+K515+K570+K625+K680+K735+K791+K874+K929 -> 0 | L20: =L75+L130+L185+L240+L295+L350+L405+L460+L515+L570+L625+L680+L735+L791+L874+L929 -> 0 | M20: =M75+M130+M185+M240+M295+M350+M405+M460+M515+M570+M625+M680+M735+M791+M874+M929 -> 0 | N20: =N75+N130+N185+N240+N295+N350+N405+N460+N515+N570+N625+N680+N735+N791+N874+N929 -> 0 | ... R20: =R75+R130+R185+R240+R295+R350+R405+R460+R515+R570+R625+R680+R735+R791+R874+R929 -> 0 | S20: =SUM(G20:R20) -> 48 | U20: =SUMIFS($G20:$R20,$G$5:$R$5,U$6) -> 48 | V20: =SUMIFS($G20:$R20,$G$5:$R$5,V$6) -> 0 | W20: =SUMIFS($G20:$R20,$G$5:$R$5,W$6) -> 0 | X20: =SUMIFS($G20:$R20,$G$5:$R$5,X$6) -> 0
B21: Electrical Breakdown | C21: HRS | E21: =E76+E130+E185+E240+E295+E350+E405+E460+E515+E570+E625+E680+E735+E790+E845+E874+E929 -> 0 | G21: =G76+G131+G186+G241+G296+G351+G406+G461+G516+G571+G626+G681+G736+G792+G875+G930 -> 0.25 | H21: =H76+H131+H186+H241+H296+H351+H406+H461+H516+H571+H626+H681+H736+H792+H875+H930 -> 0.56666667 | I21: =I76+I131+I186+I241+I296+I351+I406+I461+I516+I571+I626+I681+I736+I792+I875+I930 -> 1 | J21: =J76+J131+J186+J241+J296+J351+J406+J461+J516+J571+J626+J681+J736+J792+J875+J930 -> 0 | K21: =K76+K131+K186+K241+K296+K351+K406+K461+K516+K571+K626+K681+K736+K792+K875+K930 -> 0 | L21: =L76+L131+L186+L241+L296+L351+L406+L461+L516+L571+L626+L681+L736+L792+L875+L930 -> 0 | M21: =M76+M131+M186+M241+M296+M351+M406+M461+M516+M571+M626+M681+M736+M792+M875+M930 -> 0 | N21: =N76+N131+N186+N241+N296+N351+N406+N461+N516+N571+N626+N681+N736+N792+N875+N930 -> 0 | ... R21: =R76+R131+R186+R241+R296+R351+R406+R461+R516+R571+R626+R681+R736+R792+R875+R930 -> 0 | S21: =SUM(G21:R21) -> 1.8166667 | U21: =SUMIFS($G21:$R21,$G$5:$R$5,U$6) -> 1.8166667 | V21: =SUMIFS($G21:$R21,$G$5:$R$5,V$6) -> 0 | W21: =SUMIFS($G21:$R21,$G$5:$R$5,W$6) -> 0 | X21: =SUMIFS($G21:$R21,$G$5:$R$5,X$6) -> 0
... B30: Transfer | C30: HRS | E30: =E85+E139+E194+E249+E304+E359+E414+E469+E524+E579+E634+E689+E744+E799+E854+E883+E938 -> 0 | G30: =G85+G140+G195+G250+G305+G360+G415+G470+G525+G580+G635+G690+G745+G801+G884+G939 -> 495.91667 | H30: =H85+H140+H195+H250+H305+H360+H415+H470+H525+H580+H635+H690+H745+H801+H884+H939 -> 540.5 | I30: =I85+I140+I195+I250+I305+I360+I415+I470+I525+I580+I635+I690+I745+I801+I884+I939 -> 60.75 | J30: =J85+J140+J195+J250+J305+J360+J415+J470+J525+J580+J635+J690+J745+J801+J884+J939 -> 0 | K30: =K85+K140+K195+K250+K305+K360+K415+K470+K525+K580+K635+K690+K745+K801+K884+K939 -> 0 | L30: =L85+L140+L195+L250+L305+L360+L415+L470+L525+L580+L635+L690+L745+L801+L884+L939 -> 0 | M30: =M85+M140+M195+M250+M305+M360+M415+M470+M525+M580+M635+M690+M745+M801+M884+M939 -> 0 | N30: =N85+N140+N195+N250+N305+N360+N415+N470+N525+N580+N635+N690+N745+N801+N884+N939 -> 0 | ... R30: =R85+R140+R195+R250+R305+R360+R415+R470+R525+R580+R635+R690+R745+R801+R884+R939 -> 0 | S30: =SUM(G30:R30) -> 1097.1667 | U30: =SUMIFS($G30:$R30,$G$5:$R$5,U$6) -> 1097.1667 | V30: =SUMIFS($G30:$R30,$G$5:$R$5,V$6) -> 0 | W30: =SUMIFS($G30:$R30,$G$5:$R$5,W$6) -> 0 | X30: =SUMIFS($G30:$R30,$G$5:$R$5,X$6) -> 0
B31: Idle time | C31: HRS | E31: =E86+E158+E213+E268+E323+E378+E433+E488+E543+E600+E653+E708+E763+E818+E850+E902+E957 -> 0 | G31: =G86+G141+G196+G251+G306+G361+G416+G471+G526+G581+G636+G691+G746+G801+G885+G940 -> 82.466667 | H31: =H86+H141+H196+H251+H306+H361+H416+H471+H526+H581+H636+H691+H746+H801+H885+H940 -> 108.98333 | I31: =I86+I141+I196+I251+I306+I361+I416+I471+I526+I581+I636+I691+I746+I801+I885+I940 -> 56.083333 | J31: =J86+J141+J196+J251+J306+J361+J416+J471+J526+J581+J636+J691+J746+J801+J885+J940 -> 0 | K31: =K86+K141+K196+K251+K306+K361+K416+K471+K526+K581+K636+K691+K746+K801+K885+K940 -> 0 | L31: =L86+L141+L196+L251+L306+L361+L416+L471+L526+L581+L636+L691+L746+L801+L885+L940 -> 0 | M31: =M86+M141+M196+M251+M306+M361+M416+M471+M526+M581+M636+M691+M746+M801+M885+M940 -> 0 | N31: =N86+N141+N196+N251+N306+N361+N416+N471+N526+N581+N636+N691+N746+N801+N885+N940 -> 0 | ... R31: =R86+R141+R196+R251+R306+R361+R416+R471+R526+R581+R636+R691+R746+R801+R885+R940 -> 0 | S31: =SUM(G31:R31) -> 247.53333 | U31: =SUMIFS($G31:$R31,$G$5:$R$5,U$6) -> 247.53333 | V31: =SUMIFS($G31:$R31,$G$5:$R$5,V$6) -> 0 | W31: =SUMIFS($G31:$R31,$G$5:$R$5,W$6) -> 0 | X31: =SUMIFS($G31:$R31,$G$5:$R$5,X$6) -> 0
B32: TOTAL | C32: HRS | E32: =E87+E161+E214+E271+E326+E381+E434+E491+E546+E601+E656+E711+E766+E821+E851+E905+E960 -> #REF! | G32: =G87+G142+G197+G252+G307+G362+G417+G472+G527+G582+G637+G692+G747+G802+G886+G941 -> 18337.65 | H32: =H87+H142+H197+H252+H307+H362+H417+H472+H527+H582+H637+H692+H747+H802+H886+H941 -> 18004.567 | I32: =I87+I142+I197+I252+I307+I362+I417+I472+I527+I582+I637+I692+I747+I802+I886+I941 -> 11336.667 | J32: =J87+J142+J197+J252+J307+J362+J417+J472+J527+J582+J637+J692+J747+J802+J886+J941 -> 0 | K32: =K87+K142+K197+K252+K307+K362+K417+K472+K527+K582+K637+K692+K747+K802+K886+K941 -> 0 | L32: =L87+L142+L197+L252+L307+L362+L417+L472+L527+L582+L637+L692+L747+L802+L886+L941 -> 0 | M32: =M87+M142+M197+M252+M307+M362+M417+M472+M527+M582+M637+M692+M747+M802+M886+M941 -> 0 | N32: =N87+N142+N197+N252+N307+N362+N417+N472+N527+N582+N637+N692+N747+N802+N886+N941 -> 0 | ... R32: =R87+R142+R197+R252+R307+R362+R417+R472+R527+R582+R637+R692+R747+R802+R886+R941 -> 0 | S32: =SUM(G32:R32) -> 47678.883 | U32: =SUMIFS($G32:$R32,$G$5:$R$5,U$6) -> 47678.883 | V32: =SUMIFS($G32:$R32,$G$5:$R$5,V$6) -> 0 | W32: =SUMIFS($G32:$R32,$G$5:$R$5,W$6) -> 0 | X32: =SUMIFS($G32:$R32,$G$5:$R$5,X$6) -> 0
B34: Actual Productive Time | C34: % | E34: =IFERROR(E8/E$32,0) -> 0 | G34: =IFERROR(G9/G$32,0) -> 0.28705514 | H34: =IFERROR(H9/H$32,0) -> 0.35290584 | I34: =IFERROR(I9/I$32,0) -> 0.37296383 | J34: =IFERROR(J9/J$32,0) -> 0 | K34: =IFERROR(K9/K$32,0) -> 0 | L34: =IFERROR(L9/L$32,0) -> 0 | M34: =IFERROR(M9/M$32,0) -> 0 | N34: =IFERROR(N9/N$32,0) -> 0 | ... S34: =IFERROR(S9/S$32,0) -> 0.33234839 | U34: =IFERROR(U9/U$32,0) -> 0.33234839 | V34: =IFERROR(V9/V$32,0) -> 0 | W34: =IFERROR(W9/W$32,0) -> 0 | X34: =IFERROR(X9/X$32,0) -> 0
B35: No Production Plan | C35: % | E35: =IFERROR(E9/E$32,0) -> 0 | G35: =IFERROR(G10/G$32,0) -> 0.29180311 | H35: =IFERROR(H10/H$32,0) -> 0.21150467 | I35: =IFERROR(I10/I$32,0) -> 0.10195678 | J35: =IFERROR(J10/J$32,0) -> 0 | K35: =IFERROR(K10/K$32,0) -> 0 | L35: =IFERROR(L10/L$32,0) -> 0 | M35: =IFERROR(M10/M$32,0) -> 0 | N35: =IFERROR(N10/N$32,0) -> 0 | ... S35: =IFERROR(S10/S$32,0) -> 0.21634071 | U35: =IFERROR(U10/U$32,0) -> 0.21634071 | V35: =IFERROR(V10/V$32,0) -> 0 | W35: =IFERROR(W10/W$32,0) -> 0 | X35: =IFERROR(X10/X$32,0) -> 0
B36: No Head Count Allocation | C36: % | E36: =IFERROR(E10/E$32,0) -> 0 | G36: =IFERROR(G11/G$32,0) -> 0.16341789 | H36: =IFERROR(H11/H$32,0) -> 0.1999576 | I36: =IFERROR(I11/I$32,0) -> 0.25049397 | J36: =IFERROR(J11/J$32,0) -> 0 | K36: =IFERROR(K11/K$32,0) -> 0 | L36: =IFERROR(L11/L$32,0) -> 0 | M36: =IFERROR(M11/M$32,0) -> 0 | N36: =IFERROR(N11/N$32,0) -> 0 | ... S36: =IFERROR(S11/S$32,0) -> 0.19792025 | U36: =IFERROR(U11/U$32,0) -> 0.19792025 | V36: =IFERROR(V11/V$32,0) -> 0 | W36: =IFERROR(W11/W$32,0) -> 0 | X36: =IFERROR(X11/X$32,0) -> 0
B37: Change Over Time | C37: % | E37: =IFERROR(E11/E$32,0) -> 0 | G37: =IFERROR(G12/G$32,0) -> 0.016065308 | H37: =IFERROR(H12/H$32,0) -> 0.021621366 | I37: =IFERROR(I12/I$32,0) -> 0.018904734 | J37: =IFERROR(J12/J$32,0) -> 0 | K37: =IFERROR(K12/K$32,0) -> 0 | L37: =IFERROR(L12/L$32,0) -> 0 | M37: =IFERROR(M12/M$32,0) -> 0 | N37: =IFERROR(N12/N$32,0) -> 0 | ... S37: =IFERROR(S12/S$32,0) -> 0.018838528 | U37: =IFERROR(U12/U$32,0) -> 0.018838528 | V37: =IFERROR(V12/V$32,0) -> 0 | W37: =IFERROR(W12/W$32,0) -> 0 | X37: =IFERROR(X12/X$32,0) -> 0
B38: Meeting | C38: % | E38: =IFERROR(E12/E$32,0) -> 0 | G38: =IFERROR(G13/G$32,0) -> 0.0015941701 | H38: =IFERROR(H13/H$32,0) -> 0.0015625665 | I38: =IFERROR(I13/I$32,0) -> 0.00064686857 | J38: =IFERROR(J13/J$32,0) -> 0 | K38: =IFERROR(K13/K$32,0) -> 0 | L38: =IFERROR(L13/L$32,0) -> 0 | M38: =IFERROR(M13/M$32,0) -> 0 | N38: =IFERROR(N13/N$32,0) -> 0 | ... S38: =IFERROR(S13/S$32,0) -> 0.0013569949 | U38: =IFERROR(U13/U$32,0) -> 0.0013569949 | V38: =IFERROR(V13/V$32,0) -> 0 | W38: =IFERROR(W13/W$32,0) -> 0 | X38: =IFERROR(X13/X$32,0) -> 0
B39: Sanitation Time | C39: % | E39: =IFERROR(E13/E$32,0) -> 0 | G39: =IFERROR(G14/G$32,0) -> 0.0086488727 | H39: =IFERROR(H14/H$32,0) -> 0.010041897 | I39: =IFERROR(I14/I$32,0) -> 0.0063745957 | J39: =IFERROR(J14/J$32,0) -> 0 | K39: =IFERROR(K14/K$32,0) -> 0 | L39: =IFERROR(L14/L$32,0) -> 0 | M39: =IFERROR(M14/M$32,0) -> 0 | N39: =IFERROR(N14/N$32,0) -> 0 | ... S39: =IFERROR(S14/S$32,0) -> 0.0086341508 | U39: =IFERROR(U14/U$32,0) -> 0.0086341508 | V39: =IFERROR(V14/V$32,0) -> 0 | W39: =IFERROR(W14/W$32,0) -> 0 | X39: =IFERROR(X14/X$32,0) -> 0
B40: Start-up Time/Setup | C40: % | E40: =IFERROR(E14/E$32,0) -> 0 | G40: =IFERROR(G15/G$32,0) -> 0.016721517 | H40: =IFERROR(H15/H$32,0) -> 0.020867854 | I40: =IFERROR(I15/I$32,0) -> 0.011259924 | J40: =IFERROR(J15/J$32,0) -> 0 | K40: =IFERROR(K15/K$32,0) -> 0 | L40: =IFERROR(L15/L$32,0) -> 0 | M40: =IFERROR(M15/M$32,0) -> 0 | N40: =IFERROR(N15/N$32,0) -> 0 | ... S40: =IFERROR(S15/S$32,0) -> 0.016988653 | U40: =IFERROR(U15/U$32,0) -> 0.016988653 | V40: =IFERROR(V15/V$32,0) -> 0 | W40: =IFERROR(W15/W$32,0) -> 0 | X40: =IFERROR(X15/X$32,0) -> 0
B41: Shutdown/cooldown | C41: % | E41: =IFERROR(E15/E$32,0) -> 0 | G41: =IFERROR(G16/G$32,0) -> 4.5443845e-05 | H41: =IFERROR(H16/H$32,0) -> 0 | I41: =IFERROR(I16/I$32,0) -> 0 | J41: =IFERROR(J16/J$32,0) -> 0 | K41: =IFERROR(K16/K$32,0) -> 0 | L41: =IFERROR(L16/L$32,0) -> 0 | M41: =IFERROR(M16/M$32,0) -> 0 | N41: =IFERROR(N16/N$32,0) -> 0 | ... S41: =IFERROR(S16/S$32,0) -> 1.7478038e-05 | U41: =IFERROR(U16/U$32,0) -> 1.7478038e-05 | V41: =IFERROR(V16/V$32,0) -> 0 | W41: =IFERROR(W16/W$32,0) -> 0 | X41: =IFERROR(X16/X$32,0) -> 0
B42: Testing Time | C42: % | E42: =IFERROR(E16/E$32,0) -> 0 | G42: =IFERROR(G17/G$32,0) -> 0.0064403018 | H42: =IFERROR(H17/H$32,0) -> 0.009783629 | I42: =IFERROR(I17/I$32,0) -> 0.00074095854 | J42: =IFERROR(J17/J$32,0) -> 0 | K42: =IFERROR(K17/K$32,0) -> 0 | L42: =IFERROR(L17/L$32,0) -> 0 | M42: =IFERROR(M17/M$32,0) -> 0 | N42: =IFERROR(N17/N$32,0) -> 0 | ... S42: =IFERROR(S17/S$32,0) -> 0.0063476738 | U42: =IFERROR(U17/U$32,0) -> 0.0063476738 | V42: =IFERROR(V17/V$32,0) -> 0 | W42: =IFERROR(W17/W$32,0) -> 0 | X42: =IFERROR(X17/X$32,0) -> 0
B43: Breaktime | C43: % | E43: =IFERROR(E17/E$32,0) -> 0 | G43: =IFERROR(G18/G$32,0) -> 0.015072815 | H43: =IFERROR(H18/H$32,0) -> 0.019459878 | I43: =IFERROR(I18/I$32,0) -> 0.017153778 | J43: =IFERROR(J18/J$32,0) -> 0 | K43: =IFERROR(K18/K$32,0) -> 0 | L43: =IFERROR(L18/L$32,0) -> 0 | M43: =IFERROR(M18/M$32,0) -> 0 | N43: =IFERROR(N18/N$32,0) -> 0 | ... S43: =IFERROR(S18/S$32,0) -> 0.017224257 | U43: =IFERROR(U18/U$32,0) -> 0.017224257 | V43: =IFERROR(V18/V$32,0) -> 0 | W43: =IFERROR(W18/W$32,0) -> 0 | X43: =IFERROR(X18/X$32,0) -> 0
B44: Preventitve Maintenance | C44: % | E44: =IFERROR(E18/E$32,0) -> 0 | G44: =IFERROR(G19/G$32,0) -> 0.00016359784 | H44: =IFERROR(H19/H$32,0) -> 7.4055286e-05 | I44: =IFERROR(I19/I$32,0) -> 0.000339606 | J44: =IFERROR(J19/J$32,0) -> 0 | K44: =IFERROR(K19/K$32,0) -> 0 | L44: =IFERROR(L19/L$32,0) -> 0 | M44: =IFERROR(M19/M$32,0) -> 0 | N44: =IFERROR(N19/N$32,0) -> 0 | ... S44: =IFERROR(S19/S$32,0) -> 0.00017163433 | U44: =IFERROR(U19/U$32,0) -> 0.00017163433 | V44: =IFERROR(V19/V$32,0) -> 0 | W44: =IFERROR(W19/W$32,0) -> 0 | X44: =IFERROR(X19/X$32,0) -> 0
B45: Force Majeure | C45: % | E45: =IFERROR(E19/E$32,0) -> 0 | G45: =IFERROR(G20/G$32,0) -> 0.0026175655 | H45: =IFERROR(H20/H$32,0) -> 0 | I45: =IFERROR(I20/I$32,0) -> 0 | J45: =IFERROR(J20/J$32,0) -> 0 | K45: =IFERROR(K20/K$32,0) -> 0 | L45: =IFERROR(L20/L$32,0) -> 0 | M45: =IFERROR(M20/M$32,0) -> 0 | N45: =IFERROR(N20/N$32,0) -> 0 | ... S45: =IFERROR(S20/S$32,0) -> 0.001006735 | U45: =IFERROR(U20/U$32,0) -> 0.001006735 | V45: =IFERROR(V20/V$32,0) -> 0 | W45: =IFERROR(W20/W$32,0) -> 0 | X45: =IFERROR(X20/X$32,0) -> 0
... B56: Idle time | C56: % | E56: =IFERROR(E30/E$32,0) -> 0 | G56: =IFERROR(G31/G$32,0) -> 0.0044971229 | H56: =IFERROR(H31/H$32,0) -> 0.0060530939 | I56: =IFERROR(I31/I$32,0) -> 0.0049470744 | J56: =IFERROR(J31/J$32,0) -> 0 | K56: =IFERROR(K31/K$32,0) -> 0 | L56: =IFERROR(L31/L$32,0) -> 0 | M56: =IFERROR(M31/M$32,0) -> 0 | N56: =IFERROR(N31/N$32,0) -> 0 | ... S56: =IFERROR(S31/S$32,0) -> 0.0051916764 | U56: =IFERROR(U31/U$32,0) -> 0.0051916764 | V56: =IFERROR(V31/V$32,0) -> 0 | W56: =IFERROR(W31/W$32,0) -> 0 | X56: =IFERROR(X31/X$32,0) -> 0
B57: TOTAL | C57: % | E57: =IFERROR(E32/E$32,0) -> 0 | G57: =IFERROR(G32/G$32,0) -> 1 | H57: =IFERROR(H32/H$32,0) -> 1 | I57: =IFERROR(I32/I$32,0) -> 1 | J57: =IFERROR(J32/J$32,0) -> 0 | K57: =IFERROR(K32/K$32,0) -> 0 | L57: =IFERROR(L32/L$32,0) -> 0 | M57: =IFERROR(M32/M$32,0) -> 0 | N57: =IFERROR(N32/N$32,0) -> 0 | ... S57: =IFERROR(S32/S$32,0) -> 1 | U57: =IFERROR(U32/U$32,0) -> 1 | V57: =IFERROR(V32/V$32,0) -> 0 | W57: =IFERROR(W32/W$32,0) -> 0 | X57: =IFERROR(X32/X$32,0) -> 0
B58: # of Machines available | E58: =E113+E168+E223+E278+E333+E388+E443+E498+E553+E608+E663+E718+E773+E828+E857+E912+E967 -> 26 | G58: =G113+G168+G223+G278+G333+G388+G443+G498+G553+G608+G663+G718+G773+G828+G912+G967 -> 25 | H58: =H113+H168+H223+H278+H333+H388+H443+H498+H553+H608+H663+H718+H773+H828+H912+H967 -> 25 | I58: =I113+I168+I223+I278+I333+I388+I443+I498+I553+I608+I663+I718+I773+I828+I912+I967 -> 25 | J58: =J113+J168+J223+J278+J333+J388+J443+J498+J553+J608+J663+J718+J773+J828+J912+J967 -> 0 | K58: =K113+K168+K223+K278+K333+K388+K443+K498+K553+K608+K663+K718+K773+K828+K912+K967 -> 0 | L58: =L113+L168+L223+L278+L333+L388+L443+L498+L553+L608+L663+L718+L773+L828+L912+L967 -> 0 | M58: =M113+M168+M223+M278+M333+M388+M443+M498+M553+M608+M663+M718+M773+M828+M912+M967 -> 0 | N58: =N113+N168+N223+N278+N333+N388+N443+N498+N553+N608+N663+N718+N773+N828+N912+N967 -> 0 | ... S58: =S113+S168+S223+S278+S333+S388+S443+S498+S553+S608+S663+S718+S773+S828+S912+S967 -> 20 | U58: =SUMIFS($G58:$R58,$G$5:$R$5,U$6) -> 75 | V58: =SUMIFS($G58:$R58,$G$5:$R$5,V$6) -> 0 | W58: =SUMIFS($G58:$R58,$G$5:$R$5,W$6) -> 0 | X58: =SUMIFS($G58:$R58,$G$5:$R$5,X$6) -> 0
B59: # of Machines used | E59: =E114+E169+E224+E279+E334+E389+E444+E499+E554+E609+E664+E719+E774+E829+E858+E913+E968 -> 26 | G59: =G114+G169+G224+G279+G334+G389+G444+G499+G554+G609+G664+G719+G774+G829+G913+G968 -> 25 | H59: =H114+H169+H224+H279+H334+H389+H444+H499+H554+H609+H664+H719+H774+H829+H913+H968 -> 25 | I59: =I114+I169+I224+I279+I334+I389+I444+I499+I554+I609+I664+I719+I774+I829+I913+I968 -> 25 | J59: =J114+J169+J224+J279+J334+J389+J444+J499+J554+J609+J664+J719+J774+J829+J913+J968 -> 0 | K59: =K114+K169+K224+K279+K334+K389+K444+K499+K554+K609+K664+K719+K774+K829+K913+K968 -> 0 | L59: =L114+L169+L224+L279+L334+L389+L444+L499+L554+L609+L664+L719+L774+L829+L913+L968 -> 0 | M59: =M114+M169+M224+M279+M334+M389+M444+M499+M554+M609+M664+M719+M774+M829+M913+M968 -> 0 | N59: =N114+N169+N224+N279+N334+N389+N444+N499+N554+N609+N664+N719+N774+N829+N913+N968 -> 0 | ... S59: =S114+S169+S224+S279+S334+S389+S444+S499+S554+S609+S664+S719+S774+S829+S913+S968 -> 20 | U59: =SUMIFS($G59:$R59,$G$5:$R$5,U$6) -> 75 | V59: =SUMIFS($G59:$R59,$G$5:$R$5,V$6) -> 0 | W59: =SUMIFS($G59:$R59,$G$5:$R$5,W$6) -> 0 | X59: =SUMIFS($G59:$R59,$G$5:$R$5,X$6) -> 0
B60: Production Days | G60: =IFERROR(AVERAGE(G115,G170,G225,G280,G335,G390,G445,G500,G555,G610,G665,G720,G775,G830,G859,G914,G969),0) -> 19.75 | H60: =IFERROR(AVERAGE(H115,H170,H225,H280,H335,H390,H445,H500,H555,H610,H665,H720,H775,H830,H859,H914,H969),0) -> 23.65 | I60: =IFERROR(AVERAGE(I115,I170,I225,I280,I335,I390,I445,I500,I555,I610,I665,I720,I775,I830,I859,I914,I969),0) -> 19.45 | J60: =IFERROR(AVERAGE(J115,J170,J225,J280,J335,J390,J445,J500,J555,J610,J665,J720,J775,J830,J859,J914,J969),0) -> 0 | K60: =IFERROR(AVERAGE(K115,K170,K225,K280,K335,K390,K445,K500,K555,K610,K665,K720,K775,K830,K859,K914,K969),0) -> 0 | L60: =IFERROR(AVERAGE(L115,L170,L225,L280,L335,L390,L445,L500,L555,L610,L665,L720,L775,L830,L859,L914,L969),0) -> 0 | M60: =IFERROR(AVERAGE(M115,M170,M225,M280,M335,M390,M445,M500,M555,M610,M665,M720,M775,M830,M859,M914,M969),0) -> 0 | N60: =IFERROR(AVERAGE(N115,N170,N225,N280,N335,N390,N445,N500,N555,N610,N665,N720,N775,N830,N859,N914,N969),0) -> 0 | ... S60: =IFERROR(AVERAGE(S115,S170,S225,S280,S335,S390,S445,S500,S555,S610,S665,S720,S775,S830,S859,S914,S969),0) -> 62.85 | U60: =SUMIFS($G60:$R60,$G$5:$R$5,U$6) -> 62.85 | V60: =SUMIFS($G60:$R60,$G$5:$R$5,V$6) -> 0 | W60: =SUMIFS($G60:$R60,$G$5:$R$5,W$6) -> 0 | X60: =SUMIFS($G60:$R60,$G$5:$R$5,X$6) -> 0
B61: % Utilization | E61: =IFERROR(E32/(E60*E58*24),0) -> 0 | G61: =IFERROR(G32/(G60*G58*24),0) -> 1.547481 | H61: =IFERROR(H32/(H60*H58*24),0) -> 1.2688208 | I61: =IFERROR(I32/(I60*I58*24),0) -> 0.97143673 | J61: =IFERROR(J32/(J60*J58*24),0) -> 0 | K61: =IFERROR(K32/(K60*K58*24),0) -> 0 | L61: =IFERROR(L32/(L60*L58*24),0) -> 0 | M61: =IFERROR(M32/(M60*M58*24),0) -> 0 | N61: =IFERROR(N32/(N60*N58*24),0) -> 0 | ... S61: =IFERROR(S32/(S60*S58*24),0) -> 1.5804456 | U61: =IFERROR(U32/(U60*U58*24),0) -> 0.42145216 | V61: =IFERROR(V32/(V60*V58*24),0) -> 0 | W61: =IFERROR(W32/(W60*W58*24),0) -> 0 | X61: =IFERROR(X32/(X60*X58*24),0) -> 0
Q62: =(Q87/30)/4 -> 0
B63: LINE 6- EPOXY LINE (FILLING)
B64: Actual Productive Time | C64: HRS | G64: 936.98333 | H64: 1261.55 | I64: 782.1 | S64: =SUM(G64:R64) -> 2980.6333 | U64: =SUMIFS($G64:$R64,$G$5:$R$5,U$6) -> 2980.6333 | V64: =SUMIFS($G64:$R64,$G$5:$R$5,V$6) -> 0 | W64: =SUMIFS($G64:$R64,$G$5:$R$5,W$6) -> 0 | X64: =SUMIFS($G64:$R64,$G$5:$R$5,X$6) -> 0
B65: No Production Plan | C65: HRS | G65: 29.2 | H65: 1.5833333 | I65: 0.75 | S65: =SUM(G65:R65) -> 31.533333 | U65: =SUMIFS($G65:$R65,$G$5:$R$5,U$6) -> 31.533333 | V65: =SUMIFS($G65:$R65,$G$5:$R$5,V$6) -> 0 | W65: =SUMIFS($G65:$R65,$G$5:$R$5,W$6) -> 0 | X65: =SUMIFS($G65:$R65,$G$5:$R$5,X$6) -> 0
B66: No Head Count Allocation | C66: HRS | G66: 923.2 | H66: 788.75 | I66: 988.98333 | S66: =SUM(G66:R66) -> 2700.9333 | U66: =SUMIFS($G66:$R66,$G$5:$R$5,U$6) -> 2700.9333 | V66: =SUMIFS($G66:$R66,$G$5:$R$5,V$6) -> 0 | W66: =SUMIFS($G66:$R66,$G$5:$R$5,W$6) -> 0 | X66: =SUMIFS($G66:$R66,$G$5:$R$5,X$6) -> 0
B67: Change Over Time | C67: HRS | G67: 53.333333 | H67: 87.083333 | I67: 47.95 | S67: =SUM(G67:R67) -> 188.36667 | U67: =SUMIFS($G67:$R67,$G$5:$R$5,U$6) -> 188.36667 | V67: =SUMIFS($G67:$R67,$G$5:$R$5,V$6) -> 0 | W67: =SUMIFS($G67:$R67,$G$5:$R$5,W$6) -> 0 | X67: =SUMIFS($G67:$R67,$G$5:$R$5,X$6) -> 0
B68: Meeting | C68: HRS | G68: 3.15 | H68: 1.9166667 | I68: 1.5 | S68: =SUM(G68:R68) -> 6.5666667 | U68: =SUMIFS($G68:$R68,$G$5:$R$5,U$6) -> 6.5666667 | V68: =SUMIFS($G68:$R68,$G$5:$R$5,V$6) -> 0 | W68: =SUMIFS($G68:$R68,$G$5:$R$5,W$6) -> 0 | X68: =SUMIFS($G68:$R68,$G$5:$R$5,X$6) -> 0
B69: Sanitation Time | C69: HRS | G69: 16.9 | H69: 11.216667 | I69: 7.6666667 | S69: =SUM(G69:R69) -> 35.783333 | U69: =SUMIFS($G69:$R69,$G$5:$R$5,U$6) -> 35.783333 | V69: =SUMIFS($G69:$R69,$G$5:$R$5,V$6) -> 0 | W69: =SUMIFS($G69:$R69,$G$5:$R$5,W$6) -> 0 | X69: =SUMIFS($G69:$R69,$G$5:$R$5,X$6) -> 0
B70: Start-up Time/Setup | C70: HRS | G70: 24.716667 | H70: 15.366667 | I70: 14.183333 | S70: =SUM(G70:R70) -> 54.266667 | U70: =SUMIFS($G70:$R70,$G$5:$R$5,U$6) -> 54.266667 | V70: =SUMIFS($G70:$R70,$G$5:$R$5,V$6) -> 0 | W70: =SUMIFS($G70:$R70,$G$5:$R$5,W$6) -> 0 | X70: =SUMIFS($G70:$R70,$G$5:$R$5,X$6) -> 0
B71: Shutdown/cooldown | C71: HRS | G71: 0 | H71: 0 | I71: 0 | S71: =SUM(G71:R71) -> 0 | U71: =SUMIFS($G71:$R71,$G$5:$R$5,U$6) -> 0 | V71: =SUMIFS($G71:$R71,$G$5:$R$5,V$6) -> 0 | W71: =SUMIFS($G71:$R71,$G$5:$R$5,W$6) -> 0 | X71: =SUMIFS($G71:$R71,$G$5:$R$5,X$6) -> 0
B72: Testing Time | C72: HRS | G72: 0.43333333 | H72: 1.8 | I72: 3.1666667 | S72: =SUM(G72:R72) -> 5.4 | U72: =SUMIFS($G72:$R72,$G$5:$R$5,U$6) -> 5.4 | V72: =SUMIFS($G72:$R72,$G$5:$R$5,V$6) -> 0 | W72: =SUMIFS($G72:$R72,$G$5:$R$5,W$6) -> 0 | X72: =SUMIFS($G72:$R72,$G$5:$R$5,X$6) -> 0
B73: Breaktime | C73: HRS | G73: 43.333333 | H73: 44.833333 | I73: 32.916667 | S73: =SUM(G73:R73) -> 121.08333 | U73: =SUMIFS($G73:$R73,$G$5:$R$5,U$6) -> 121.08333 | V73: =SUMIFS($G73:$R73,$G$5:$R$5,V$6) -> 0 | W73: =SUMIFS($G73:$R73,$G$5:$R$5,W$6) -> 0 | X73: =SUMIFS($G73:$R73,$G$5:$R$5,X$6) -> 0
B74: Preventitve Maintenance | C74: HRS | G74: 0 | H74: 0 | I74: 0 | S74: =SUM(G74:R74) -> 0 | U74: =SUMIFS($G74:$R74,$G$5:$R$5,U$6) -> 0 | V74: =SUMIFS($G74:$R74,$G$5:$R$5,V$6) -> 0 | W74: =SUMIFS($G74:$R74,$G$5:$R$5,W$6) -> 0 | X74: =SUMIFS($G74:$R74,$G$5:$R$5,X$6) -> 0
B75: Force Majeure | C75: HRS | G75: 48 | H75: 0 | I75: 0 | S75: =SUM(G75:R75) -> 48 | U75: =SUMIFS($G75:$R75,$G$5:$R$5,U$6) -> 48 | V75: =SUMIFS($G75:$R75,$G$5:$R$5,V$6) -> 0 | W75: =SUMIFS($G75:$R75,$G$5:$R$5,W$6) -> 0 | X75: =SUMIFS($G75:$R75,$G$5:$R$5,X$6) -> 0
... B86: Idle time | C86: HRS | G86: 8.5333333 | H86: 9.1166667 | I86: 7.25 | S86: =SUM(G86:R86) -> 24.9 | U86: =SUMIFS($G86:$R86,$G$5:$R$5,U$6) -> 24.9 | V86: =SUMIFS($G86:$R86,$G$5:$R$5,V$6) -> 0 | W86: =SUMIFS($G86:$R86,$G$5:$R$5,W$6) -> 0 | X86: =SUMIFS($G86:$R86,$G$5:$R$5,X$6) -> 0
B87: TOTAL | C87: HRS | E87: =SUM(E64:E86) -> 0 | G87: =SUM(G64:G86) -> 2208 | H87: =SUM(H64:H86) -> 2304 | I87: =SUM(I64:I86) -> 2016 | J87: =SUM(J64:J86) -> 0 | K87: =SUM(K64:K86) -> 0 | L87: =SUM(L64:L86) -> 0 | M87: =SUM(M64:M86) -> 0 | N87: =SUM(N64:N86) -> 0 | ... R87: =SUM(R64:R86) -> 0 | S87: =SUM(G87:R87) -> 6528 | U87: =SUM(U64:U86) -> 6528 | V87: =SUM(V64:V86) -> 0 | W87: =SUM(W64:W86) -> 0 | X87: =SUM(X64:X86) -> 0
B89: Actual Productive Time | C89: % | E89: =IFERROR(E65/E$87,0) -> 0 | G89: =IFERROR(G65/G$87,0) -> 0.013224638 | H89: =IFERROR(H65/H$87,0) -> 0.00068721065 | I89: =IFERROR(I65/I$87,0) -> 0.00037202381 | J89: =IFERROR(J65/J$87,0) -> 0 | K89: =IFERROR(K65/K$87,0) -> 0 | L89: =IFERROR(L65/L$87,0) -> 0 | M89: =IFERROR(M65/M$87,0) -> 0 | N89: =IFERROR(N65/N$87,0) -> 0 | ... S89: =IFERROR(S65/S$87,0) -> 0.0048304739 | U89: =IFERROR(U65/U$87,0) -> 0.0048304739 | V89: =IFERROR(V65/V$87,0) -> 0 | W89: =IFERROR(W65/W$87,0) -> 0 | X89: =IFERROR(X65/X$87,0) -> 0
B90: No Production Plan | C90: % | E90: =IFERROR(E58/E$87,0) -> 0 | G90: =IFERROR(G58/G$87,0) -> 0.011322464 | H90: =IFERROR(H58/H$87,0) -> 0.010850694 | I90: =IFERROR(I58/I$87,0) -> 0.012400794 | J90: =IFERROR(J58/J$87,0) -> 0 | K90: =IFERROR(K58/K$87,0) -> 0 | L90: =IFERROR(L58/L$87,0) -> 0 | M90: =IFERROR(M58/M$87,0) -> 0 | N90: =IFERROR(N58/N$87,0) -> 0 | ... S90: =IFERROR(S58/S$87,0) -> 0.0030637255 | U90: =IFERROR(U58/U$87,0) -> 0.011488971 | V90: =IFERROR(V58/V$87,0) -> 0 | W90: =IFERROR(W58/W$87,0) -> 0 | X90: =IFERROR(X58/X$87,0) -> 0
B91: No Head Count Allocation | C91: % | E91: =IFERROR(E59/E$87,0) -> 0 | G91: =IFERROR(G59/G$87,0) -> 0.011322464 | H91: =IFERROR(H59/H$87,0) -> 0.010850694 | I91: =IFERROR(I59/I$87,0) -> 0.012400794 | J91: =IFERROR(J59/J$87,0) -> 0 | K91: =IFERROR(K59/K$87,0) -> 0 | L91: =IFERROR(L59/L$87,0) -> 0 | M91: =IFERROR(M59/M$87,0) -> 0 | N91: =IFERROR(N59/N$87,0) -> 0 | ... S91: =IFERROR(S59/S$87,0) -> 0.0030637255 | U91: =IFERROR(U59/U$87,0) -> 0.011488971 | V91: =IFERROR(V59/V$87,0) -> 0 | W91: =IFERROR(W59/W$87,0) -> 0 | X91: =IFERROR(X59/X$87,0) -> 0
B92: Change Over Time | C92: % | E92: =IFERROR(E60/E$87,0) -> 0 | G92: =IFERROR(G60/G$87,0) -> 0.0089447464 | H92: =IFERROR(H60/H$87,0) -> 0.010264757 | I92: =IFERROR(I60/I$87,0) -> 0.0096478175 | J92: =IFERROR(J60/J$87,0) -> 0 | K92: =IFERROR(K60/K$87,0) -> 0 | L92: =IFERROR(L60/L$87,0) -> 0 | M92: =IFERROR(M60/M$87,0) -> 0 | N92: =IFERROR(N60/N$87,0) -> 0 | ... S92: =IFERROR(S60/S$87,0) -> 0.0096277574 | U92: =IFERROR(U60/U$87,0) -> 0.0096277574 | V92: =IFERROR(V60/V$87,0) -> 0 | W92: =IFERROR(W60/W$87,0) -> 0 | X92: =IFERROR(X60/X$87,0) -> 0
B93: Meeting | C93: % | E93: =IFERROR(E61/E$87,0) -> 0 | G93: =IFERROR(G61/G$87,0) -> 0.00070085191 | H93: =IFERROR(H61/H$87,0) -> 0.00055070346 | I93: =IFERROR(I61/I$87,0) -> 0.00048186346 | J93: =IFERROR(J61/J$87,0) -> 0 | K93: =IFERROR(K61/K$87,0) -> 0 | L93: =IFERROR(L61/L$87,0) -> 0 | M93: =IFERROR(M61/M$87,0) -> 0 | N93: =IFERROR(N61/N$87,0) -> 0 | ... S93: =IFERROR(S61/S$87,0) -> 0.00024210258 | U93: =IFERROR(U61/U$87,0) -> 6.4560687e-05 | V93: =IFERROR(V61/V$87,0) -> 0 | W93: =IFERROR(W61/W$87,0) -> 0 | X93: =IFERROR(X61/X$87,0) -> 0
B94: Sanitation Time | C94: % | E94: =IFERROR(E62/E$87,0) -> 0 | G94: =IFERROR(G62/G$87,0) -> 0 | H94: =IFERROR(H62/H$87,0) -> 0 | I94: =IFERROR(I62/I$87,0) -> 0 | J94: =IFERROR(J62/J$87,0) -> 0 | K94: =IFERROR(K62/K$87,0) -> 0 | L94: =IFERROR(L62/L$87,0) -> 0 | M94: =IFERROR(M62/M$87,0) -> 0 | N94: =IFERROR(N62/N$87,0) -> 0 | ... S94: =IFERROR(S62/S$87,0) -> 0 | U94: =IFERROR(U62/U$87,0) -> 0 | V94: =IFERROR(V62/V$87,0) -> 0 | W94: =IFERROR(W62/W$87,0) -> 0 | X94: =IFERROR(X62/X$87,0) -> 0
B95: Start-up Time/Setup | C95: % | E95: =IFERROR(E63/E$87,0) -> 0 | G95: =IFERROR(G63/G$87,0) -> 0 | H95: =IFERROR(H63/H$87,0) -> 0 | I95: =IFERROR(I63/I$87,0) -> 0 | J95: =IFERROR(J63/J$87,0) -> 0 | K95: =IFERROR(K63/K$87,0) -> 0 | L95: =IFERROR(L63/L$87,0) -> 0 | M95: =IFERROR(M63/M$87,0) -> 0 | N95: =IFERROR(N63/N$87,0) -> 0 | ... S95: =IFERROR(S63/S$87,0) -> 0 | U95: =IFERROR(U63/U$87,0) -> 0 | V95: =IFERROR(V63/V$87,0) -> 0 | W95: =IFERROR(W63/W$87,0) -> 0 | X95: =IFERROR(X63/X$87,0) -> 0
B96: Shutdown/cooldown | C96: % | E96: =IFERROR(E64/E$87,0) -> 0 | G96: =IFERROR(G64/G$87,0) -> 0.42435839 | H96: =IFERROR(H64/H$87,0) -> 0.54754774 | I96: =IFERROR(I64/I$87,0) -> 0.38794643 | J96: =IFERROR(J64/J$87,0) -> 0 | K96: =IFERROR(K64/K$87,0) -> 0 | L96: =IFERROR(L64/L$87,0) -> 0 | M96: =IFERROR(M64/M$87,0) -> 0 | N96: =IFERROR(N64/N$87,0) -> 0 | ... S96: =IFERROR(S64/S$87,0) -> 0.45659212 | U96: =IFERROR(U64/U$87,0) -> 0.45659212 | V96: =IFERROR(V64/V$87,0) -> 0 | W96: =IFERROR(W64/W$87,0) -> 0 | X96: =IFERROR(X64/X$87,0) -> 0
B97: Testing Time | C97: % | E97: =IFERROR(E65/E$87,0) -> 0 | G97: =IFERROR(G65/G$87,0) -> 0.013224638 | H97: =IFERROR(H65/H$87,0) -> 0.00068721065 | I97: =IFERROR(I65/I$87,0) -> 0.00037202381 | J97: =IFERROR(J65/J$87,0) -> 0 | K97: =IFERROR(K65/K$87,0) -> 0 | L97: =IFERROR(L65/L$87,0) -> 0 | M97: =IFERROR(M65/M$87,0) -> 0 | N97: =IFERROR(N65/N$87,0) -> 0 | ... S97: =IFERROR(S65/S$87,0) -> 0.0048304739 | U97: =IFERROR(U65/U$87,0) -> 0.0048304739 | V97: =IFERROR(V65/V$87,0) -> 0 | W97: =IFERROR(W65/W$87,0) -> 0 | X97: =IFERROR(X65/X$87,0) -> 0
B98: Breaktime | C98: % | E98: =IFERROR(E66/E$87,0) -> 0 | G98: =IFERROR(G66/G$87,0) -> 0.41811594 | H98: =IFERROR(H66/H$87,0) -> 0.34233941 | I98: =IFERROR(I66/I$87,0) -> 0.49056713 | J98: =IFERROR(J66/J$87,0) -> 0 | K98: =IFERROR(K66/K$87,0) -> 0 | L98: =IFERROR(L66/L$87,0) -> 0 | M98: =IFERROR(M66/M$87,0) -> 0 | N98: =IFERROR(N66/N$87,0) -> 0 | ... S98: =IFERROR(S66/S$87,0) -> 0.41374592 | U98: =IFERROR(U66/U$87,0) -> 0.41374592 | V98: =IFERROR(V66/V$87,0) -> 0 | W98: =IFERROR(W66/W$87,0) -> 0 | X98: =IFERROR(X66/X$87,0) -> 0
B99: Preventitve Maintenance | C99: % | E99: =IFERROR(E67/E$87,0) -> 0 | G99: =IFERROR(G67/G$87,0) -> 0.024154589 | H99: =IFERROR(H67/H$87,0) -> 0.037796586 | I99: =IFERROR(I67/I$87,0) -> 0.023784722 | J99: =IFERROR(J67/J$87,0) -> 0 | K99: =IFERROR(K67/K$87,0) -> 0 | L99: =IFERROR(L67/L$87,0) -> 0 | M99: =IFERROR(M67/M$87,0) -> 0 | N99: =IFERROR(N67/N$87,0) -> 0 | ... S99: =IFERROR(S67/S$87,0) -> 0.028855188 | U99: =IFERROR(U67/U$87,0) -> 0.028855188 | V99: =IFERROR(V67/V$87,0) -> 0 | W99: =IFERROR(W67/W$87,0) -> 0 | X99: =IFERROR(X67/X$87,0) -> 0
B100: Force Majeure | C100: % | E100: =IFERROR(E68/E$87,0) -> 0 | G100: =IFERROR(G68/G$87,0) -> 0.0014266304 | H100: =IFERROR(H68/H$87,0) -> 0.00083188657 | I100: =IFERROR(I68/I$87,0) -> 0.00074404762 | J100: =IFERROR(J68/J$87,0) -> 0 | K100: =IFERROR(K68/K$87,0) -> 0 | L100: =IFERROR(L68/L$87,0) -> 0 | M100: =IFERROR(M68/M$87,0) -> 0 | N100: =IFERROR(N68/N$87,0) -> 0 | ... S100: =IFERROR(S68/S$87,0) -> 0.0010059232 | U100: =IFERROR(U68/U$87,0) -> 0.0010059232 | V100: =IFERROR(V68/V$87,0) -> 0 | W100: =IFERROR(W68/W$87,0) -> 0 | X100: =IFERROR(X68/X$87,0) -> 0
B101: Electrical Breakdown | C101: % | E101: =IFERROR(E69/E$87,0) -> 0 | G101: =IFERROR(G69/G$87,0) -> 0.0076539855 | H101: =IFERROR(H69/H$87,0) -> 0.0048683449 | I101: =IFERROR(I69/I$87,0) -> 0.0038029101 | J101: =IFERROR(J69/J$87,0) -> 0 | K101: =IFERROR(K69/K$87,0) -> 0 | L101: =IFERROR(L69/L$87,0) -> 0 | M101: =IFERROR(M69/M$87,0) -> 0 | N101: =IFERROR(N69/N$87,0) -> 0 | ... S101: =IFERROR(S69/S$87,0) -> 0.0054815155 | U101: =IFERROR(U69/U$87,0) -> 0.0054815155 | V101: =IFERROR(V69/V$87,0) -> 0 | W101: =IFERROR(W69/W$87,0) -> 0 | X101: =IFERROR(X69/X$87,0) -> 0
... B111: Idle time | C111: % | E111: =IFERROR(E79/E$87,0) -> 0 | G111: =IFERROR(G79/G$87,0) -> 0.00037741546 | H111: =IFERROR(H79/H$87,0) -> 0.00068721065 | I111: =IFERROR(I79/I$87,0) -> 0.00090112434 | J111: =IFERROR(J79/J$87,0) -> 0 | K111: =IFERROR(K79/K$87,0) -> 0 | L111: =IFERROR(L79/L$87,0) -> 0 | M111: =IFERROR(M79/M$87,0) -> 0 | N111: =IFERROR(N79/N$87,0) -> 0 | ... S111: =IFERROR(S79/S$87,0) -> 0.00064848856 | U111: =IFERROR(U79/U$87,0) -> 0.00064848856 | V111: =IFERROR(V79/V$87,0) -> 0 | W111: =IFERROR(W79/W$87,0) -> 0 | X111: =IFERROR(X79/X$87,0) -> 0
B112: TOTAL | C112: % | E112: =IFERROR(E87/E87,0) -> 0 | G112: =IFERROR(G87/G87,0) -> 1 | H112: =IFERROR(H87/H87,0) -> 1 | I112: =IFERROR(I87/I87,0) -> 1 | J112: =IFERROR(J87/J87,0) -> 0 | K112: =IFERROR(K87/K87,0) -> 0 | L112: =IFERROR(L87/L87,0) -> 0 | M112: =IFERROR(M87/M87,0) -> 0 | N112: =IFERROR(N87/N87,0) -> 0 | ... S112: =IFERROR(S87/S87,0) -> 1 | U112: =IFERROR(U87/U$87,0) -> 1 | V112: =IFERROR(V87/V87,0) -> 0 | W112: =IFERROR(W87/W87,0) -> 0 | X112: =IFERROR(X87/X87,0) -> 0
B113: # of Machines available | E113: 4 | G113: 4 | H113: 4 | I113: 4 | S113: 4 | U113: =SUMIFS($G113:$R113,$G$5:$R$5,U$6) -> 12 | V113: =SUMIFS($G113:$R113,$G$5:$R$5,V$6) -> 0 | W113: =SUMIFS($G113:$R113,$G$5:$R$5,W$6) -> 0 | X113: =SUMIFS($G113:$R113,$G$5:$R$5,X$6) -> 0
B114: # of Machines used | E114: 4 | G114: 4 | H114: 4 | I114: 4 | S114: 4 | U114: =SUMIFS($G114:$R114,$G$5:$R$5,U$6) -> 12 | V114: =SUMIFS($G114:$R114,$G$5:$R$5,V$6) -> 0 | W114: =SUMIFS($G114:$R114,$G$5:$R$5,W$6) -> 0 | X114: =SUMIFS($G114:$R114,$G$5:$R$5,X$6) -> 0
B115: Production Days | G115: 19.75 | H115: 23.65 | I115: 19.45 | S115: =SUM(G115:R115) -> 62.85 | U115: =SUMIFS($G115:$R115,$G$5:$R$5,U$6) -> 62.85 | V115: =SUMIFS($G115:$R115,$G$5:$R$5,V$6) -> 0 | W115: =SUMIFS($G115:$R115,$G$5:$R$5,W$6) -> 0 | X115: =SUMIFS($G115:$R115,$G$5:$R$5,X$6) -> 0
B116: % Utilization | E116: =IFERROR(E87/(E115*E113*24),0) -> 0 | G116: =IFERROR(G87/(G115*G113*24),0) -> 1.164557 | H116: =IFERROR(H87/(H115*H113*24),0) -> 1.0147992 | I116: =IFERROR(I87/(I115*I113*24),0) -> 1.0796915 | J116: =IFERROR(J87/(J115*J113*24),0) -> 0 | K116: =IFERROR(K87/(K115*K113*24),0) -> 0 | L116: =IFERROR(L87/(L115*L113*24),0) -> 0 | M116: =IFERROR(M87/(M115*M113*24),0) -> 0 | N116: =IFERROR(N87/(N115*N113*24),0) -> 0 | ... S116: =IFERROR(S87/(S115*S113*24),0) -> 1.0819411 | U116: =IFERROR(U87/(U115*U113*24),0) -> 0.36064704 | V116: =IFERROR(V87/(V115*V113*24),0) -> 0 | W116: =IFERROR(W87/(W115*W113*24),0) -> 0 | X116: =IFERROR(X87/(X115*X113*24),0) -> 0
N117: =(N87/24)/4 -> 0 | O117: =(O87/24)/O113 -> #DIV/0! | W117: =(W87/24)/W113 -> #DIV/0!
B118: LINE 6- EPOXY LINE (MIXER)
B119: Actual Productive Time | C119: HRS | G119: 610.2 | H119: 901.96667 | I119: 590.7 | S119: =SUM(G119:R119) -> 2102.8667 | U119: =SUMIFS($G119:$R119,$G$5:$R$5,U$6) -> 2102.8667 | V119: =SUMIFS($G119:$R119,$G$5:$R$5,V$6) -> 0 | W119: =SUMIFS($G119:$R119,$G$5:$R$5,W$6) -> 0 | X119: =SUMIFS($G119:$R119,$G$5:$R$5,X$6) -> 0
B120: No Production Plan | C120: HRS | G120: 233.6 | H120: 0.5 | I120: 4.0666667 | S120: =SUM(G120:R120) -> 238.16667 | U120: =SUMIFS($G120:$R120,$G$5:$R$5,U$6) -> 238.16667 | V120: =SUMIFS($G120:$R120,$G$5:$R$5,V$6) -> 0 | W120: =SUMIFS($G120:$R120,$G$5:$R$5,W$6) -> 0 | X120: =SUMIFS($G120:$R120,$G$5:$R$5,X$6) -> 0
B121: No Head Count Allocation | C121: HRS | G121: 104.91667 | H121: 0 | I121: 23.7 | S121: =SUM(G121:R121) -> 128.61667 | U121: =SUMIFS($G121:$R121,$G$5:$R$5,U$6) -> 128.61667 | V121: =SUMIFS($G121:$R121,$G$5:$R$5,V$6) -> 0 | W121: =SUMIFS($G121:$R121,$G$5:$R$5,W$6) -> 0 | X121: =SUMIFS($G121:$R121,$G$5:$R$5,X$6) -> 0
B122: Change Over Time | C122: HRS | G122: 42.466667 | H122: 71.633333 | I122: 36.283333 | S122: =SUM(G122:R122) -> 150.38333 | U122: =SUMIFS($G122:$R122,$G$5:$R$5,U$6) -> 150.38333 | V122: =SUMIFS($G122:$R122,$G$5:$R$5,V$6) -> 0 | W122: =SUMIFS($G122:$R122,$G$5:$R$5,W$6) -> 0 | X122: =SUMIFS($G122:$R122,$G$5:$R$5,X$6) -> 0
B123: Meeting | C123: HRS | G123: 0.95 | H123: 1.6666667 | I123: 1.3333333 | S123: =SUM(G123:R123) -> 3.95 | U123: =SUMIFS($G123:$R123,$G$5:$R$5,U$6) -> 3.95 | V123: =SUMIFS($G123:$R123,$G$5:$R$5,V$6) -> 0 | W123: =SUMIFS($G123:$R123,$G$5:$R$5,W$6) -> 0 | X123: =SUMIFS($G123:$R123,$G$5:$R$5,X$6) -> 0
B124: Sanitation Time | C124: HRS | G124: 30.383333 | H124: 34.616667 | I124: 34.45 | S124: =SUM(G124:R124) -> 99.45 | U124: =SUMIFS($G124:$R124,$G$5:$R$5,U$6) -> 99.45 | V124: =SUMIFS($G124:$R124,$G$5:$R$5,V$6) -> 0 | W124: =SUMIFS($G124:$R124,$G$5:$R$5,W$6) -> 0 | X124: =SUMIFS($G124:$R124,$G$5:$R$5,X$6) -> 0
B125: Start-up Time/Setup | C125: HRS | G125: 36.7 | H125: 38.85 | I125: 27.866667 | S125: =SUM(G125:R125) -> 103.41667 | U125: =SUMIFS($G125:$R125,$G$5:$R$5,U$6) -> 103.41667 | V125: =SUMIFS($G125:$R125,$G$5:$R$5,V$6) -> 0 | W125: =SUMIFS($G125:$R125,$G$5:$R$5,W$6) -> 0 | X125: =SUMIFS($G125:$R125,$G$5:$R$5,X$6) -> 0
B126: Shutdown/cooldown | C126: HRS | G126: 0 | H126: 0 | I126: 0 | S126: =SUM(G126:R126) -> 0 | U126: =SUMIFS($G126:$R126,$G$5:$R$5,U$6) -> 0 | V126: =SUMIFS($G126:$R126,$G$5:$R$5,V$6) -> 0 | W126: =SUMIFS($G126:$R126,$G$5:$R$5,W$6) -> 0 | X126: =SUMIFS($G126:$R126,$G$5:$R$5,X$6) -> 0
B127: Testing Time | C127: HRS | G127: 0.11666667 | H127: 1.3666667 | I127: 4.4833333 | S127: =SUM(G127:R127) -> 5.9666667 | U127: =SUMIFS($G127:$R127,$G$5:$R$5,U$6) -> 5.9666667 | V127: =SUMIFS($G127:$R127,$G$5:$R$5,V$6) -> 0 | W127: =SUMIFS($G127:$R127,$G$5:$R$5,W$6) -> 0 | X127: =SUMIFS($G127:$R127,$G$5:$R$5,X$6) -> 0
B128: Breaktime | C128: HRS | G128: 1.75 | H128: 7.05 | I128: 13.116667 | S128: =SUM(G128:R128) -> 21.916667 | U128: =SUMIFS($G128:$R128,$G$5:$R$5,U$6) -> 21.916667 | V128: =SUMIFS($G128:$R128,$G$5:$R$5,V$6) -> 0 | W128: =SUMIFS($G128:$R128,$G$5:$R$5,W$6) -> 0 | X128: =SUMIFS($G128:$R128,$G$5:$R$5,X$6) -> 0
B129: Preventitve Maintenance | C129: HRS | G129: 0 | H129: 0 | I129: 0 | S129: =SUM(G129:R129) -> 0 | U129: =SUMIFS($G129:$R129,$G$5:$R$5,U$6) -> 0 | V129: =SUMIFS($G129:$R129,$G$5:$R$5,V$6) -> 0 | W129: =SUMIFS($G129:$R129,$G$5:$R$5,W$6) -> 0 | X129: =SUMIFS($G129:$R129,$G$5:$R$5,X$6) -> 0
B130: Force Majeure | C130: HRS | G130: 0 | H130: 0 | I130: 0 | S130: =SUM(G130:R130) -> 0 | U130: =SUMIFS($G130:$R130,$G$5:$R$5,U$6) -> 0 | V130: =SUMIFS($G130:$R130,$G$5:$R$5,V$6) -> 0 | W130: =SUMIFS($G130:$R130,$G$5:$R$5,W$6) -> 0 | X130: =SUMIFS($G130:$R130,$G$5:$R$5,X$6) -> 0
... B141: Idle time | C141: HRS | G141: 8.1166667 | H141: 16.283333 | I141: 30.416667 | S141: =SUM(G141:R141) -> 54.816667 | U141: =SUMIFS($G141:$R141,$G$5:$R$5,U$6) -> 54.816667 | V141: =SUMIFS($G141:$R141,$G$5:$R$5,V$6) -> 0 | W141: =SUMIFS($G141:$R141,$G$5:$R$5,W$6) -> 0 | X141: =SUMIFS($G141:$R141,$G$5:$R$5,X$6) -> 0
B142: TOTAL | C142: HRS | E142: =SUM(E119:E141) -> 0 | G142: =SUM(G119:G141) -> 1296 | H142: =SUM(H119:H141) -> 1152 | I142: =SUM(I119:I141) -> 1008 | J142: =SUM(J119:J141) -> 0 | K142: =SUM(K119:K141) -> 0 | L142: =SUM(L119:L141) -> 0 | M142: =SUM(M119:M141) -> 0 | N142: =SUM(N119:N141) -> 0 | ... S142: =SUM(S119:S141) -> 3456 | U142: =SUM(U119:U141) -> 3456 | V142: =SUM(V119:V141) -> 0 | W142: =SUM(W119:W141) -> 0 | X142: =SUM(X119:X141) -> 0
B144: Actual Productive Time | C144: % | E144: =IFERROR(E119/E$142,0) -> 0 | G144: =IFERROR(G119/G$142,0) -> 0.47083333 | H144: =IFERROR(H119/H$142,0) -> 0.78295718 | I144: =IFERROR(I119/I$142,0) -> 0.5860119 | J144: =IFERROR(J119/J$142,0) -> 0 | K144: =IFERROR(K119/K$142,0) -> 0 | L144: =IFERROR(L119/L$142,0) -> 0 | M144: =IFERROR(M119/M$142,0) -> 0 | N144: =IFERROR(N119/N$142,0) -> 0 | ... S144: =IFERROR(S119/S$142,0) -> 0.60846836 | U144: =IFERROR(U119/U$142,0) -> 0.60846836 | V144: =IFERROR(V119/V$142,0) -> 0 | W144: =IFERROR(W119/W$142,0) -> 0 | X144: =IFERROR(X119/X$142,0) -> 0
B145: No Production Plan | C145: % | E145: =IFERROR(E120/E$142,0) -> 0 | G145: =IFERROR(G120/G$142,0) -> 0.18024691 | H145: =IFERROR(H120/H$142,0) -> 0.00043402778 | I145: =IFERROR(I120/I$142,0) -> 0.0040343915 | J145: =IFERROR(J120/J$142,0) -> 0 | K145: =IFERROR(K120/K$142,0) -> 0 | L145: =IFERROR(L120/L$142,0) -> 0 | M145: =IFERROR(M120/M$142,0) -> 0 | N145: =IFERROR(N120/N$142,0) -> 0 | ... S145: =IFERROR(S120/S$142,0) -> 0.068913966 | U145: =IFERROR(U120/U$142,0) -> 0.068913966 | V145: =IFERROR(V120/V$142,0) -> 0 | W145: =IFERROR(W120/W$142,0) -> 0 | X145: =IFERROR(X120/X$142,0) -> 0
B146: No Head Count Allocation | C146: % | E146: =IFERROR(E121/E$142,0) -> 0 | G146: =IFERROR(G121/G$142,0) -> 0.080954218 | H146: =IFERROR(H121/H$142,0) -> 0 | I146: =IFERROR(I121/I$142,0) -> 0.023511905 | J146: =IFERROR(J121/J$142,0) -> 0 | K146: =IFERROR(K121/K$142,0) -> 0 | L146: =IFERROR(L121/L$142,0) -> 0 | M146: =IFERROR(M121/M$142,0) -> 0 | N146: =IFERROR(N121/N$142,0) -> 0 | ... S146: =IFERROR(S121/S$142,0) -> 0.037215471 | U146: =IFERROR(U121/U$142,0) -> 0.037215471 | V146: =IFERROR(V121/V$142,0) -> 0 | W146: =IFERROR(W121/W$142,0) -> 0 | X146: =IFERROR(X121/X$142,0) -> 0
B147: Change Over Time | C147: % | E147: =IFERROR(E122/E$142,0) -> 0 | G147: =IFERROR(G122/G$142,0) -> 0.03276749 | H147: =IFERROR(H122/H$142,0) -> 0.062181713 | I147: =IFERROR(I122/I$142,0) -> 0.03599537 | J147: =IFERROR(J122/J$142,0) -> 0 | K147: =IFERROR(K122/K$142,0) -> 0 | L147: =IFERROR(L122/L$142,0) -> 0 | M147: =IFERROR(M122/M$142,0) -> 0 | N147: =IFERROR(N122/N$142,0) -> 0 | ... S147: =IFERROR(S122/S$142,0) -> 0.043513696 | U147: =IFERROR(U122/U$142,0) -> 0.043513696 | V147: =IFERROR(V122/V$142,0) -> 0 | W147: =IFERROR(W122/W$142,0) -> 0 | X147: =IFERROR(X122/X$142,0) -> 0
B148: Meeting | C148: % | E148: =IFERROR(E123/E$142,0) -> 0 | G148: =IFERROR(G123/G$142,0) -> 0.00073302469 | H148: =IFERROR(H123/H$142,0) -> 0.0014467593 | I148: =IFERROR(I123/I$142,0) -> 0.0013227513 | J148: =IFERROR(J123/J$142,0) -> 0 | K148: =IFERROR(K123/K$142,0) -> 0 | L148: =IFERROR(L123/L$142,0) -> 0 | M148: =IFERROR(M123/M$142,0) -> 0 | N148: =IFERROR(N123/N$142,0) -> 0 | ... S148: =IFERROR(S123/S$142,0) -> 0.0011429398 | U148: =IFERROR(U123/U$142,0) -> 0.0011429398 | V148: =IFERROR(V123/V$142,0) -> 0 | W148: =IFERROR(W123/W$142,0) -> 0 | X148: =IFERROR(X123/X$142,0) -> 0
B149: Sanitation Time | C149: % | E149: =IFERROR(E124/E$142,0) -> 0 | G149: =IFERROR(G124/G$142,0) -> 0.02344393 | H149: =IFERROR(H124/H$142,0) -> 0.03004919 | I149: =IFERROR(I124/I$142,0) -> 0.034176587 | J149: =IFERROR(J124/J$142,0) -> 0 | K149: =IFERROR(K124/K$142,0) -> 0 | L149: =IFERROR(L124/L$142,0) -> 0 | M149: =IFERROR(M124/M$142,0) -> 0 | N149: =IFERROR(N124/N$142,0) -> 0 | ... S149: =IFERROR(S124/S$142,0) -> 0.028776042 | U149: =IFERROR(U124/U$142,0) -> 0.028776042 | V149: =IFERROR(V124/V$142,0) -> 0 | W149: =IFERROR(W124/W$142,0) -> 0 | X149: =IFERROR(X124/X$142,0) -> 0
B150: Start-up Time/Setup | C150: % | E150: =IFERROR(E125/E$142,0) -> 0 | G150: =IFERROR(G125/G$142,0) -> 0.028317901 | H150: =IFERROR(H125/H$142,0) -> 0.033723958 | I150: =IFERROR(I125/I$142,0) -> 0.027645503 | J150: =IFERROR(J125/J$142,0) -> 0 | K150: =IFERROR(K125/K$142,0) -> 0 | L150: =IFERROR(L125/L$142,0) -> 0 | M150: =IFERROR(M125/M$142,0) -> 0 | N150: =IFERROR(N125/N$142,0) -> 0 | ... S150: =IFERROR(S125/S$142,0) -> 0.029923804 | U150: =IFERROR(U125/U$142,0) -> 0.029923804 | V150: =IFERROR(V125/V$142,0) -> 0 | W150: =IFERROR(W125/W$142,0) -> 0 | X150: =IFERROR(X125/X$142,0) -> 0
B151: Shutdown/cooldown | C151: % | E151: =IFERROR(E126/E$142,0) -> 0 | G151: =IFERROR(G126/G$142,0) -> 0 | H151: =IFERROR(H126/H$142,0) -> 0 | I151: =IFERROR(I126/I$142,0) -> 0 | J151: =IFERROR(J126/J$142,0) -> 0 | K151: =IFERROR(K126/K$142,0) -> 0 | L151: =IFERROR(L126/L$142,0) -> 0 | M151: =IFERROR(M126/M$142,0) -> 0 | N151: =IFERROR(N126/N$142,0) -> 0 | ... S151: =IFERROR(S126/S$142,0) -> 0 | U151: =IFERROR(U126/U$142,0) -> 0 | V151: =IFERROR(V126/V$142,0) -> 0 | W151: =IFERROR(W126/W$142,0) -> 0 | X151: =IFERROR(X126/X$142,0) -> 0
...

Sheet WHSE & LOGS
A1: PIONEER
A2: 2026 KPI TRACKER
A3: SC - LOGISTICS
G5: Q1 | H5: Q1 | I5: Q1 | J5: Q2 | K5: Q2 | L5: Q2 | M5: Q3 | N5: Q3 | O5: Q3 | P5: Q4 | Q5: Q4 | R5: Q4
C6: UoM | E6: 2026 ABP | G6: OCT | H6: NOV | I6: DEC | J6: JAN | K6: FEB | L6: MAR | M6: APR | N6: MAY | O6: JUN | P6: JUL | Q6: AUG | R6: SEP | S6: 2026 YTD | U6: Q1 | V6: Q2 | W6: Q3 | X6: Q4
A8: A. | B8: OTIF PER PESO VALUE
B9: Served per Line item | C9: count | R9: =R14 | S9: =SUM(G9:R9) -> 0 | U9: =SUMIFS($G9:$R9,'SCM - PLANNING'!$G$5:$R$5,'SCM - PLANNING'!U$6) -> 0 | V9: =SUMIFS($G9:$R9,'SCM - PLANNING'!$G$5:$R$5,'SCM - PLANNING'!V$6) -> 0 | W9: =SUMIFS($G9:$R9,'SCM - PLANNING'!$G$5:$R$5,'SCM - PLANNING'!W$6) -> 0 | X9: =SUMIFS($G9:$R9,'SCM - PLANNING'!$G$5:$R$5,'SCM - PLANNING'!X$6) -> 0
B10: Total per Line Item | C10: count | R10: =R15 | S10: =SUM(G10:R10) -> 0 | U10: =SUMIFS($G10:$R10,'SCM - PLANNING'!$G$5:$R$5,'SCM - PLANNING'!U$6) -> 0 | V10: =SUMIFS($G10:$R10,'SCM - PLANNING'!$G$5:$R$5,'SCM - PLANNING'!V$6) -> 0 | W10: =SUMIFS($G10:$R10,'SCM - PLANNING'!$G$5:$R$5,'SCM - PLANNING'!W$6) -> 0 | X10: =SUMIFS($G10:$R10,'SCM - PLANNING'!$G$5:$R$5,'SCM - PLANNING'!X$6) -> 0
B11: OTIF RATE | C11: % | E11: 0.98 | G11: =IFERROR(G9/G10,0) -> 0 | H11: =IFERROR(H9/H10,0) -> 0 | I11: =IFERROR(I9/I10,0) -> 0 | J11: =IFERROR(J9/J10,0) -> 0 | K11: =IFERROR(K9/K10,0) -> 0 | L11: =IFERROR(L9/L10,0) -> 0 | M11: =IFERROR(M9/M10,0) -> 0 | N11: =IFERROR(N9/N10,0) -> 0 | ... S11: =IFERROR(S9/S10,0) -> 0 | U11: =IFERROR(U9/U10,0) -> 0 | V11: =IFERROR(V9/V10,0) -> 0 | W11: =IFERROR(W9/W10,0) -> 0 | X11: =IFERROR(X9/X10,0) -> 0
A13: B. | B13: Volume Fill Rate (Corporate Fillrate)
B14: Actual Delivered | C14: PHP | G14: 111890730 | H14: 1.4536511e+08 | I14: 2.4979807e+08 | J14: 260557368 | S14: =SUM(G14:R14) -> 7.6761127e+08 | U14: =SUMIFS($G14:$R14,'SCM - PLANNING'!$G$5:$R$5,'SCM - PLANNING'!U$6) -> 5.0705391e+08 | V14: =SUMIFS($G14:$R14,'SCM - PLANNING'!$G$5:$R$5,'SCM - PLANNING'!V$6) -> 260557368 | W14: =SUMIFS($G14:$R14,'SCM - PLANNING'!$G$5:$R$5,'SCM - PLANNING'!W$6) -> 0 | X14: =SUMIFS($G14:$R14,'SCM - PLANNING'!$G$5:$R$5,'SCM - PLANNING'!X$6) -> 0
B15: Actual Orders | C15: PHP | G15: 252093285 | H15: 4.0545527e+08 | I15: 3.0275088e+08 | J15: 295860615 | S15: =SUM(G15:R15) -> 1256160052 | U15: =SUMIFS($G15:$R15,'SCM - PLANNING'!$G$5:$R$5,'SCM - PLANNING'!U$6) -> 9.6029944e+08 | V15: =SUMIFS($G15:$R15,'SCM - PLANNING'!$G$5:$R$5,'SCM - PLANNING'!V$6) -> 295860615 | W15: =SUMIFS($G15:$R15,'SCM - PLANNING'!$G$5:$R$5,'SCM - PLANNING'!W$6) -> 0 | X15: =SUMIFS($G15:$R15,'SCM - PLANNING'!$G$5:$R$5,'SCM - PLANNING'!X$6) -> 0
B16: Hit Rate | C16: % | E16: 1 | G16: =IFERROR(G14/G15,0) -> 0.44384653 | H16: =IFERROR(H14/H15,0) -> 0.35852317 | I16: =IFERROR(I14/I15,0) -> 0.82509444 | J16: =IFERROR(J14/J15,0) -> 0.88067608 | K16: =IFERROR(K14/K15,0) -> 0 | L16: =IFERROR(L14/L15,0) -> 0 | M16: =IFERROR(M14/M15,0) -> 0 | N16: =IFERROR(N14/N15,0) -> 0 | ... S16: =IFERROR(S14/S15,0) -> 0.6110776 | U16: =IFERROR(U14/U15,0) -> 0.52801646 | V16: =IFERROR(V14/V15,0) -> 0.88067608 | W16: =IFERROR(W14/W15,0) -> 0 | X16: =IFERROR(X14/X15,0) -> 0
A18: C. | B18: Value Fill Rate (SC Fillrate)
B19: Actual Delivered (SI) million | C19: PHP | G19: 111890730 | H19: 1.4536511e+08 | I19: 2.4979807e+08 | J19: 260557368 | S19: =SUM(G19:R19) -> 7.6761127e+08 | U19: =SUMIFS($G19:$R19,'SCM - PLANNING'!$G$5:$R$5,'SCM - PLANNING'!U$6) -> 5.0705391e+08 | V19: =SUMIFS($G19:$R19,'SCM - PLANNING'!$G$5:$R$5,'SCM - PLANNING'!V$6) -> 260557368 | W19: =SUMIFS($G19:$R19,'SCM - PLANNING'!$G$5:$R$5,'SCM - PLANNING'!W$6) -> 0 | X19: =SUMIFS($G19:$R19,'SCM - PLANNING'!$G$5:$R$5,'SCM - PLANNING'!X$6) -> 0
B20: Actual Orders million | C20: PHP | G20: 186864585 | H20: 1.7997696e+08 | I20: 2.8393437e+08 | J20: 263346205 | S20: =SUM(G20:R20) -> 9.1412212e+08 | U20: =SUMIFS($G20:$R20,'SCM - PLANNING'!$G$5:$R$5,'SCM - PLANNING'!U$6) -> 6.5077592e+08 | V20: =SUMIFS($G20:$R20,'SCM - PLANNING'!$G$5:$R$5,'SCM - PLANNING'!V$6) -> 263346205 | W20: =SUMIFS($G20:$R20,'SCM - PLANNING'!$G$5:$R$5,'SCM - PLANNING'!W$6) -> 0 | X20: =SUMIFS($G20:$R20,'SCM - PLANNING'!$G$5:$R$5,'SCM - PLANNING'!X$6) -> 0
B21: Budget | C21: PHP
B22: Hit Rate | C22: % | E22: 1 | G22: =IFERROR(G19/G20,0) -> 0.59877975 | H22: =IFERROR(H19/H20,0) -> 0.8076873 | I22: =IFERROR(I19/I20,0) -> 0.87977398 | J22: =IFERROR(J19/J20,0) -> 0.98941 | K22: =IFERROR(K19/K20,0) -> 0 | L22: =IFERROR(L19/L20,0) -> 0 | M22: =IFERROR(M19/M20,0) -> 0 | N22: =IFERROR(N19/N20,0) -> 0 | ... S22: =IFERROR(S19/S20,0) -> 0.83972508 | U22: =IFERROR(U19/U20,0) -> 0.77915284 | V22: =IFERROR(V19/V20,0) -> 0.98941 | W22: =IFERROR(W19/W20,0) -> 0 | X22: =IFERROR(X19/X20,0) -> 0
A24: C. | B24: Value Fill Rate (Corporate Fillrate)
B25: Actual Delivered (SI) million | C25: PHP | S25: =SUM(G25:R25) -> 0 | U25: =SUMIFS($G25:$R25,'SCM - PLANNING'!$G$5:$R$5,'SCM - PLANNING'!U$6) -> 0 | V25: =SUMIFS($G25:$R25,'SCM - PLANNING'!$G$5:$R$5,'SCM - PLANNING'!V$6) -> 0 | W25: =SUMIFS($G25:$R25,'SCM - PLANNING'!$G$5:$R$5,'SCM - PLANNING'!W$6) -> 0 | X25: =SUMIFS($G25:$R25,'SCM - PLANNING'!$G$5:$R$5,'SCM - PLANNING'!X$6) -> 0
B26: Actual Orders million | C26: PHP | S26: =SUM(G26:R26) -> 0 | U26: =SUMIFS($G26:$R26,'SCM - PLANNING'!$G$5:$R$5,'SCM - PLANNING'!U$6) -> 0 | V26: =SUMIFS($G26:$R26,'SCM - PLANNING'!$G$5:$R$5,'SCM - PLANNING'!V$6) -> 0 | W26: =SUMIFS($G26:$R26,'SCM - PLANNING'!$G$5:$R$5,'SCM - PLANNING'!W$6) -> 0 | X26: =SUMIFS($G26:$R26,'SCM - PLANNING'!$G$5:$R$5,'SCM - PLANNING'!X$6) -> 0
B27: Budget | C27: PHP
B28: Hit Rate | C28: % | E28: 1 | G28: =IFERROR(G25/G26,0) -> 0 | H28: =IFERROR(H25/H26,0) -> 0 | I28: =IFERROR(I25/I26,0) -> 0 | J28: =IFERROR(J25/J26,0) -> 0 | K28: =IFERROR(K25/K26,0) -> 0 | L28: =IFERROR(L25/L26,0) -> 0 | M28: =IFERROR(M25/M26,0) -> 0 | N28: =IFERROR(N25/N26,0) -> 0 | ... S28: =IFERROR(S25/S26,0) -> 0 | U28: =IFERROR(U25/U26,0) -> 0 | V28: =IFERROR(V25/V26,0) -> 0 | W28: =IFERROR(W25/W26,0) -> 0 | X28: =IFERROR(X25/X26,0) -> 0
A30: C.1 | B30: Value Fill Rate (Core product)
B31: Actual Delivered (SI) million | C31: PHP | S31: =SUM(G31:R31) -> 0 | U31: =SUMIFS($G31:$R31,'SCM - PLANNING'!$G$5:$R$5,'SCM - PLANNING'!U$6) -> 0 | V31: =SUMIFS($G31:$R31,'SCM - PLANNING'!$G$5:$R$5,'SCM - PLANNING'!V$6) -> 0 | W31: =SUMIFS($G31:$R31,'SCM - PLANNING'!$G$5:$R$5,'SCM - PLANNING'!W$6) -> 0 | X31: =SUMIFS($G31:$R31,'SCM - PLANNING'!$G$5:$R$5,'SCM - PLANNING'!X$6) -> 0
B32: Actual Orders million | C32: PHP | S32: =SUM(G32:R32) -> 0 | U32: =SUMIFS($G32:$R32,'SCM - PLANNING'!$G$5:$R$5,'SCM - PLANNING'!U$6) -> 0 | V32: =SUMIFS($G32:$R32,'SCM - PLANNING'!$G$5:$R$5,'SCM - PLANNING'!V$6) -> 0 | W32: =SUMIFS($G32:$R32,'SCM - PLANNING'!$G$5:$R$5,'SCM - PLANNING'!W$6) -> 0 | X32: =SUMIFS($G32:$R32,'SCM - PLANNING'!$G$5:$R$5,'SCM - PLANNING'!X$6) -> 0
B33: Budget | C33: PHP
B34: Hit Rate | C34: % | E34: 1 | G34: =IFERROR(G31/G32,0) -> 0 | H34: =IFERROR(H31/H32,0) -> 0 | I34: =IFERROR(I31/I32,0) -> 0 | J34: =IFERROR(J31/J32,0) -> 0 | K34: =IFERROR(K31/K32,0) -> 0 | L34: =IFERROR(L31/L32,0) -> 0 | M34: =IFERROR(M31/M32,0) -> 0 | N34: =IFERROR(N31/N32,0) -> 0 | ... S34: =IFERROR(S31/S32,0) -> 0 | U34: =IFERROR(U31/U32,0) -> 0 | V34: =IFERROR(V31/V32,0) -> 0 | W34: =IFERROR(W31/W32,0) -> 0 | X34: =IFERROR(X31/X32,0) -> 0
A36: C.2 | B36: Value Fill Rate (Emmerging)
B37: Actual Delivered (SI) million | C37: PHP | S37: =SUM(G37:R37) -> 0 | U37: =SUMIFS($G37:$R37,'SCM - PLANNING'!$G$5:$R$5,'SCM - PLANNING'!U$6) -> 0 | V37: =SUMIFS($G37:$R37,'SCM - PLANNING'!$G$5:$R$5,'SCM - PLANNING'!V$6) -> 0 | W37: =SUMIFS($G37:$R37,'SCM - PLANNING'!$G$5:$R$5,'SCM - PLANNING'!W$6) -> 0 | X37: =SUMIFS($G37:$R37,'SCM - PLANNING'!$G$5:$R$5,'SCM - PLANNING'!X$6) -> 0
B38: Actual Orders million | C38: PHP | S38: =SUM(G38:R38) -> 0 | U38: =SUMIFS($G38:$R38,'SCM - PLANNING'!$G$5:$R$5,'SCM - PLANNING'!U$6) -> 0 | V38: =SUMIFS($G38:$R38,'SCM - PLANNING'!$G$5:$R$5,'SCM - PLANNING'!V$6) -> 0 | W38: =SUMIFS($G38:$R38,'SCM - PLANNING'!$G$5:$R$5,'SCM - PLANNING'!W$6) -> 0 | X38: =SUMIFS($G38:$R38,'SCM - PLANNING'!$G$5:$R$5,'SCM - PLANNING'!X$6) -> 0
B39: Budget | C39: PHP
B40: Hit Rate | C40: % | E40: 1 | G40: =IFERROR(G37/G38,0) -> 0 | H40: =IFERROR(H37/H38,0) -> 0 | I40: =IFERROR(I37/I38,0) -> 0 | J40: =IFERROR(J37/J38,0) -> 0 | K40: =IFERROR(K37/K38,0) -> 0 | L40: =IFERROR(L37/L38,0) -> 0 | M40: =IFERROR(M37/M38,0) -> 0 | N40: =IFERROR(N37/N38,0) -> 0 | ... S40: =IFERROR(S37/S38,0) -> 0 | U40: =IFERROR(U37/U38,0) -> 0 | V40: =IFERROR(V37/V38,0) -> 0 | W40: =IFERROR(W37/W38,0) -> 0 | X40: =IFERROR(X37/X38,0) -> 0
A42: D. | B42: BREAKDOWN OF NON OTIF
A43: PL | B43: Material constraint | C43: count | S43: =SUM(G43:R43) -> 0 | U43: =SUMIFS($G43:$R43,'SCM - PLANNING'!$G$5:$R$5,'SCM - PLANNING'!U$6) -> 0 | V43: =SUMIFS($G43:$R43,'SCM - PLANNING'!$G$5:$R$5,'SCM - PLANNING'!V$6) -> 0 | W43: =SUMIFS($G43:$R43,'SCM - PLANNING'!$G$5:$R$5,'SCM - PLANNING'!W$6) -> 0 | X43: =SUMIFS($G43:$R43,'SCM - PLANNING'!$G$5:$R$5,'SCM - PLANNING'!X$6) -> 0
A44: PL | B44: Planning error | C44: count | S44: =SUM(G44:R44) -> 0 | U44: =SUMIFS($G44:$R44,'SCM - PLANNING'!$G$5:$R$5,'SCM - PLANNING'!U$6) -> 0 | V44: =SUMIFS($G44:$R44,'SCM - PLANNING'!$G$5:$R$5,'SCM - PLANNING'!V$6) -> 0 | W44: =SUMIFS($G44:$R44,'SCM - PLANNING'!$G$5:$R$5,'SCM - PLANNING'!W$6) -> 0 | X44: =SUMIFS($G44:$R44,'SCM - PLANNING'!$G$5:$R$5,'SCM - PLANNING'!X$6) -> 0
A45: PL | B45: Capacity Constraint | C45: count | S45: =SUM(G45:R45) -> 0 | U45: =SUMIFS($G45:$R45,'SCM - PLANNING'!$G$5:$R$5,'SCM - PLANNING'!U$6) -> 0 | V45: =SUMIFS($G45:$R45,'SCM - PLANNING'!$G$5:$R$5,'SCM - PLANNING'!V$6) -> 0 | W45: =SUMIFS($G45:$R45,'SCM - PLANNING'!$G$5:$R$5,'SCM - PLANNING'!W$6) -> 0 | X45: =SUMIFS($G45:$R45,'SCM - PLANNING'!$G$5:$R$5,'SCM - PLANNING'!X$6) -> 0
A46: PL | B46: Acumatica Inventory Issue | C46: count | S46: =SUM(G46:R46) -> 0 | U46: =SUMIFS($G46:$R46,'SCM - PLANNING'!$G$5:$R$5,'SCM - PLANNING'!U$6) -> 0 | V46: =SUMIFS($G46:$R46,'SCM - PLANNING'!$G$5:$R$5,'SCM - PLANNING'!V$6) -> 0 | W46: =SUMIFS($G46:$R46,'SCM - PLANNING'!$G$5:$R$5,'SCM - PLANNING'!W$6) -> 0 | X46: =SUMIFS($G46:$R46,'SCM - PLANNING'!$G$5:$R$5,'SCM - PLANNING'!X$6) -> 0
A47: FG | B47: Warehouse Constraint | C47: count | S47: =SUM(G47:R47) -> 0 | U47: =SUMIFS($G47:$R47,'SCM - PLANNING'!$G$5:$R$5,'SCM - PLANNING'!U$6) -> 0 | V47: =SUMIFS($G47:$R47,'SCM - PLANNING'!$G$5:$R$5,'SCM - PLANNING'!V$6) -> 0 | W47: =SUMIFS($G47:$R47,'SCM - PLANNING'!$G$5:$R$5,'SCM - PLANNING'!W$6) -> 0 | X47: =SUMIFS($G47:$R47,'SCM - PLANNING'!$G$5:$R$5,'SCM - PLANNING'!X$6) -> 0
A48: FG | B48: Truck unavailability | C48: count | S48: =SUM(G48:R48) -> 0 | U48: =SUMIFS($G48:$R48,'SCM - PLANNING'!$G$5:$R$5,'SCM - PLANNING'!U$6) -> 0 | V48: =SUMIFS($G48:$R48,'SCM - PLANNING'!$G$5:$R$5,'SCM - PLANNING'!V$6) -> 0 | W48: =SUMIFS($G48:$R48,'SCM - PLANNING'!$G$5:$R$5,'SCM - PLANNING'!W$6) -> 0 | X48: =SUMIFS($G48:$R48,'SCM - PLANNING'!$G$5:$R$5,'SCM - PLANNING'!X$6) -> 0
A49: FG | B49: Dispatch Issue | C49: count | S49: =SUM(G49:R49) -> 0 | U49: =SUMIFS($G49:$R49,'SCM - PLANNING'!$G$5:$R$5,'SCM - PLANNING'!U$6) -> 0 | V49: =SUMIFS($G49:$R49,'SCM - PLANNING'!$G$5:$R$5,'SCM - PLANNING'!V$6) -> 0 | W49: =SUMIFS($G49:$R49,'SCM - PLANNING'!$G$5:$R$5,'SCM - PLANNING'!W$6) -> 0 | X49: =SUMIFS($G49:$R49,'SCM - PLANNING'!$G$5:$R$5,'SCM - PLANNING'!X$6) -> 0
A50: FG | B50: Custom Issue | C50: count | S50: =SUM(G50:R50) -> 0 | U50: =SUMIFS($G50:$R50,'SCM - PLANNING'!$G$5:$R$5,'SCM - PLANNING'!U$6) -> 0 | V50: =SUMIFS($G50:$R50,'SCM - PLANNING'!$G$5:$R$5,'SCM - PLANNING'!V$6) -> 0 | W50: =SUMIFS($G50:$R50,'SCM - PLANNING'!$G$5:$R$5,'SCM - PLANNING'!W$6) -> 0 | X50: =SUMIFS($G50:$R50,'SCM - PLANNING'!$G$5:$R$5,'SCM - PLANNING'!X$6) -> 0
A51: FG | B51: Permits | C51: count | S51: =SUM(G51:R51) -> 0 | U51: =SUMIFS($G51:$R51,'SCM - PLANNING'!$G$5:$R$5,'SCM - PLANNING'!U$6) -> 0 | V51: =SUMIFS($G51:$R51,'SCM - PLANNING'!$G$5:$R$5,'SCM - PLANNING'!V$6) -> 0 | W51: =SUMIFS($G51:$R51,'SCM - PLANNING'!$G$5:$R$5,'SCM - PLANNING'!W$6) -> 0 | X51: =SUMIFS($G51:$R51,'SCM - PLANNING'!$G$5:$R$5,'SCM - PLANNING'!X$6) -> 0
A52: PR | B52: Machine downtime | C52: count | S52: =SUM(G52:R52) -> 0 | U52: =SUMIFS($G52:$R52,'SCM - PLANNING'!$G$5:$R$5,'SCM - PLANNING'!U$6) -> 0 | V52: =SUMIFS($G52:$R52,'SCM - PLANNING'!$G$5:$R$5,'SCM - PLANNING'!V$6) -> 0 | W52: =SUMIFS($G52:$R52,'SCM - PLANNING'!$G$5:$R$5,'SCM - PLANNING'!W$6) -> 0 | X52: =SUMIFS($G52:$R52,'SCM - PLANNING'!$G$5:$R$5,'SCM - PLANNING'!X$6) -> 0
A53: PR | B53: Production Under run | C53: count | S53: =SUM(G53:R53) -> 0 | U53: =SUMIFS($G53:$R53,'SCM - PLANNING'!$G$5:$R$5,'SCM - PLANNING'!U$6) -> 0 | V53: =SUMIFS($G53:$R53,'SCM - PLANNING'!$G$5:$R$5,'SCM - PLANNING'!V$6) -> 0 | W53: =SUMIFS($G53:$R53,'SCM - PLANNING'!$G$5:$R$5,'SCM - PLANNING'!W$6) -> 0 | X53: =SUMIFS($G53:$R53,'SCM - PLANNING'!$G$5:$R$5,'SCM - PLANNING'!X$6) -> 0
A54: PR | B54: Manpower constraint | C54: count | S54: =SUM(G54:R54) -> 0 | U54: =SUMIFS($G54:$R54,'SCM - PLANNING'!$G$5:$R$5,'SCM - PLANNING'!U$6) -> 0 | V54: =SUMIFS($G54:$R54,'SCM - PLANNING'!$G$5:$R$5,'SCM - PLANNING'!V$6) -> 0 | W54: =SUMIFS($G54:$R54,'SCM - PLANNING'!$G$5:$R$5,'SCM - PLANNING'!W$6) -> 0 | X54: =SUMIFS($G54:$R54,'SCM - PLANNING'!$G$5:$R$5,'SCM - PLANNING'!X$6) -> 0
... A63: FI | B63: Pricing Issue | C63: count | S63: =SUM(G63:R63) -> 0 | U63: =SUMIFS($G63:$R63,'SCM - PLANNING'!$G$5:$R$5,'SCM - PLANNING'!U$6) -> 0 | V63: =SUMIFS($G63:$R63,'SCM - PLANNING'!$G$5:$R$5,'SCM - PLANNING'!V$6) -> 0 | W63: =SUMIFS($G63:$R63,'SCM - PLANNING'!$G$5:$R$5,'SCM - PLANNING'!W$6) -> 0 | X63: =SUMIFS($G63:$R63,'SCM - PLANNING'!$G$5:$R$5,'SCM - PLANNING'!X$6) -> 0
B64: TOTAL UNSERVE | C64: count | G64: =SUM(G43:G63) -> 0 | H64: =SUM(H43:H63) -> 0 | I64: =SUM(I42:I63) -> 0 | J64: =SUM(J42:J63) -> 0 | K64: =SUM(K42:K63) -> 0 | L64: =SUM(L42:L63) -> 0 | M64: =SUM(M42:M63) -> 0 | N64: =SUM(N42:N63) -> 0 | O64: =SUM(O42:O63) -> 0 | P64: =SUM(P42:P63) -> 0 | ... S64: =SUM(S42:S63) -> 0 | U64: =SUMIFS($G64:$R64,'SCM - PLANNING'!$G$5:$R$5,'SCM - PLANNING'!U$6) -> 0 | V64: =SUMIFS($G64:$R64,'SCM - PLANNING'!$G$5:$R$5,'SCM - PLANNING'!V$6) -> 0 | W64: =SUMIFS($G64:$R64,'SCM - PLANNING'!$G$5:$R$5,'SCM - PLANNING'!W$6) -> 0 | X64: =SUMIFS($G64:$R64,'SCM - PLANNING'!$G$5:$R$5,'SCM - PLANNING'!X$6) -> 0
A66: E. | B66: STOCK OUTS
A67: PL | B67: Material constraint | C67: KGS | S67: =SUM(G67:R67) -> 0 | U67: =SUMIFS($G67:$R67,'SCM - PLANNING'!$G$5:$R$5,'SCM - PLANNING'!U$6) -> 0 | V67: =SUMIFS($G67:$R67,'SCM - PLANNING'!$G$5:$R$5,'SCM - PLANNING'!V$6) -> 0 | W67: =SUMIFS($G67:$R67,'SCM - PLANNING'!$G$5:$R$5,'SCM - PLANNING'!W$6) -> 0 | X67: =SUMIFS($G67:$R67,'SCM - PLANNING'!$G$5:$R$5,'SCM - PLANNING'!X$6) -> 0
A68: PL | B68: Planning error | C68: KGS | S68: =SUM(G68:R68) -> 0 | U68: =SUMIFS($G68:$R68,'SCM - PLANNING'!$G$5:$R$5,'SCM - PLANNING'!U$6) -> 0 | V68: =SUMIFS($G68:$R68,'SCM - PLANNING'!$G$5:$R$5,'SCM - PLANNING'!V$6) -> 0 | W68: =SUMIFS($G68:$R68,'SCM - PLANNING'!$G$5:$R$5,'SCM - PLANNING'!W$6) -> 0 | X68: =SUMIFS($G68:$R68,'SCM - PLANNING'!$G$5:$R$5,'SCM - PLANNING'!X$6) -> 0
A69: PL | B69: Capacity Constraint | C69: KGS | S69: =SUM(G69:R69) -> 0 | U69: =SUMIFS($G69:$R69,'SCM - PLANNING'!$G$5:$R$5,'SCM - PLANNING'!U$6) -> 0 | V69: =SUMIFS($G69:$R69,'SCM - PLANNING'!$G$5:$R$5,'SCM - PLANNING'!V$6) -> 0 | W69: =SUMIFS($G69:$R69,'SCM - PLANNING'!$G$5:$R$5,'SCM - PLANNING'!W$6) -> 0 | X69: =SUMIFS($G69:$R69,'SCM - PLANNING'!$G$5:$R$5,'SCM - PLANNING'!X$6) -> 0
A70: PL | B70: Acumatica Inventory Issue | C70: KGS | S70: =SUM(G70:R70) -> 0 | U70: =SUMIFS($G70:$R70,'SCM - PLANNING'!$G$5:$R$5,'SCM - PLANNING'!U$6) -> 0 | V70: =SUMIFS($G70:$R70,'SCM - PLANNING'!$G$5:$R$5,'SCM - PLANNING'!V$6) -> 0 | W70: =SUMIFS($G70:$R70,'SCM - PLANNING'!$G$5:$R$5,'SCM - PLANNING'!W$6) -> 0 | X70: =SUMIFS($G70:$R70,'SCM - PLANNING'!$G$5:$R$5,'SCM - PLANNING'!X$6) -> 0
A71: FG | B71: Warehouse Constraint | C71: KGS | S71: =SUM(G71:R71) -> 0 | U71: =SUMIFS($G71:$R71,'SCM - PLANNING'!$G$5:$R$5,'SCM - PLANNING'!U$6) -> 0 | V71: =SUMIFS($G71:$R71,'SCM - PLANNING'!$G$5:$R$5,'SCM - PLANNING'!V$6) -> 0 | W71: =SUMIFS($G71:$R71,'SCM - PLANNING'!$G$5:$R$5,'SCM - PLANNING'!W$6) -> 0 | X71: =SUMIFS($G71:$R71,'SCM - PLANNING'!$G$5:$R$5,'SCM - PLANNING'!X$6) -> 0
A72: FG | B72: Truck unavailability | C72: KGS | S72: =SUM(G72:R72) -> 0 | U72: =SUMIFS($G72:$R72,'SCM - PLANNING'!$G$5:$R$5,'SCM - PLANNING'!U$6) -> 0 | V72: =SUMIFS($G72:$R72,'SCM - PLANNING'!$G$5:$R$5,'SCM - PLANNING'!V$6) -> 0 | W72: =SUMIFS($G72:$R72,'SCM - PLANNING'!$G$5:$R$5,'SCM - PLANNING'!W$6) -> 0 | X72: =SUMIFS($G72:$R72,'SCM - PLANNING'!$G$5:$R$5,'SCM - PLANNING'!X$6) -> 0
A73: FG | B73: Dispatch Issue | C73: KGS | S73: =SUM(G73:R73) -> 0 | U73: =SUMIFS($G73:$R73,'SCM - PLANNING'!$G$5:$R$5,'SCM - PLANNING'!U$6) -> 0 | V73: =SUMIFS($G73:$R73,'SCM - PLANNING'!$G$5:$R$5,'SCM - PLANNING'!V$6) -> 0 | W73: =SUMIFS($G73:$R73,'SCM - PLANNING'!$G$5:$R$5,'SCM - PLANNING'!W$6) -> 0 | X73: =SUMIFS($G73:$R73,'SCM - PLANNING'!$G$5:$R$5,'SCM - PLANNING'!X$6) -> 0
A74: FG | B74: Custom Issue | C74: KGS | S74: =SUM(G74:R74) -> 0 | U74: =SUMIFS($G74:$R74,'SCM - PLANNING'!$G$5:$R$5,'SCM - PLANNING'!U$6) -> 0 | V74: =SUMIFS($G74:$R74,'SCM - PLANNING'!$G$5:$R$5,'SCM - PLANNING'!V$6) -> 0 | W74: =SUMIFS($G74:$R74,'SCM - PLANNING'!$G$5:$R$5,'SCM - PLANNING'!W$6) -> 0 | X74: =SUMIFS($G74:$R74,'SCM - PLANNING'!$G$5:$R$5,'SCM - PLANNING'!X$6) -> 0
A75: FG | B75: Permits | C75: KGS | S75: =SUM(G75:R75) -> 0 | U75: =SUMIFS($G75:$R75,'SCM - PLANNING'!$G$5:$R$5,'SCM - PLANNING'!U$6) -> 0 | V75: =SUMIFS($G75:$R75,'SCM - PLANNING'!$G$5:$R$5,'SCM - PLANNING'!V$6) -> 0 | W75: =SUMIFS($G75:$R75,'SCM - PLANNING'!$G$5:$R$5,'SCM - PLANNING'!W$6) -> 0 | X75: =SUMIFS($G75:$R75,'SCM - PLANNING'!$G$5:$R$5,'SCM - PLANNING'!X$6) -> 0
A76: PR | B76: Machine downtime | C76: KGS | S76: =SUM(G76:R76) -> 0 | U76: =SUMIFS($G76:$R76,'SCM - PLANNING'!$G$5:$R$5,'SCM - PLANNING'!U$6) -> 0 | V76: =SUMIFS($G76:$R76,'SCM - PLANNING'!$G$5:$R$5,'SCM - PLANNING'!V$6) -> 0 | W76: =SUMIFS($G76:$R76,'SCM - PLANNING'!$G$5:$R$5,'SCM - PLANNING'!W$6) -> 0 | X76: =SUMIFS($G76:$R76,'SCM - PLANNING'!$G$5:$R$5,'SCM - PLANNING'!X$6) -> 0
A77: PR | B77: Production Under run | C77: KGS | S77: =SUM(G77:R77) -> 0 | U77: =SUMIFS($G77:$R77,'SCM - PLANNING'!$G$5:$R$5,'SCM - PLANNING'!U$6) -> 0 | V77: =SUMIFS($G77:$R77,'SCM - PLANNING'!$G$5:$R$5,'SCM - PLANNING'!V$6) -> 0 | W77: =SUMIFS($G77:$R77,'SCM - PLANNING'!$G$5:$R$5,'SCM - PLANNING'!W$6) -> 0 | X77: =SUMIFS($G77:$R77,'SCM - PLANNING'!$G$5:$R$5,'SCM - PLANNING'!X$6) -> 0
A78: PR | B78: Manpower constraint | C78: KGS | S78: =SUM(G78:R78) -> 0 | U78: =SUMIFS($G78:$R78,'SCM - PLANNING'!$G$5:$R$5,'SCM - PLANNING'!U$6) -> 0 | V78: =SUMIFS($G78:$R78,'SCM - PLANNING'!$G$5:$R$5,'SCM - PLANNING'!V$6) -> 0 | W78: =SUMIFS($G78:$R78,'SCM - PLANNING'!$G$5:$R$5,'SCM - PLANNING'!W$6) -> 0 | X78: =SUMIFS($G78:$R78,'SCM - PLANNING'!$G$5:$R$5,'SCM - PLANNING'!X$6) -> 0
... A88: FI | B88: Pricing Issue | C88: KGS | S88: =SUM(G88:R88) -> 0 | U88: =SUMIFS($G88:$R88,'SCM - PLANNING'!$G$5:$R$5,'SCM - PLANNING'!U$6) -> 0 | V88: =SUMIFS($G88:$R88,'SCM - PLANNING'!$G$5:$R$5,'SCM - PLANNING'!V$6) -> 0 | W88: =SUMIFS($G88:$R88,'SCM - PLANNING'!$G$5:$R$5,'SCM - PLANNING'!W$6) -> 0 | X88: =SUMIFS($G88:$R88,'SCM - PLANNING'!$G$5:$R$5,'SCM - PLANNING'!X$6) -> 0
B89: TOTAL UNSERVE | C89: KGS | G89: =SUM(G66:G88) -> 0 | H89: =SUM(H66:H88) -> 0 | I89: =SUM(I66:I88) -> 0 | J89: =SUM(J66:J88) -> 0 | K89: =SUM(K66:K88) -> 0 | L89: =SUM(L66:L88) -> 0 | M89: =SUM(M66:M88) -> 0 | N89: =SUM(N66:N88) -> 0 | ... S89: =SUM(S66:S88) -> 0 | U89: =SUMIFS($G89:$R89,'SCM - PLANNING'!$G$5:$R$5,'SCM - PLANNING'!U$6) -> 0 | V89: =SUMIFS($G89:$R89,'SCM - PLANNING'!$G$5:$R$5,'SCM - PLANNING'!V$6) -> 0 | W89: =SUMIFS($G89:$R89,'SCM - PLANNING'!$G$5:$R$5,'SCM - PLANNING'!W$6) -> 0 | X89: =SUMIFS($G89:$R89,'SCM - PLANNING'!$G$5:$R$5,'SCM - PLANNING'!X$6) -> 0
A91: F. | B91: STOCK OUTS
A92: PL | B92: Material constraint | C92: PHP | S92: =SUM(G92:R92) -> 0 | U92: =SUMIFS($G92:$R92,'SCM - PLANNING'!$G$5:$R$5,'SCM - PLANNING'!U$6) -> 0 | V92: =SUMIFS($G92:$R92,'SCM - PLANNING'!$G$5:$R$5,'SCM - PLANNING'!V$6) -> 0 | W92: =SUMIFS($G92:$R92,'SCM - PLANNING'!$G$5:$R$5,'SCM - PLANNING'!W$6) -> 0 | X92: =SUMIFS($G92:$R92,'SCM - PLANNING'!$G$5:$R$5,'SCM - PLANNING'!X$6) -> 0
A93: PL | B93: Planning error | C93: PHP | S93: =SUM(G93:R93) -> 0 | U93: =SUMIFS($G93:$R93,'SCM - PLANNING'!$G$5:$R$5,'SCM - PLANNING'!U$6) -> 0 | V93: =SUMIFS($G93:$R93,'SCM - PLANNING'!$G$5:$R$5,'SCM - PLANNING'!V$6) -> 0 | W93: =SUMIFS($G93:$R93,'SCM - PLANNING'!$G$5:$R$5,'SCM - PLANNING'!W$6) -> 0 | X93: =SUMIFS($G93:$R93,'SCM - PLANNING'!$G$5:$R$5,'SCM - PLANNING'!X$6) -> 0
A94: PL | B94: Capacity Constraint | C94: PHP | S94: =SUM(G94:R94) -> 0 | U94: =SUMIFS($G94:$R94,'SCM - PLANNING'!$G$5:$R$5,'SCM - PLANNING'!U$6) -> 0 | V94: =SUMIFS($G94:$R94,'SCM - PLANNING'!$G$5:$R$5,'SCM - PLANNING'!V$6) -> 0 | W94: =SUMIFS($G94:$R94,'SCM - PLANNING'!$G$5:$R$5,'SCM - PLANNING'!W$6) -> 0 | X94: =SUMIFS($G94:$R94,'SCM - PLANNING'!$G$5:$R$5,'SCM - PLANNING'!X$6) -> 0
A95: PL | B95: Acumatica Inventory Issue | C95: PHP | S95: =SUM(G95:R95) -> 0 | U95: =SUMIFS($G95:$R95,'SCM - PLANNING'!$G$5:$R$5,'SCM - PLANNING'!U$6) -> 0 | V95: =SUMIFS($G95:$R95,'SCM - PLANNING'!$G$5:$R$5,'SCM - PLANNING'!V$6) -> 0 | W95: =SUMIFS($G95:$R95,'SCM - PLANNING'!$G$5:$R$5,'SCM - PLANNING'!W$6) -> 0 | X95: =SUMIFS($G95:$R95,'SCM - PLANNING'!$G$5:$R$5,'SCM - PLANNING'!X$6) -> 0
A96: FG | B96: Warehouse Constraint | C96: PHP | S96: =SUM(G96:R96) -> 0 | U96: =SUMIFS($G96:$R96,'SCM - PLANNING'!$G$5:$R$5,'SCM - PLANNING'!U$6) -> 0 | V96: =SUMIFS($G96:$R96,'SCM - PLANNING'!$G$5:$R$5,'SCM - PLANNING'!V$6) -> 0 | W96: =SUMIFS($G96:$R96,'SCM - PLANNING'!$G$5:$R$5,'SCM - PLANNING'!W$6) -> 0 | X96: =SUMIFS($G96:$R96,'SCM - PLANNING'!$G$5:$R$5,'SCM - PLANNING'!X$6) -> 0
A97: FG | B97: Truck unavailability | C97: PHP | S97: =SUM(G97:R97) -> 0 | U97: =SUMIFS($G97:$R97,'SCM - PLANNING'!$G$5:$R$5,'SCM - PLANNING'!U$6) -> 0 | V97: =SUMIFS($G97:$R97,'SCM - PLANNING'!$G$5:$R$5,'SCM - PLANNING'!V$6) -> 0 | W97: =SUMIFS($G97:$R97,'SCM - PLANNING'!$G$5:$R$5,'SCM - PLANNING'!W$6) -> 0 | X97: =SUMIFS($G97:$R97,'SCM - PLANNING'!$G$5:$R$5,'SCM - PLANNING'!X$6) -> 0
A98: FG | B98: Dispatch Issue | C98: PHP | S98: =SUM(G98:R98) -> 0 | U98: =SUMIFS($G98:$R98,'SCM - PLANNING'!$G$5:$R$5,'SCM - PLANNING'!U$6) -> 0 | V98: =SUMIFS($G98:$R98,'SCM - PLANNING'!$G$5:$R$5,'SCM - PLANNING'!V$6) -> 0 | W98: =SUMIFS($G98:$R98,'SCM - PLANNING'!$G$5:$R$5,'SCM - PLANNING'!W$6) -> 0 | X98: =SUMIFS($G98:$R98,'SCM - PLANNING'!$G$5:$R$5,'SCM - PLANNING'!X$6) -> 0
A99: FG | B99: Custom Issue | C99: PHP | S99: =SUM(G99:R99) -> 0 | U99: =SUMIFS($G99:$R99,'SCM - PLANNING'!$G$5:$R$5,'SCM - PLANNING'!U$6) -> 0 | V99: =SUMIFS($G99:$R99,'SCM - PLANNING'!$G$5:$R$5,'SCM - PLANNING'!V$6) -> 0 | W99: =SUMIFS($G99:$R99,'SCM - PLANNING'!$G$5:$R$5,'SCM - PLANNING'!W$6) -> 0 | X99: =SUMIFS($G99:$R99,'SCM - PLANNING'!$G$5:$R$5,'SCM - PLANNING'!X$6) -> 0
A100: FG | B100: Permits | C100: PHP | S100: =SUM(G100:R100) -> 0 | U100: =SUMIFS($G100:$R100,'SCM - PLANNING'!$G$5:$R$5,'SCM - PLANNING'!U$6) -> 0 | V100: =SUMIFS($G100:$R100,'SCM - PLANNING'!$G$5:$R$5,'SCM - PLANNING'!V$6) -> 0 | W100: =SUMIFS($G100:$R100,'SCM - PLANNING'!$G$5:$R$5,'SCM - PLANNING'!W$6) -> 0 | X100: =SUMIFS($G100:$R100,'SCM - PLANNING'!$G$5:$R$5,'SCM - PLANNING'!X$6) -> 0
A101: PR | B101: Machine downtime | C101: PHP | S101: =SUM(G101:R101) -> 0 | U101: =SUMIFS($G101:$R101,'SCM - PLANNING'!$G$5:$R$5,'SCM - PLANNING'!U$6) -> 0 | V101: =SUMIFS($G101:$R101,'SCM - PLANNING'!$G$5:$R$5,'SCM - PLANNING'!V$6) -> 0 | W101: =SUMIFS($G101:$R101,'SCM - PLANNING'!$G$5:$R$5,'SCM - PLANNING'!W$6) -> 0 | X101: =SUMIFS($G101:$R101,'SCM - PLANNING'!$G$5:$R$5,'SCM - PLANNING'!X$6) -> 0
A102: PR | B102: Production Under run | C102: PHP | S102: =SUM(G102:R102) -> 0 | U102: =SUMIFS($G102:$R102,'SCM - PLANNING'!$G$5:$R$5,'SCM - PLANNING'!U$6) -> 0 | V102: =SUMIFS($G102:$R102,'SCM - PLANNING'!$G$5:$R$5,'SCM - PLANNING'!V$6) -> 0 | W102: =SUMIFS($G102:$R102,'SCM - PLANNING'!$G$5:$R$5,'SCM - PLANNING'!W$6) -> 0 | X102: =SUMIFS($G102:$R102,'SCM - PLANNING'!$G$5:$R$5,'SCM - PLANNING'!X$6) -> 0
A103: PR | B103: Manpower constraint | C103: PHP | S103: =SUM(G103:R103) -> 0 | U103: =SUMIFS($G103:$R103,'SCM - PLANNING'!$G$5:$R$5,'SCM - PLANNING'!U$6) -> 0 | V103: =SUMIFS($G103:$R103,'SCM - PLANNING'!$G$5:$R$5,'SCM - PLANNING'!V$6) -> 0 | W103: =SUMIFS($G103:$R103,'SCM - PLANNING'!$G$5:$R$5,'SCM - PLANNING'!W$6) -> 0 | X103: =SUMIFS($G103:$R103,'SCM - PLANNING'!$G$5:$R$5,'SCM - PLANNING'!X$6) -> 0
... A113: FI | B113: Pricing Issue | C113: PHP | S113: =SUM(G113:R113) -> 0 | U113: =SUMIFS($G113:$R113,'SCM - PLANNING'!$G$5:$R$5,'SCM - PLANNING'!U$6) -> 0 | V113: =SUMIFS($G113:$R113,'SCM - PLANNING'!$G$5:$R$5,'SCM - PLANNING'!V$6) -> 0 | W113: =SUMIFS($G113:$R113,'SCM - PLANNING'!$G$5:$R$5,'SCM - PLANNING'!W$6) -> 0 | X113: =SUMIFS($G113:$R113,'SCM - PLANNING'!$G$5:$R$5,'SCM - PLANNING'!X$6) -> 0
B114: TOTAL UNSERVE | C114: PHP | G114: =SUM(G91:G113) -> 0 | H114: =SUM(H91:H113) -> 0 | I114: =SUM(I91:I113) -> 0 | J114: =SUM(J91:J113) -> 0 | K114: =SUM(K91:K113) -> 0 | L114: =SUM(L91:L113) -> 0 | M114: =SUM(M91:M113) -> 0 | N114: =SUM(N91:N113) -> 0 | ... S114: =SUM(S91:S113) -> 0 | U114: =SUM(U91:U113) -> 0 | V114: =SUM(V91:V113) -> 0 | W114: =SUM(W91:W113) -> 0 | X114: =SUM(X91:X113) -> 0
A116: G. | B116: OTDL
B117: GMA | C117: days | G117: 10.832496 | H117: 2.0349462 | I117: 2.7477876 | J117: 2.05 | S117: =SUM(G117:R117) -> 17.66523 | U117: =SUMIFS($G117:$R117,$G$5:$R$5,U$6) -> 15.61523 | V117: =SUMIFS($G117:$R117,$G$5:$R$5,V$6) -> 2.05 | W117: =SUMIFS($G117:$R117,$G$5:$R$5,W$6) -> 0 | X117: =SUMIFS($G117:$R117,$G$5:$R$5,X$6) -> 0
B118: NORTH LUZON | C118: days | G118: 20.665595 | H118: 6.6538462 | I118: 6.6538462 | J118: 10.461538 | S118: =SUM(G118:R118) -> 44.434826 | U118: =SUMIFS($G118:$R118,$G$5:$R$5,U$6) -> 33.973287 | V118: =SUMIFS($G118:$R118,$G$5:$R$5,V$6) -> 10.461538 | W118: =SUMIFS($G118:$R118,$G$5:$R$5,W$6) -> 0 | X118: =SUMIFS($G118:$R118,$G$5:$R$5,X$6) -> 0
B119: SOUTH LUZON | C119: days | G119: 16.846957 | H119: 5.776 | I119: 5.776 | J119: 9.1190476 | S119: =SUM(G119:R119) -> 37.518004 | U119: =SUMIFS($G119:$R119,$G$5:$R$5,U$6) -> 28.398957 | V119: =SUMIFS($G119:$R119,$G$5:$R$5,V$6) -> 9.1190476 | W119: =SUMIFS($G119:$R119,$G$5:$R$5,W$6) -> 0 | X119: =SUMIFS($G119:$R119,$G$5:$R$5,X$6) -> 0
B120: CENTRAL LUZOM | C120: days | S120: =SUM(G120:R120) -> 0 | U120: =SUMIFS($G120:$R120,$G$5:$R$5,U$6) -> 0 | V120: =SUMIFS($G120:$R120,$G$5:$R$5,V$6) -> 0 | W120: =SUMIFS($G120:$R120,$G$5:$R$5,W$6) -> 0 | X120: =SUMIFS($G120:$R120,$G$5:$R$5,X$6) -> 0
B121: VISAYAS | C121: days | G121: 26.797538 | S121: =SUM(G121:R121) -> 26.797538 | U121: =SUMIFS($G121:$R121,$G$5:$R$5,U$6) -> 26.797538 | V121: =SUMIFS($G121:$R121,$G$5:$R$5,V$6) -> 0 | W121: =SUMIFS($G121:$R121,$G$5:$R$5,W$6) -> 0 | X121: =SUMIFS($G121:$R121,$G$5:$R$5,X$6) -> 0
B122: MINDANAO | C122: days | G122: 26.540346 | H122: 13.085714 | I122: 13.333333 | J122: 18 | S122: =SUM(G122:R122) -> 70.959393 | U122: =SUMIFS($G122:$R122,$G$5:$R$5,U$6) -> 52.959393 | V122: =SUMIFS($G122:$R122,$G$5:$R$5,V$6) -> 18 | W122: =SUMIFS($G122:$R122,$G$5:$R$5,W$6) -> 0 | X122: =SUMIFS($G122:$R122,$G$5:$R$5,X$6) -> 0
B123: MODERN TRADE | C123: days | G123: 8.8760504 | H123: 4.875 | I123: 6.8984375 | J123: 1.6363636 | S123: =SUM(G123:R123) -> 22.285852 | U123: =SUMIFS($G123:$R123,$G$5:$R$5,U$6) -> 20.649488 | V123: =SUMIFS($G123:$R123,$G$5:$R$5,V$6) -> 1.6363636 | W123: =SUMIFS($G123:$R123,$G$5:$R$5,W$6) -> 0 | X123: =SUMIFS($G123:$R123,$G$5:$R$5,X$6) -> 0
B124: PAI OTDL | C124: days | S124: =SUM(G124:R124) -> 0 | U124: =SUMIFS($G124:$R124,$G$5:$R$5,U$6) -> 0 | V124: =SUMIFS($G124:$R124,$G$5:$R$5,V$6) -> 0 | W124: =SUMIFS($G124:$R124,$G$5:$R$5,W$6) -> 0 | X124: =SUMIFS($G124:$R124,$G$5:$R$5,X$6) -> 0
B125: OTDL RATE | C125: % | G125: =IFERROR(G124/#REF!,0) -> 0 | H125: =IFERROR(H124/#REF!,0) -> 0 | I125: =IFERROR(I124/#REF!,0) -> 0 | J125: =IFERROR(J124/#REF!,0) -> 0 | K125: =IFERROR(K124/#REF!,0) -> 0 | L125: =IFERROR(L124/#REF!,0) -> 0 | M125: =IFERROR(M124/#REF!,0) -> 0 | N125: =IFERROR(N124/#REF!,0) -> 0 | ... S125: =IFERROR(S124/#REF!,0) -> 0 | U125: =IFERROR(U124/#REF!,0) -> 0 | V125: =IFERROR(V124/#REF!,0) -> 0 | W125: =IFERROR(W124/#REF!,0) -> 0 | X125: =IFERROR(X124/#REF!,0) -> 0
A127: H. | B127: TRUCK UTILIZATION (volume)
B128: 10wheeler/wing van | C128: volume (cbm) | S128: =IFERROR(AVERAGE(G128:R128),0) -> 0 | U128: =IFERROR(AVERAGE(G128:I128),0) -> 0 | V128: =IFERROR(AVERAGE(J128:L128),0) -> 0 | W128: =IFERROR(AVERAGE(M128:O128),0) -> 0 | X128: =IFERROR(AVERAGE(P128:R128),0) -> 0
B129: AUV | C129: volume (cbm) | S129: =IFERROR(AVERAGE(G129:R129),0) -> 0 | U129: =IFERROR(AVERAGE(G129:I129),0) -> 0 | V129: =IFERROR(AVERAGE(J129:L129),0) -> 0 | W129: =IFERROR(AVERAGE(M129:O129),0) -> 0 | X129: =IFERROR(AVERAGE(P129:R129),0) -> 0
B130: 6 wheeler | C130: volume (cbm) | S130: =IFERROR(AVERAGE(G130:R130),0) -> 0 | U130: =IFERROR(AVERAGE(G130:I130),0) -> 0 | V130: =IFERROR(AVERAGE(J130:L130),0) -> 0 | W130: =IFERROR(AVERAGE(M130:O130),0) -> 0 | X130: =IFERROR(AVERAGE(P130:R130),0) -> 0
B131: 4 wheeler | C131: volume (cbm) | S131: =IFERROR(AVERAGE(G131:R131),0) -> 0 | U131: =IFERROR(AVERAGE(G131:I131),0) -> 0 | V131: =IFERROR(AVERAGE(J131:L131),0) -> 0 | W131: =IFERROR(AVERAGE(M131:O131),0) -> 0 | X131: =IFERROR(AVERAGE(P131:R131),0) -> 0
B132: 20-foot container | C132: volume (cbm) | S132: =IFERROR(AVERAGE(G132:R132),0) -> 0 | U132: =IFERROR(AVERAGE(G132:I132),0) -> 0 | V132: =IFERROR(AVERAGE(J132:L132),0) -> 0 | W132: =IFERROR(AVERAGE(M132:O132),0) -> 0 | X132: =IFERROR(AVERAGE(P132:R132),0) -> 0
B133: Truck Utilization | C133: % | G133: =IFERROR(SUM(G128:G132)/SUM($E$128:$E$132),0) -> 0 | H133: =IFERROR(SUM(H128:H132)/SUM($E$128:$E$132),0) -> 0 | I133: =IFERROR(SUM(I128:I132)/SUM($E$128:$E$132),0) -> 0 | J133: =IFERROR(SUM(J128:J132)/SUM($E$128:$E$132),0) -> 0 | K133: =IFERROR(SUM(K128:K132)/SUM($E$128:$E$132),0) -> 0 | L133: =IFERROR(SUM(L128:L132)/SUM($E$128:$E$132),0) -> 0 | M133: =IFERROR(SUM(M128:M132)/SUM($E$128:$E$132),0) -> 0 | N133: =IFERROR(SUM(N128:N132)/SUM($E$128:$E$132),0) -> 0 | ... S133: =IFERROR(SUM(S128:S132)/SUM($E$128:$E$132),0) -> 0 | U133: =IFERROR(SUM(U128:U132)/SUM($E$128:$E$132),0) -> 0 | V133: =IFERROR(SUM(V128:V132)/SUM($E$128:$E$132),0) -> 0 | W133: =IFERROR(SUM(W128:W132)/SUM($E$128:$E$132),0) -> 0 | X133: =IFERROR(SUM(X128:X132)/SUM($E$128:$E$132),0) -> 0
A135: I. | B135: FREIGHT COST - PER KILO
B136: GMA | C136: PHP | S136: =IFERROR(AVERAGE(G136:R136),0) -> 0 | U136: =SUMIFS($G136:$R136,'WHSE & LOGS'!$G$5:$R$5,'WHSE & LOGS'!U$6) -> 0 | V136: =SUMIFS($G136:$R136,'WHSE & LOGS'!$G$5:$R$5,'WHSE & LOGS'!V$6) -> 0 | W136: =SUMIFS($G136:$R136,'WHSE & LOGS'!$G$5:$R$5,'WHSE & LOGS'!W$6) -> 0 | X136: =SUMIFS($G136:$R136,'WHSE & LOGS'!$G$5:$R$5,'WHSE & LOGS'!X$6) -> 0
B137: NORTH LUZON | C137: PHP | S137: =IFERROR(AVERAGE(G137:R137),0) -> 0 | U137: =SUMIFS($G137:$R137,'WHSE & LOGS'!$G$5:$R$5,'WHSE & LOGS'!U$6) -> 0 | V137: =SUMIFS($G137:$R137,'WHSE & LOGS'!$G$5:$R$5,'WHSE & LOGS'!V$6) -> 0 | W137: =SUMIFS($G137:$R137,'WHSE & LOGS'!$G$5:$R$5,'WHSE & LOGS'!W$6) -> 0 | X137: =SUMIFS($G137:$R137,'WHSE & LOGS'!$G$5:$R$5,'WHSE & LOGS'!X$6) -> 0
B138: SOUTH LUZON | C138: PHP | S138: =IFERROR(AVERAGE(G138:R138),0) -> 0 | U138: =SUMIFS($G138:$R138,'WHSE & LOGS'!$G$5:$R$5,'WHSE & LOGS'!U$6) -> 0 | V138: =SUMIFS($G138:$R138,'WHSE & LOGS'!$G$5:$R$5,'WHSE & LOGS'!V$6) -> 0 | W138: =SUMIFS($G138:$R138,'WHSE & LOGS'!$G$5:$R$5,'WHSE & LOGS'!W$6) -> 0 | X138: =SUMIFS($G138:$R138,'WHSE & LOGS'!$G$5:$R$5,'WHSE & LOGS'!X$6) -> 0
B139: CENTRAL LUZON | C139: PHP | S139: =IFERROR(AVERAGE(G139:R139),0) -> 0 | U139: =SUMIFS($G139:$R139,'WHSE & LOGS'!$G$5:$R$5,'WHSE & LOGS'!U$6) -> 0 | V139: =SUMIFS($G139:$R139,'WHSE & LOGS'!$G$5:$R$5,'WHSE & LOGS'!V$6) -> 0 | W139: =SUMIFS($G139:$R139,'WHSE & LOGS'!$G$5:$R$5,'WHSE & LOGS'!W$6) -> 0 | X139: =SUMIFS($G139:$R139,'WHSE & LOGS'!$G$5:$R$5,'WHSE & LOGS'!X$6) -> 0
...

Sheet FINANCE DEPT
B2: KPI | C2: DEFINITION | D2: HOW TO GET | E2: UoM | G2: 2026 ABP | I2: OCT | J2: NOV | K2: DEC | L2: JAN | M2: FEB | N2: MAR | O2: APR | P2: MAY | Q2: JUN | R2: JUL | S2: AUG | T2: SEP | U2: 2026 ACTUAL
A3: BUSINESS GOALS:
A4: =MAX($A3:A$3)+1 -> 1 | B4: FINANCIALS
B5: Conversion Cost | E5: PHP/KG
B6: Conversion Cost (SC only) | E6: PHP/KG | G6: 11 | I6: 10.929592 | J6: 9.9039022 | K6: 14.391261 | L6: 9.9342105
B7: Conversion Cost (Overall) | E7: PHP/KG | G7: 15 | I7: 18.577245 | J7: 15.555569 | K7: 23.639818 | L7: 15.056688
B8: Volume produced (MT) Actual | E8: MT | G8: =U8 -> 5574.716 | I8: 1235.0772 | J8: 1603.4058 | K8: 1115.1986 | L8: 1621.0345 | U8: =SUM(I8:T8) -> 5574.716
B9: Volume produced (MT) Target | E9: MT | G9: 18814 | I9: 1221.8656 | J9: 1414.9244 | K9: 1090.6968 | L9: 1561.4227 | U9: =SUM(I9:T9) -> 5288.9096
B10: Volume produced % | E10: % | G10: =IFERROR(G8/G9,0) -> 0.29630679 | I10: =IFERROR(I8/I9,0) -> 1.0108127 | J10: =IFERROR(J8/J9,0) -> 1.1332095 | K10: =IFERROR(K8/K9,0) -> 1.0224643 | L10: =IFERROR(L8/L9,0) -> 1.0381779 | U10: =IFERROR(U8/U9,0) -> 1.0540388
A12: =MAX($A$3:A11)+1 -> 2 | B12: FINANCIALS
B13: Operational Cost
B14: Actual | E14: Php | I14: 13498890 | J14: 15879974 | K14: 16049114 | L14: 16103698
B15: Budget | E15: Php | I15: 16189431 | J15: 16210988 | K15: 17645273 | L15: 17976491 | M15: 16185973 | N15: 16413735 | O15: 17230887 | P15: 18623374 | Q15: 18089652 | R15: 18239848 | S15: 18330580 | T15: 18213005
B16: Operational Cost % | E16: % | I16: =IFERROR(I14/I15,0) -> 0.8338088 | J16: =IFERROR(J14/J15,0) -> 0.97958091 | K16: =IFERROR(K14/K15,0) -> 0.90954182 | L16: =IFERROR(L14/L15,0) -> 0.89581984
B18: Capital Expenditures | F18: on-going
B19: Actual | E19: Php | I19: =2042.36*1000 -> 2042360 | J19: =2033.33*1000 -> 2033330
B20: Budget | E20: Php | I20: =1946.8*1000 -> 1946800 | J20: =1966.8*1000 -> 1966800
B21: Capital Expenditures % | E21: % | I21: =IFERROR(I19/I20,0) -> 1.0490857 | J21: =IFERROR(J19/J20,0) -> 1.0338265
B23: Variance Analysis (Expense) | F23: on-going
B24: Actual | E24: Php | I24: =675.11*1000 -> 675110 | J24: =631.03*1000 -> 631030
B25: Budget | E25: Php | I25: =602.1*1000 -> 602100 | J25: =602.1*1000 -> 602100
B26: Variance Analysis (Expense) % | E26: % | I26: =IFERROR(I24/I25,0) -> 1.1212589 | J26: =IFERROR(J24/J25,0) -> 1.0480485 | U26: =SUM(I26:T26) -> 2.1693074
A28: =MAX($A27:A$40)+1 -> #REF! | B28: Workforce & Labor Reports
B29: Labor productivity
B30: Regular hours | E30: hrs | I30: =I33+I36 -> 36650.84 | J30: =J33+J36 -> 36117.1 | U30: =SUM(I30:T30) -> 72767.94
B31: Overtime hours | E31: hrs | I31: =I34+I37 -> 9705 | J31: =J34+J37 -> 11807 | U31: =SUM(I31:T31) -> 21512
B32: Overtime % | E32: % | I32: =IFERROR(I31/I30,0) -> 0.26479611 | J32: =IFERROR(J31/J30,0) -> 0.32690886 | U32: =IFERROR(U31/U30,0) -> 0.29562469
B33: Regular hours DL | E33: hrs | I33: 30584.01 | J33: 29807.03 | U33: =SUM(I33:T33) -> 60391.04
B34: Overtime hours DL | E34: hrs | I34: 7548.5 | J34: 10069.5 | U34: =SUM(I34:T34) -> 17618
B35: Overtime % | E35: % | I35: =IFERROR(I34/I33,0) -> 0.24681198 | J35: =IFERROR(J34/J33,0) -> 0.33782299 | U35: =IFERROR(U34/U33,0) -> 0.29173202
B36: Regular hours IL | E36: hrs | I36: 6066.83 | J36: 6310.07 | U36: =SUM(I36:T36) -> 12376.9
B37: Overtime hours IL | E37: hrs | I37: 2156.5 | J37: 1737.5 | U37: =SUM(I37:T37) -> 3894
B38: Overtime % | E38: % | I38: =IFERROR(I37/I36,0) -> 0.35545746 | J38: =IFERROR(J37/J36,0) -> 0.27535352 | U38: =IFERROR(U37/U36,0) -> 0.31461836
B39: Absenteeism
A43: =MAX($A$4:A11)+1 -> 2 | B43: IMPROVE QUALITY
B44: Customer Complaint | E44: COUNT | U44: =SUM(I44:T44) -> 0
B45: CARs Closed | E45: COUNT | U45: =SUM(I45:T45) -> 0
B46: % | E46: % | I46: =IFERROR(I45/I44,0) -> 0 | J46: =IFERROR(J45/J44,0) -> 0 | K46: =IFERROR(K45/K44,0) -> 0 | L46: =IFERROR(L45/L44,0) -> 0 | M46: =IFERROR(M45/M44,0) -> 0 | N46: =IFERROR(N45/N44,0) -> 0 | O46: =IFERROR(O45/O44,0) -> 0 | P46: =IFERROR(P45/P44,0) -> 0 | ... U46: =IFERROR(U45/U44,0) -> 0
A47: =MAX($A$43:A46)+1 -> 3 | B47: HEALTH & SAFETY GOALS
B48: Hazard Identified | E48: COUNT | U48: =SUM(I48:T48) -> 0
B49: CARs Closed | E49: COUNT | U49: =SUM(I49:T49) -> 0
B50: % | E50: % | I50: =IFERROR(I49/I48,0) -> 0 | J50: =IFERROR(J49/J48,0) -> 0 | K50: =IFERROR(K49/K48,0) -> 0 | L50: =IFERROR(L49/L48,0) -> 0 | M50: =IFERROR(M49/M48,0) -> 0 | N50: =IFERROR(N49/N48,0) -> 0 | O50: =IFERROR(O49/O48,0) -> 0 | P50: =IFERROR(P49/P48,0) -> 0 | ... U50: =IFERROR(U49/U48,0) -> 0
B51: Safety Violation | E51: COUNT | U51: =SUM(I51:T51) -> 0
B52: CARs Closed | E52: COUNT | U52: =SUM(I52:T52) -> 0
B53: % | E53: % | I53: =IFERROR(I52/I51,0) -> 0 | J53: =IFERROR(J52/J51,0) -> 0 | K53: =IFERROR(K52/K51,0) -> 0 | L53: =IFERROR(L52/L51,0) -> 0 | M53: =IFERROR(M52/M51,0) -> 0 | N53: =IFERROR(N52/N51,0) -> 0 | O53: =IFERROR(O52/O51,0) -> 0 | P53: =IFERROR(P52/P51,0) -> 0 | ... U53: =IFERROR(U52/U51,0) -> 0

Sheet OEE
A1: L06 | B1: 3558.7344 | C1: SET | D1: 2025 KPI - Actuals | E1: UoM | G1: Jan | H1: Feb | I1: Mar | J1: Apr | K1: May | L1: Jun | M1: Jul | N1: Aug | O1: Sep | P1: Oct | Q1: Nov | R1: Dec | S1: YTD | U1: 2025 KPI - Actuals | V1: UoM | X1: Jan | Y1: Feb | Z1: Mar | AA1: Apr | AB1: May | AC1: Jun | AD1: Jul | AE1: Aug | AF1: Sep | AG1: Oct | AH1: Nov | AI1: Dec | AJ1: YTD
B2: =B1/2 -> 1779.3672 | C2: A OR B | D2: OEE - LINE 06 FILLING | U2: OEE - LINE 06 MIXING
A3: L04 | B3: 1450 | C3: ES | D3: Availability | U3: Availability
A4: L04 | B4: 2366 | C4: BB | D4: Planned Run Time | E4: hr | K4: =PRODUCTION!N87 -> 0 | L4: =PRODUCTION!O87 -> 0 | S4: =SUM(G4:R4) -> 0 | U4: Planned Run Time | V4: hr | AB4: =PRODUCTION!N142 -> 0 | AC4: =PRODUCTION!O142 -> 0 | AJ4: =SUM(X4:AI4) -> 0
D5: Actual Run Time | E5: hr | K5: =PRODUCTION!N65 | L5: =PRODUCTION!O65 | S5: =SUM(G5:R5) -> 0 | U5: Actual Run Time | V5: hr | AB5: =PRODUCTION!N119 | AC5: =PRODUCTION!O119 | AJ5: =SUM(X5:AI5) -> 0
D6: Availability Rate | E6: % | G6: =IFERROR(G5/G4,0) -> 0 | H6: =IFERROR(H5/H4,0) -> 0 | I6: =IFERROR(I5/I4,0) -> 0 | J6: =IFERROR(J5/J4,0) -> 0 | K6: =IFERROR(K5/K4,0) -> 0 | L6: =IFERROR(L5/L4,0) -> 0 | M6: =IFERROR(M5/M4,0) -> 0 | N6: =IFERROR(N5/N4,0) -> 0 | ... S6: =IFERROR(S5/S4,0) -> 0 | U6: Availability Rate | V6: % | X6: =IFERROR(X5/X4,0) -> 0 | Y6: =IFERROR(Y5/Y4,0) -> 0 | Z6: =IFERROR(Z5/Z4,0) -> 0 | AA6: =IFERROR(AA5/AA4,0) -> 0 | AB6: =IFERROR(AB5/AB4,0) -> 0 | AC6: =IFERROR(AC5/AC4,0) -> 0 | AD6: =IFERROR(AD5/AD4,0) -> 0 | AE6: =IFERROR(AE5/AE4,0) -> 0 | ... AJ6: =IFERROR(AJ5/AJ4,0) -> 0
D8: Performance | U8: Performance
D9: Theoretical Output | E9: kgs | K9: =(24*24*60)*37.5 -> 1296000 | L9: =(22*24*60)*37.5 -> 1188000 | S9: =SUM(G9:R9) -> 2484000 | U9: Theoretical Output | V9: kgs | AB9: =(24*24*60)*37.5 -> 1296000 | AC9: =(22*24*60)*37.5 -> 1188000 | AJ9: =SUM(X9:AI9) -> 2484000
D10: Actual Output | E10: kgs | K10: =PRODUCTION!N985 | L10: =PRODUCTION!O985 | S10: =SUM(G10:R10) -> 0 | U10: Actual Output | V10: kgs | AB10: =PRODUCTION!N985 | AC10: =PRODUCTION!N985 | AJ10: =SUM(X10:AI10) -> 0
D11: Performance Rate | E11: % | G11: =IFERROR(G10/G9,0) -> 0 | H11: =IFERROR(H10/H9,0) -> 0 | I11: =IFERROR(I10/I9,0) -> 0 | J11: =IFERROR(J10/J9,0) -> 0 | K11: =IFERROR(K10/K9,0) -> 0 | L11: =IFERROR(L10/L9,0) -> 0 | M11: =IFERROR(M10/M9,0) -> 0 | N11: =IFERROR(N10/N9,0) -> 0 | ... S11: =IFERROR(S10/S9,0) -> 0 | U11: Performance Rate | V11: % | X11: =IFERROR(X10/X9,0) -> 0 | Y11: =IFERROR(Y10/Y9,0) -> 0 | Z11: =IFERROR(Z10/Z9,0) -> 0 | AA11: =IFERROR(AA10/AA9,0) -> 0 | AB11: =IFERROR(AB10/AB9,0) -> 0 | AC11: =IFERROR(AC10/AC9,0) -> 0 | AD11: =IFERROR(AD10/AD9,0) -> 0 | AE11: =IFERROR(AE10/AE9,0) -> 0 | ... AJ11: =IFERROR(AJ10/AJ9,0) -> 0
D13: Quality | U13: Quality
D14: Total Output | E14: kgs | K14: =PRODUCTION!N985 | L14: =PRODUCTION!O985 | S14: =SUM(G14:R14) -> 0 | U14: Total Output | V14: kgs | AB14: =PRODUCTION!N985 | AC14: =PRODUCTION!O985 | AJ14: =SUM(X14:AI14) -> 0
D15: Internal Rejection | E15: kgs | K15: =PRODUCTION!N986+PRODUCTION!N987 -> 0 | L15: =PRODUCTION!O986+PRODUCTION!O987 -> 0 | S15: =SUM(G15:R15) -> 0 | U15: Internal Rejection | V15: kgs | AB15: =PRODUCTION!N986+PRODUCTION!N987 -> 0 | AC15: =PRODUCTION!O986+PRODUCTION!O987 -> 0 | AJ15: =SUM(X15:AI15) -> 0
D16: Waste | E16: kgs | K16: =3558.7344*13 -> 46263.547 | L16: =3558.7344*4 -> 14234.938 | S16: =SUM(G16:R16) -> 60498.485 | T16: from QA data | U16: Waste | V16: kgs | AB16: =3558.7344*13 -> 46263.547 | AC16: =3558.7344*4 -> 14234.938 | AJ16: =SUM(X16:AI16) -> 60498.485 | AK16: from QA data
D17: Quality Rate | E17: % | G17: =IFERROR(G14/SUM(G14:G16),0) -> 0 | H17: =IFERROR(H14/SUM(H14:H16),0) -> 0 | I17: =IFERROR(I14/SUM(I14:I16),0) -> 0 | J17: =IFERROR(J14/SUM(J14:J16),0) -> 0 | K17: =IFERROR(K14/SUM(K14:K16),0) -> 0 | L17: =IFERROR(L14/SUM(L14:L16),0) -> 0 | M17: =IFERROR(M14/SUM(M14:M16),0) -> 0 | N17: =IFERROR(N14/SUM(N14:N16),0) -> 0 | ... S17: =IFERROR(S14/SUM(S14:S16),0) -> 0 | U17: Quality Rate | V17: % | X17: =IFERROR(X14/SUM(X14:X16),0) -> 0 | Y17: =IFERROR(Y14/SUM(Y14:Y16),0) -> 0 | Z17: =IFERROR(Z14/SUM(Z14:Z16),0) -> 0 | AA17: =IFERROR(AA14/SUM(AA14:AA16),0) -> 0 | AB17: =IFERROR(AB14/SUM(AB14:AB16),0) -> 0 | AC17: =IFERROR(AC14/SUM(AC14:AC16),0) -> 0 | AD17: =IFERROR(AD14/SUM(AD14:AD16),0) -> 0 | AE17: =IFERROR(AE14/SUM(AE14:AE16),0) -> 0 | ... AJ17: =IFERROR(AJ14/SUM(AJ14:AJ16),0) -> 0
D19: TOTAL OEE | E19: % | G19: =IFERROR(G6*G11*G17,0) -> 0 | H19: =IFERROR(H6*H11*H17,0) -> 0 | I19: =IFERROR(I6*I11*I17,0) -> 0 | J19: =IFERROR(J6*J11*J17,0) -> 0 | K19: =IFERROR(K6*K11*K17,0) -> 0 | L19: =IFERROR(L6*L11*L17,0) -> 0 | M19: =IFERROR(M6*M11*M17,0) -> 0 | N19: =IFERROR(N6*N11*N17,0) -> 0 | ... S19: =IFERROR(S6*S11*S17,0) -> 0 | U19: TOTAL OEE | V19: % | X19: =IFERROR(X6*X11*X17,0) -> 0 | Y19: =IFERROR(Y6*Y11*Y17,0) -> 0 | Z19: =IFERROR(Z6*Z11*Z17,0) -> 0 | AA19: =IFERROR(AA6*AA11*AA17,0) -> 0 | AB19: =IFERROR(AB6*AB11*AB17,0) -> 0 | AC19: =IFERROR(AC6*AC11*AC17,0) -> 0 | AD19: =IFERROR(AD6*AD11*AD17,0) -> 0 | AE19: =IFERROR(AE6*AE11*AE17,0) -> 0 | ... AJ19: =IFERROR(AJ6*AJ11*AJ17,0) -> 0
D22: Semi-automatic process capability yields 30% for Part A and 40% for Part B within specification.
D24: Quality
D25: Total Output | E25: kgs | K25: =PRODUCTION!N985 | L25: =PRODUCTION!O985 | S25: =SUM(G25:R25) -> 0
D26: Internal Rejection | E26: kgs | K26: =PRODUCTION!N986+PRODUCTION!N987 -> 0 | L26: =PRODUCTION!O986+PRODUCTION!O987 -> 0 | S26: =SUM(G26:R26) -> 0
D27: Waste (weight discrepancy) | E27: kgs | K27: =3558.7344*13 -> 46263.547 | L27: =3558.7344*4 -> 14234.938 | S27: =SUM(G27:R27) -> 60498.485
D28: Quality Rate | E28: % | G28: =AVERAGE(30%,40%) -> 0.35 | H28: =AVERAGE(30%,40%) -> 0.35 | I28: =AVERAGE(30%,40%) -> 0.35 | J28: =AVERAGE(30%,40%) -> 0.35 | K28: =AVERAGE(30%,40%) -> 0.35 | L28: =AVERAGE(30%,40%) -> 0.35 | M28: =AVERAGE(30%,40%) -> 0.35 | N28: =AVERAGE(30%,40%) -> 0.35 | ... S28: =AVERAGE(30%,40%) -> 0.35 | T28: comes from Ms. Liway weight analysis
D30: TOTAL OEE | E30: % | G30: =IFERROR(G6*G11*G28,0) -> 0 | H30: =IFERROR(H6*H11*H28,0) -> 0 | I30: =IFERROR(I6*I11*I28,0) -> 0 | J30: =IFERROR(J6*J11*J28,0) -> 0 | K30: =IFERROR(K6*K11*K28,0) -> 0 | L30: =IFERROR(L6*L11*L28,0) -> 0 | M30: =IFERROR(M6*M11*M28,0) -> 0 | N30: =IFERROR(N6*N11*N28,0) -> 0 | ... S30: =IFERROR(S6*S11*S28,0) -> 0
D35: 2025 KPI - Actuals | E35: UoM | G35: Jan | H35: Feb | I35: Mar | J35: Apr | K35: May | L35: Jun | M35: Jul | N35: Aug | O35: Sep | P35: Oct | Q35: Nov | R35: Dec | S35: YTD | U35: 2025 KPI - Actuals | V35: UoM | X35: Jan | Y35: Feb | Z35: Mar | AA35: Apr | AB35: May | AC35: Jun | AD35: Jul | AE35: Aug | AF35: Sep | AG35: Oct | AH35: Nov | AI35: Dec | AJ35: YTD
D36: OEE - LINE 04 FILLING | U36: OEE - LINE 04 MIXING
D37: Availability | U37: Availability
D38: Planned Run Time | E38: hr | K38: =PRODUCTION!N197 -> 0 | L38: =PRODUCTION!O197 -> 0 | S38: =SUM(G38:R38) -> 0 | U38: Planned Run Time | V38: hr | AB38: =PRODUCTION!N252 -> 0 | AC38: =PRODUCTION!O252 -> 0 | AJ38: =SUM(X38:AI38) -> 0
D39: Actual Run Time | E39: hr | K39: =PRODUCTION!N174 | L39: =PRODUCTION!O174 | S39: =SUM(G39:R39) -> 0 | U39: Actual Run Time | V39: hr | AB39: =PRODUCTION!N229 | AC39: =PRODUCTION!O229 | AJ39: =SUM(X39:AI39) -> 0
D40: Availability Rate | E40: % | G40: =IFERROR(G39/G38,0) -> 0 | H40: =IFERROR(H39/H38,0) -> 0 | I40: =IFERROR(I39/I38,0) -> 0 | J40: =IFERROR(J39/J38,0) -> 0 | K40: =IFERROR(K39/K38,0) -> 0 | L40: =IFERROR(L39/L38,0) -> 0 | M40: =IFERROR(M39/M38,0) -> 0 | N40: =IFERROR(N39/N38,0) -> 0 | ... S40: =IFERROR(S39/S38,0) -> 0 | U40: Availability Rate | V40: % | X40: =IFERROR(X39/X38,0) -> 0 | Y40: =IFERROR(Y39/Y38,0) -> 0 | Z40: =IFERROR(Z39/Z38,0) -> 0 | AA40: =IFERROR(AA39/AA38,0) -> 0 | AB40: =IFERROR(AB39/AB38,0) -> 0 | AC40: =IFERROR(AC39/AC38,0) -> 0 | AD40: =IFERROR(AD39/AD38,0) -> 0 | AE40: =IFERROR(AE39/AE38,0) -> 0 | ... AJ40: =IFERROR(AJ39/AJ38,0) -> 0
D42: Performance | U42: Performance
D43: Theoretical Output | E43: kgs | K43: =(24*24*60)*10.2754 -> 355117.82 | L43: =(24*24*60)*10.2754 -> 355117.82 | S43: =SUM(G43:R43) -> 710235.65 | U43: Theoretical Output | V43: kgs | AB43: =(24*24*60)*10.2754 -> 355117.82 | AC43: =(24*24*60)*10.2754 -> 355117.82 | AJ43: =SUM(X43:AI43) -> 710235.65
D44: Actual Output | E44: kgs | K44: =PRODUCTION!N996 | L44: =PRODUCTION!O996 | S44: =SUM(G44:R44) -> 0 | U44: Actual Output | V44: kgs | AB44: =PRODUCTION!N996 | AC44: =PRODUCTION!O996 | AJ44: =SUM(X44:AI44) -> 0
D45: Performance Rate | E45: % | G45: =IFERROR(G44/G43,0) -> 0 | H45: =IFERROR(H44/H43,0) -> 0 | I45: =IFERROR(I44/I43,0) -> 0 | J45: =IFERROR(J44/J43,0) -> 0 | K45: =IFERROR(K44/K43,0) -> 0 | L45: =IFERROR(L44/L43,0) -> 0 | M45: =IFERROR(M44/M43,0) -> 0 | N45: =IFERROR(N44/N43,0) -> 0 | ... S45: =IFERROR(S44/S43,0) -> 0 | U45: Performance Rate | V45: % | X45: =IFERROR(X44/X43,0) -> 0 | Y45: =IFERROR(Y44/Y43,0) -> 0 | Z45: =IFERROR(Z44/Z43,0) -> 0 | AA45: =IFERROR(AA44/AA43,0) -> 0 | AB45: =IFERROR(AB44/AB43,0) -> 0 | AC45: =IFERROR(AC44/AC43,0) -> 0 | AD45: =IFERROR(AD44/AD43,0) -> 0 | AE45: =IFERROR(AE44/AE43,0) -> 0 | ... AJ45: =IFERROR(AJ44/AJ43,0) -> 0
D47: Quality | U47: Quality
D48: Total Output | E48: kgs | K48: =PRODUCTION!N996 | L48: =PRODUCTION!O996 | S48: =SUM(G48:R48) -> 0 | U48: Total Output | V48: kgs | AB48: =PRODUCTION!N996 | AC48: =PRODUCTION!O996 | AJ48: =SUM(X48:AI48) -> 0
D49: Internal Rejection | E49: kgs | K49: =PRODUCTION!N997 | L49: =PRODUCTION!O997 | S49: =SUM(G49:R49) -> 0 | U49: Internal Rejection | V49: kgs | AB49: =PRODUCTION!N997 | AC49: =PRODUCTION!O997 | AJ49: =SUM(X49:AI49) -> 0
D50: Waste | E50: kgs | K50: =1450*9+2366*1 -> 15416 | L50: =1450*1+2366*1 -> 3816 | S50: =SUM(G50:R50) -> 19232 | T50: from QA data | U50: Waste | V50: kgs | AB50: =1450*9+2366*1 -> 15416 | AC50: =1450*1+2366*1 -> 3816 | AJ50: =SUM(X50:AI50) -> 19232 | AK50: from QA data
D51: Quality Rate | E51: % | G51: =IFERROR(G48/SUM(G48:G50),0) -> 0 | H51: =IFERROR(H48/SUM(H48:H50),0) -> 0 | I51: =IFERROR(I48/SUM(I48:I50),0) -> 0 | J51: =IFERROR(J48/SUM(J48:J50),0) -> 0 | K51: =IFERROR(K48/SUM(K48:K50),0) -> 0 | L51: =IFERROR(L48/SUM(L48:L50),0) -> 0 | M51: =IFERROR(M48/SUM(M48:M50),0) -> 0 | N51: =IFERROR(N48/SUM(N48:N50),0) -> 0 | ... S51: =IFERROR(S48/SUM(S48:S50),0) -> 0 | U51: Quality Rate | V51: % | X51: =IFERROR(X48/SUM(X48:X50),0) -> 0 | Y51: =IFERROR(Y48/SUM(Y48:Y50),0) -> 0 | Z51: =IFERROR(Z48/SUM(Z48:Z50),0) -> 0 | AA51: =IFERROR(AA48/SUM(AA48:AA50),0) -> 0 | AB51: =IFERROR(AB48/SUM(AB48:AB50),0) -> 0 | AC51: =IFERROR(AC48/SUM(AC48:AC50),0) -> 0 | AD51: =IFERROR(AD48/SUM(AD48:AD50),0) -> 0 | AE51: =IFERROR(AE48/SUM(AE48:AE50),0) -> 0 | ... AJ51: =IFERROR(AJ48/SUM(AJ48:AJ50),0) -> 0
D53: TOTAL OEE | E53: % | G53: =IFERROR(G40*G45*G51,0) -> 0 | H53: =IFERROR(H40*H45*H51,0) -> 0 | I53: =IFERROR(I40*I45*I51,0) -> 0 | J53: =IFERROR(J40*J45*J51,0) -> 0 | K53: =IFERROR(K40*K45*K51,0) -> 0 | L53: =IFERROR(L40*L45*L51,0) -> 0 | M53: =IFERROR(M40*M45*M51,0) -> 0 | N53: =IFERROR(N40*N45*N51,0) -> 0 | ... S53: =IFERROR(S40*S45*S51,0) -> 0 | U53: TOTAL OEE | V53: % | X53: =IFERROR(X40*X45*X51,0) -> 0 | Y53: =IFERROR(Y40*Y45*Y51,0) -> 0 | Z53: =IFERROR(Z40*Z45*Z51,0) -> 0 | AA53: =IFERROR(AA40*AA45*AA51,0) -> 0 | AB53: =IFERROR(AB40*AB45*AB51,0) -> 0 | AC53: =IFERROR(AC40*AC45*AC51,0) -> 0 | AD53: =IFERROR(AD40*AD45*AD51,0) -> 0 | AE53: =IFERROR(AE40*AE45*AE51,0) -> 0 | ... AJ53: =IFERROR(AJ40*AJ45*AJ51,0) -> 0
D57: 2025 KPI - Actuals | E57: UoM | G57: Jan | H57: Feb | I57: Mar | J57: Apr | K57: May | L57: Jun | M57: Jul | N57: Aug | O57: Sep | P57: Oct | Q57: Nov | R57: Dec | S57: YTD
D58: OEE - LINE 01 FILLING
D59: Availability
D60: Planned Run Time | E60: hr | L60: =(23*24)*4 -> 2208 | S60: =SUM(G60:R60) -> 2208
D61: Actual Run Time | E61: hr | L61: =40186/60 -> 669.76667 | S61: =SUM(G61:R61) -> 669.76667 | T61: 132992
D62: Availability Rate | E62: % | G62: =IFERROR(G61/G60,0) -> 0 | H62: =IFERROR(H61/H60,0) -> 0 | I62: =IFERROR(I61/I60,0) -> 0 | J62: =IFERROR(J61/J60,0) -> 0 | K62: =IFERROR(K61/K60,0) -> 0 | L62: =IFERROR(L61/L60,0) -> 0.30333635 | M62: =IFERROR(M61/M60,0) -> 0 | N62: =IFERROR(N61/N60,0) -> 0 | ... S62: =IFERROR(S61/S60,0) -> 0.30333635 | T62: =T61/60 -> 2216.5333
T63: =T62/4 -> 554.13333
D64: Performance
D65: Theoretical Output | E65: kgs | L65: =T67 -> 0 | S65: =SUM(G65:R65) -> 0
D66: Actual Output | E66: kgs | K66: =PRODUCTION!N1174 | L66: =PRODUCTION!O1174 | S66: =SUM(G66:R66) -> 0 | T66: =L66/L61 -> 0
D67: Performance Rate | E67: % | G67: =IFERROR(G66/G65,0) -> 0 | H67: =IFERROR(H66/H65,0) -> 0 | I67: =IFERROR(I66/I65,0) -> 0 | J67: =IFERROR(J66/J65,0) -> 0 | K67: =IFERROR(K66/K65,0) -> 0 | L67: =IFERROR(L66/L65,0) -> 0 | M67: =IFERROR(M66/M65,0) -> 0 | N67: =IFERROR(N66/N65,0) -> 0 | ... S67: =IFERROR(S66/S65,0) -> 0 | T67: =((T66*23)*24)*4 -> 0
D69: Quality
D70: Total Output | E70: kgs | K70: =PRODUCTION!N1174 | L70: =PRODUCTION!O1174 | S70: =SUM(G70:R70) -> 0
D71: Internal Rejection | E71: kgs | K71: =PRODUCTION!N1019 | L71: =PRODUCTION!O1019 | S71: =SUM(G71:R71) -> 0
D72: Waste | E72: kgs | S72: =SUM(G72:R72) -> 0
D73: Quality Rate | E73: % | G73: =IFERROR(G70/SUM(G70:G72),0) -> 0 | H73: =IFERROR(H70/SUM(H70:H72),0) -> 0 | I73: =IFERROR(I70/SUM(I70:I72),0) -> 0 | J73: =IFERROR(J70/SUM(J70:J72),0) -> 0 | K73: =IFERROR(K70/SUM(K70:K72),0) -> 0 | L73: =IFERROR(L70/SUM(L70:L72),0) -> 0 | M73: =IFERROR(M70/SUM(M70:M72),0) -> 0 | N73: =IFERROR(N70/SUM(N70:N72),0) -> 0 | ... S73: =IFERROR(S70/SUM(S70:S72),0) -> 0
D75: TOTAL OEE | E75: % | G75: =IFERROR(G62*G67*G73,0) -> 0 | H75: =IFERROR(H62*H67*H73,0) -> 0 | I75: =IFERROR(I62*I67*I73,0) -> 0 | J75: =IFERROR(J62*J67*J73,0) -> 0 | K75: =IFERROR(K62*K67*K73,0) -> 0 | L75: =IFERROR(L62*L67*L73,0) -> 0 | M75: =IFERROR(M62*M67*M73,0) -> 0 | N75: =IFERROR(N62*N67*N73,0) -> 0 | ... S75: =IFERROR(S62*S67*S73,0) -> 0
K78: 27
G79: 24 | H79: 24 | I79: 24 | J79: 16 | K79: 24
J80: =6*16 -> 96
J81: =J80/24 -> 4

Sheet Sheet1
B1: CONVERSION COST
C2: OCT | D2: NOV | H2: OCT | I2: NOV
B3: Conversion Cost (SC only) | C3: 10.93 | D3: 9.9 | G3: Change Over Time | H3: 0.02608477 | I3: 0.026832007
B4: Conversion Cost (Overall) | C4: 18.58 | D4: 15.56 | G4: Meeting | H4: 0.0051507471 | I4: 0.0023436472
G5: Sanitation Time | H5: 0.012388871 | I5: 0.0065222646
G6: Start-up Time/Setup | H6: 0.025931527 | I6: 0.015852052
G7: Testing Time | H7: 0.0086879803 | I7: 0.00099962013
G8: Breaktime | H8: 0.017009963 | I8: 0.012264247
G9: Breakdown | H9: 0.0059258885 | I9: 0.0013477605
G10: Idle time | H10: 0.08793465 | I10: 0.048100302
G11: Preventive Maintenance | H11: 0 | I11: 0
B17: FILL RATE
C18: OCT | D18: NOV
B19: Achievement (Value) | C19: 0.71045649 | D19: 0.98166348
B31: Capital Expenditures
C32: OCT | D32: NOV
B33: Actual | C33: =2042360/1000 -> 2042.36 | D33: =2033330/1000 -> 2033.33
B34: Budget | C34: =1946800/1000 -> 1946.8 | D34: =1966800/1000 -> 1966.8
B51: Operational Cost
C52: OCT | D52: NOV
B53: Actual | C53: =13498890.24/1000 -> 13498.89 | D53: =15879974.2/1000 -> 15879.974
B54: Budget | C54: =16189431.264843/1000 -> 16189.431 | D54: =16210987.8286226/1000 -> 16210.988

Sheet BUSINESS GOALS
A1: BUSINESS GOALS
B3: FINANCIALS | F3: PIC
B4: COGS | C4: PERFORMANCE VS TARGET | D4: KPI | E4: Ms. Amor | F4: MFG/PROC/ENG'G
B5: CONVERSION COST | C5: PERFORMANCE VS TARGET | D5: KPI | E5: Ms. Amor | F5: MFG/ENG'G
B6: RMPM COST | C6: PERFORMANCE VS TARGET | D6: KPI | E6: Ms. Amor | F6: PROC
B8: FILL RATE | C8: FILL RATE (SC FILLRATE) | D8: KPI | E8: 0.9925 | F8: PLAN/LOGS
B10: OTIF | C10: OTIF PER PESO VALUE | D10: KPI | E10: 0.95 | F10: PLAN/LOGS
B12: KG/MH | C12: PERFORMANCE VS TARGET | D12: KPI | E12: Ms. Amor | F12: MFG/ENG'G
B14: CUSTOMER COMPLAINT | C14: DUE TO PRODUCT QUALITY | D14: KPI | E14: Ms. Liway | F14: MFG/LOGS/ENG'G
B16: Develop Succession Plan | C16: Learning and Growth | D16: KPI | E16: Exit FY vs Plan (on identified critical position) | F16: OVP

Sheet OPERATIONAL OBECTIVE
A1: OPERATIONAL OBJECTIVES
B3: PRIORITY | C3: LESS PRIORITY
A4: PRODUCTION | L4: CAPACITY STATEMENT | O4: (u/wk)
B5: CHANGE OVER >>> AVE HOURS | D5: KPI
B6: CHANGE OVER >>> PLAN vs ACTUAL (FREQ ACTUAL AND PLAN TIME vs ACTUAL TIME) | D6: KPI | L6: Eqpt Availability | N6: eff eng'g | O6: hrs/wk
B7: INTERNAL REJECTION | D7: KPI | E7: BONUS BACK FOR ALL HOLD IF NO REWORK / NO CONCESSION | L7: Run Rate | N7: raw uph (eff) | O7: u/wk
B8: WASTE (PROCESS INHERENT) | D8: KPI | E8: WASTE PERCENTAGE | L8: Productive time | N8: eff. Mfg | O8: hrs/wk
B9: Material Usage (Yield Rate) (BACKFLUSH + ADJUSMENT) | D9: KPI | L9: Yield | N9: final | O9: % out/in
B10: >>> MONITORING OF ADJUSMENT | D10: MONITORING | N10: ____________ | O10: u/wk
B11: OEE (PER LINE) | C11: OEE (PER MACHINE) - PRODUCTIVE TIME/AVAILABILITY | D11: KPI
B12: ELOR (PER LINE) | C12: EFFECTIVE LINE OPERATING RATE (PER MACHINE) | D12: KPI | E12: AVAILABILITY = LESS PLANNED DOWNTIME QUALITY = GOOD / OUTPUT (GOOD+REJECT) RATE = ACTUAL OUTPUT / THEORETICAL OUTPUT
B13: ELUR (PER LINE) | C13: EFFECTIVE LINE UTILIZATION RATE (PER MACHINE) | D13: KPI | E13: AVAILABILITY = 24 HOURS QUALITY = GOOD / OUTPUT (GOOD+REJECT) RATE = ACTUAL OUTPUT / THEORETICAL OUTPUT
B14: COMPLIANCE TO SCHEDULE | D14: KPI | E14: WEEKLY COMPLIANCE - PRODUCTION ORDER (VOLUME IN KGS)
A17: OVERALL
C18: NUMBER OF REGULAR | D18: MONITORING
C19: NUMBER OF NON-REGULAR | D19: MONITORING
C21: CUSTOMER COMPLAINT | D21: MONITORING | E21: COMPLAINT OTHER THAN PRODUCT FEATURE
C22: Hazard Identified | D22: MONITORING
C23: Safety Violation | D23: MONITORING
C25: Retention Rate | D25: MONITORING | E25: Current vs Plan
C27: MANPOWER PLAN | D27: MONITORING
A29: ENGINEERING
B30: FUEL | C30: ACTUAL VS PLAN | D30: KPI | E30: WITH ALLOCATION PER BUILDING | F30: Ms. Amor
B31: WATER | C31: ACTUAL VS PLAN | D31: KPI | E31: WITH ALLOCATION PER BUILDING | F31: Ms. Amor
B32: ELECTRICITY | C32: ACTUAL VS PLAN | D32: KPI | E32: WITH ALLOCATION PER BUILDING | F32: Ms. Amor
B33: FACILITY MAINTENANCE | C33: ACTUAL VS PLAN | D33: KPI | E33: WITH ALLOCATION PER BUILDING | F33: Ms. Amor
A35: PLANNING
B36: DIO (based on P&L COGS)
B37: LID
C38: LRA WAREHOUSE | D38: MONITORING
C39: WAREHOUSE UTILIZATION | D39: MONITORING
C40: INVENTORY DISTRIBUTION | D40: MONITORING | E40: CORE/EMERGING/NTE/EXPIRED/FOR WRITE OFF
C41: INVENTORY ACCURACY | D41: MONITORING
C42: FORECAST ACCURACY | D42: MONITORING
A45: WHSE | B45: OTIF PER PESO VALUE | D45: KPI | E45: OTIF PER LINE ITEM
B46: FILL RATE (SC FILLRATE) | D46: KPI
C47: FILL RATE (CORP FILLRATE) | D47: MONITORING
C48: FILL RATE (CORP FILLRATE) - CORE | D48: MONITORING
C49: FILL RATE (CORP FILLRATE) - EMERGING | D49: MONITORING
C50: BREAKDOWN OF NON-OTIF | D50: MONITORING
C51: STOCK OUTS | D51: MONITORING
C52: OTDL | D52: MONITORING
B54: FREIGHT COST - PER KILO | D54: KPI
C55: ISSUANCE TURNAROUND TIME (INBOUND) | D55: MONITORING
C56: RECEIVING TURNAROUND TIME | D56: MONITORING
C57: FREIGHT COST UTILIZATION IMPORTATION | D57: MONITORING
A59: PROC | B59: SAVINGS | D59: KPI
B60: P.O CONFORMANCE | D60: KPI
C61: RM/PM PRICE ANALYSIS | D61: MONITORING
